Workbook

Sheet Master - Brand Overview
A2: Brand Name | B2: Website URL | C2: Category | D2: Category | E2: Total Active Ads | F2: Video Ads Count | G2: Image Ads Count | H2: Image Ad Ratio | I2: Pass 35% Filter | J2: Landing pages | K2: Số lượng ads/prelanding chạy ads | L2: Số lượng page Blog | M2: Traffic | N2: %Meta | O2: AOV | P2: % Prelander | Q2: Est Revenue | R2: Ad Efficiency | S2: Checkout champ | T2: Note
A3: GNC | B3: gnc.com | C3: General Supplements | D3: US | E3: 2300 | F3: 730 | G3: 1500 | H3: =G3/E3 -> 0.65217391 | I3: =IF(AND(H3>=30%, E3>100), "Pass", "Fail") -> Pass | J3: View details | K3: 0 | L3: 0 | M3: =2.846*1000000 -> 2846000 | N3: 0.502 | O3: 68 | P3: =K3/G3 -> 0 | Q3: =O3*2.5%*(M3*N3) -> 2428776.4 | R3: =Q3/E3 -> 1055.9897 | S3: FALSE
A4: Tryrosabella | B4: get.tryrosabella.com | C4: Women's Wellness | D4: US | E4: 5500 | F4: 2400 | G4: 3100 | H4: =G4/E4 -> 0.56363636 | I4: =IF(AND(H4>=30%, E4>100), "Pass", "Fail") -> Pass | J4: View details | K4: 180 | L4: 0 | M4: =2.059*1000000 -> 2059000 | N4: 0.9737 | O4: 99.95 | P4: =K4/G4 -> 0.058064516 | Q4: =O4*2.5%*(M4*N4) -> 5009614.7 | R4: =Q4/E4 -> 910.83903 | S4: TRUE
A5: Drink AG1 | B5: drinkag1.com | C5: Greens/Multivitamin | D5: US | E5: 360 | F5: 160 | G5: 200 | H5: =G5/E5 -> 0.55555556 | I5: =IF(AND(H5>=50%, E5>100), "Pass", "Fail") -> Pass | K5: 1 | M5: 2.171M | N5: 0.182
A6: Rejuvacare | B6: rejuvacare.com | C6: Health & Wellness | D6: US | E6: 1600 | F6: 790 | G6: 800 | H6: =G6/E6 -> 0.5 | I6: =IF(AND(H6>=30%, E6>100), "Pass", "Fail") -> Pass | J6: View details | K6: 180 | L6: 26 | M6: =1.668*1000000 -> 1668000 | N6: 0.99 | O6: 84.43 | P6: =K6/G6 -> 0.225 | Q6: =O6*2.5%*(M6*N6) -> 3485523.7 | R6: =Q6/E6 -> 2178.4523 | S6: TRUE
A7: Happy Mammoth | B7: happymammoth.com | C7: Wellness | D7: UK | E7: 2500 | F7: 560 | G7: 1900 | H7: =G7/E7 -> 0.76 | I7: =IF(AND(H7>=30%, E7>100), "Pass", "Fail") -> Pass | J7: View details | K7: 172 | L7: 271 | M7: =1.319*1000000 -> 1319000 | N7: 0.8377 | O7: 68.08 | P7: =K7/G7 -> 0.090526316 | Q7: =O7*2.5%*(M7*N7) -> 1880584.6 | R7: =Q7/E7 -> 752.23383 | S7: FALSE | T7: Shopify
A8: Marmens | B8: mengotomars.com | C8: MEN's Health | D8: US | E8: 760 | F8: 450 | G8: 310 | H8: =G8/E8 -> 0.40789474 | I8: =IF(AND(H8>=30%, E8>100), "Pass", "Fail") -> Pass | J8: View details | K8: 68 | L8: 4 | M8: =1.088*1000000 -> 1088000 | N8: 0.753 | O8: 82 | P8: =K8/G8 -> 0.21935484 | Q8: =O8*2.5%*(M8*N8) -> 1679491.2 | R8: =Q8/E8 -> 2209.8568 | S8: FALSE | T8: Shopify
A9: Froya | B9: froyaorganics.com | C9: Women's Wellness | D9: US | E9: 6100 | F9: 1500 | G9: 4600 | H9: =G9/E9 -> 0.75409836 | I9: =IF(AND(H9>=30%, E9>100), "Pass", "Fail") -> Pass | J9: View details | K9: 350 | L9: 68 | M9: 796408 | N9: 0.8985 | O9: 46.08 | P9: =K9/G9 -> 0.076086957 | Q9: =O9*2.5%*(M9*N9) -> 824339.62 | R9: =Q9/E9 -> 135.13764 | S9: FALSE
A10: Nutrafol | B10: nutrafol.com | C10: Hair Health | D10: US | E10: 1500 | F10: 240 | G10: 1200 | H10: =G10/E10 -> 0.8 | I10: =IF(AND(H10>=50%, E10>100), "Pass", "Fail") -> Pass | M10: 2.221M | N10: 0.273
A11: Hone Health | B11: honehealth.com | C11: Men's Health | D11: US | E11: 240 | F11: 170 | G11: 88 | H11: =G11/E11 -> 0.36666667 | I11: =IF(AND(H11>=30%, E11>100), "Pass", "Fail") -> Pass | J11: View details | K11: 0 | L11: 1008 | M11: 789471 | N11: 0.6984 | O11: 179 | P11: =K11/G11 -> 0 | Q11: =O11*2.5%*(M11*N11) -> 2467365.3 | R11: =Q11/E11 -> 10280.689 | S11: FALSE
A12: Ellaola | B12: ellaola.com | C12: Health/Supplement | D12: US | E12: 4400 | F12: 2700 | G12: 1700 | H12: =G12/E12 -> 0.38636364 | I12: =IF(AND(H12>=30%, E12>100), "Pass", "Fail") -> Pass | J12: View details | K12: 0 | L12: 135 | M12: 699360 | N12: 0.8118 | O12: 92 | P12: =K12/G12 -> 0 | Q12: =O12*2.5%*(M12*N12) -> 1305803 | R12: =Q12/E12 -> 296.77342 | S12: FALSE
A13: Naked Nutrition | B13: nakednutrition.com | C13: Protein/Sports Nutrition | D13: US | E13: 730 | F13: 310 | G13: 420 | H13: =G13/E13 -> 0.57534247 | I13: =IF(AND(H13>=50%, E13>100), "Pass", "Fail") -> Pass | M13: 673291 | N13: 0.1044
A14: Luxeresearchlab | B14: luxeresearchlab.com | C14: Women's Wellness | D14: US | E14: 310 | F14: 170 | G14: 140 | H14: =G14/E14 -> 0.4516129 | I14: =IF(AND(H14>=30%, E14>100), "Pass", "Fail") -> Pass | J14: View details | K14: 74 | L14: 1 | M14: 698267 | N14: 0.932 | O14: 54 | P14: =K14/G14 -> 0.52857143 | Q14: =O14*2.5%*(M14*N14) -> 878559.54 | R14: =Q14/E14 -> 2834.063 | S14: FALSE
A15: Bucked Up | B15: buckedup.com | C15: Sports Nutrition | D15: US | E15: 410 | F15: 150 | G15: 250 | H15: =G15/E15 -> 0.6097561 | I15: =IF(AND(H15>=30%, E15>100), "Pass", "Fail") -> Pass | J15: View details | K15: 0 | L15: 0 | M15: 607745 | N15: 0.8749 | O15: 88 | P15: =K15/G15 -> 0 | Q15: =O15*2.5%*(M15*N15) -> 1169775.4 | R15: =Q15/E15 -> 2853.1108 | S15: FALSE
A16: BulkSupplements | B16: bulksupplements.com | C16: Protein/Sports | D16: US | E16: 190 | F16: 14 | G16: 170 | H16: =G16/E16 -> 0.89473684 | I16: =IF(AND(H16>=50%, E16>100), "Pass", "Fail") -> Pass | M16: 834650 | N16: 0.065
A17: Olavita | B17: try.olavita.co | C17: Women's Wellness | D17: US | E17: 300 | F17: 82 | G17: 210 | H17: =G17/E17 -> 0.7 | I17: =IF(AND(H17>=30%, E17>100), "Pass", "Fail") -> Pass | J17: View details | K17: 60 | L17: 0 | M17: 604931 | N17: 0.9675 | O17: 99.95 | P17: =K17/G17 -> 0.28571429 | Q17: =O17*2.5%*(M17*N17) -> 1462445.3 | R17: =Q17/E17 -> 4874.8176 | S17: TRUE
A18: MuscleFood | B18: musclefood.com | C18: Health/Supplement | D18: UK | E18: 230 | F18: 110 | G18: 110 | H18: =G18/E18 -> 0.47826087 | I18: =IF(AND(H18>=30%, E18>100), "Pass", "Fail") -> Pass | J18: View details | K18: 0 | L18: 53 | M18: 473606 | N18: 0.986 | O18: 62 | P18: =K18/G18 -> 0 | Q18: =O18*2.5%*(M18*N18) -> 723812.05 | R18: =Q18/E18 -> 3147.0089 | S18: FALSE
A19: Alpha Lion | B19: alphalion.com | C19: Sports Nutrition | D19: US | E19: 280 | F19: 160 | G19: 110 | H19: =G19/E19 -> 0.39285714 | I19: =IF(AND(H19>=30%, E19>100), "Pass", "Fail") -> Pass | J19: View details | K19: 7 | L19: 23 | M19: 393544 | N19: 0.863 | O19: 85 | P19: =K19/G19 -> 0.063636364 | Q19: =O19*2.5%*(M19*N19) -> 721710.5 | R19: =Q19/E19 -> 2577.5375 | S19: FALSE
A20: Huel | B20: huel.com | C20: Meal Replacement | D20: US | E20: 810 | F20: 270 | G20: 500 | H20: =G20/E20 -> 0.61728395 | I20: =IF(AND(H20>=50%, E20>100), "Pass", "Fail") -> Pass | M20: 2.106M | N20: 0.258
A21: Primal King | B21: primalviking.com | C21: MEN's Health | D21: US | E21: 840 | F21: 160 | G21: 670 | H21: =G21/E21 -> 0.79761905 | I21: =IF(AND(H21>=30%, E21>100), "Pass", "Fail") -> Pass | J21: View details | K21: 40 | L21: 1 | M21: 361507 | N21: 0.8348 | O21: 84.63 | P21: =K21/G21 -> 0.059701493 | Q21: =O21*2.5%*(M21*N21) -> 638503.82 | R21: =Q21/E21 -> 760.1236 | S21: FALSE
A22: InnoSupps | B22: innosupps.com | C22: Health/Weight Loss | D22: US | E22: 420 | F22: 150 | G22: 270 | H22: =G22/E22 -> 0.64285714 | I22: =IF(AND(H22>=30%, E22>100), "Pass", "Fail") -> Pass | J22: View details | K22: {=XLOOKUP("*" & B22 & "*", Prelander!$B$2:$B$55, Prelander!$D$2:$D$55, "Không tìm thấy", 2)} -> 5 | L22: 41 | M22: 326601 | N22: 1 | O22: 67.08 | P22: =K22/G22 -> 0.018518519 | Q22: =O22*2.5%*(M22*N22) -> 547709.88 | R22: =Q22/E22 -> 1304.0711 | S22: FALSE
A23: Ploise | B23: https://ploise.com | C23: Personal Care | D23: US | E23: 500 | F23: 130 | G23: 280 | H23: =G23/E23 -> 0.56 | I23: =IF(AND(H23>=30%, E23>100), "Pass", "Fail") -> Pass | J23: View details | K23: 97 | L23: 0 | M23: 309389 | N23: 0.9975 | O23: 93.87 | P23: =K23/G23 -> 0.34642857 | Q23: =O23*2.5%*(M23*N23) -> 724243.49 | R23: =Q23/E23 -> 1448.487 | S23: FALSE | T23: NextJs
A24: Equip Foods | B24: equipfoods.com | C24: Beef Protein | D24: US | E24: 750 | F24: 190 | G24: 530 | H24: =G24/E24 -> 0.70666667 | I24: =IF(AND(H24>=30%, E24>100), "Pass", "Fail") -> Pass | J24: View details | K24: 0 | L24: 65 | M24: 283452 | N24: 0.7819 | O24: 98 | P24: =K24/G24 -> 0 | Q24: =O24*2.5%*(M24*N24) -> 542996.24 | R24: =Q24/E24 -> 723.99499 | S24: FALSE
A25: Ancestral Supplements | B25: ancestralsupplements.com | C25: Sports Nutrition | D25: US | E25: 380 | F25: 190 | G25: 180 | H25: =G25/E25 -> 0.47368421 | I25: =IF(AND(H25>=30%, E25>100), "Pass", "Fail") -> Pass | J25: View details | K25: 0 | L25: 216 | M25: 264545 | N25: 0.953 | O25: 92 | P25: =K25/G25 -> 0 | Q25: =O25*2.5%*(M25*N25) -> 579856.19 | R25: =Q25/E25 -> 1525.9373 | S25: FALSE
A26: Myoro | B26: myoro.co | C26: MEN's Health | D26: US | E26: 160 | F26: 78 | G26: 82 | H26: =G26/E26 -> 0.5125 | I26: =IF(AND(H26>=30%, E26>100), "Pass", "Fail") -> Pass | J26: View details | K26: 48 | L26: 1 | M26: 257226 | N26: 0.7411 | O26: 95 | P26: =K26/G26 -> 0.58536585 | Q26: =O26*2.5%*(M26*N26) -> 452746.7 | R26: =Q26/E26 -> 2829.6669 | S26: FALSE
A27: AG1 | B27: drinkag1.com | C27: Greens/Wellness | D27: US | E27: 360 | F27: 160 | G27: 200 | H27: =G27/E27 -> 0.55555556 | I27: =IF(AND(H27>=50%, E27>100), "Pass", "Fail") -> Pass | M27: 2.171M | N27: 0.182
A28: Fiera Cosmetic | B28: fieracosmetics.com | C28: Women's Wellness | D28: US | E28: 150 | F28: 54 | G28: 92 | H28: =G28/E28 -> 0.61333333 | I28: =IF(AND(H28>=30%, E28>100), "Pass", "Fail") -> Pass | J28: View details | K28: 20 | L28: 322 | M28: 243028 | N28: 1 | O28: 78 | P28: =K28/G28 -> 0.2173913 | Q28: =O28*2.5%*(M28*N28) -> 473904.6 | R28: =Q28/E28 -> 3159.364 | S28: FALSE
A29: Orgain | B29: orgain.com | C29: Protein/Organic | D29: US | E29: 190 | F29: 85 | G29: 100 | H29: =G29/E29 -> 0.52631579 | I29: =IF(AND(H29>=50%, E29>100), "Pass", "Fail") -> Pass | M29: 253379 | N29: 0.1952
A30: REDCON1 | B30: redcon1.com | C30: Sports Nutrition | D30: US | E30: 110 | F30: 22 | G30: 80 | H30: =G30/E30 -> 0.72727273 | I30: =IF(AND(H30>=50%, E30>100), "Pass", "Fail") -> Pass | M30: 111321 | N30: 0.2304
A31: Pendulum | B31: pendulumlife.com | C31: Gut Health/Probiotics | D31: US | E31: 210 | F31: 110 | G31: 76 | H31: =G31/E31 -> 0.36190476 | I31: =IF(AND(H31>=30%, E31>100), "Pass", "Fail") -> Pass | J31: View details | K31: 0 | L31: 236 | M31: 237589 | N31: 0.842 | O31: 120 | P31: =K31/G31 -> 0 | Q31: =O31*2.5%*(M31*N31) -> 600149.81 | R31: =Q31/E31 -> 2857.8563 | S31: FALSE
A32: The BB Co | B32: thebbco.com | C32: Collagen/Beauty | D32: US | E32: 7600 | F32: 4700 | G32: 2700 | H32: =G32/E32 -> 0.35526316 | I32: =IF(AND(H32>=30%, E32>100), "Pass", "Fail") -> Pass | J32: View details | K32: {=XLOOKUP("*" & B32 & "*", Prelander!$B$2:$B$55, Prelander!$D$2:$D$55, "Không tìm thấy", 2)} -> 221 | L32: 234 | M32: 221871 | N32: 0.9325 | O32: 82 | P32: =K32/G32 -> 0.081851852 | Q32: =O32*2.5%*(M32*N32) -> 424134.15 | R32: =Q32/E32 -> 55.807125 | S32: FALSE
A33: Norse Organics | B33: norseorganics.co | C33: Women's Wellness | D33: US | E33: 910 | F33: 370 | G33: 510 | H33: =G33/E33 -> 0.56043956 | I33: =IF(AND(H33>=30%, E33>100), "Pass", "Fail") -> Pass | J33: View details | K33: 75 | L33: 9 | M33: 163693 | N33: 0.72 | O33: 86 | P33: =K33/G33 -> 0.14705882 | Q33: =O33*2.5%*(M33*N33) -> 253396.76 | R33: =Q33/E33 -> 278.45798 | S33: FALSE
A34: Balmbare | B34: balmbare.com | C34: Women's Wellness | D34: US | E34: 1200 | F34: 220 | G34: 1000 | H34: =G34/E34 -> 0.83333333 | I34: =IF(AND(H34>=30%, E34>100), "Pass", "Fail") -> Pass | J34: View details | K34: 0 | L34: 0 | M34: 163458 | N34: 0.9437 | O34: 55 | P34: =K34/G34 -> 0 | Q34: =O34*2.5%*(M34*N34) -> 212101.06 | R34: =Q34/E34 -> 176.75088 | S34: FALSE
A35: Thorne | B35: thorne.com | C35: Health/Supplements | D35: US | E35: 16000 | F35: 8800 | G35: 6900 | H35: =G35/E35 -> 0.43125 | I35: =IF(AND(H35>=30%, E35>100), "Pass", "Fail") -> Pass | J35: View details | K35: 0 | L35: 0 | M35: =2.065*1000000 -> 2065000 | N35: 0.465 | O35: 95 | P35: =K35/G35 -> 0 | Q35: =O35*2.5%*(M35*N35) -> 2280534.4 | R35: =Q35/E35 -> 142.5334
A36: Truvani | B36: truvani.com | C36: Protein/Wellness | D36: US | E36: 470 | F36: 370 | G36: 250 | H36: =G36/E36 -> 0.53191489 | I36: =IF(AND(H36>=30%, E36>100), "Pass", "Fail") -> Pass | J36: View details | K36: 0 | L36: 0 | M36: 148684 | N36: 0.8547 | O36: 57 | P36: =K36/G36 -> 0 | Q36: =O36*2.5%*(M36*N36) -> 181089.31 | R36: =Q36/E36 -> 385.2964 | S36: FALSE
A37: Naked Nutrition | B37: nakednutrition.com | C37: Protein/Supplements | D37: US | E37: 730 | F37: 310 | G37: 420 | H37: =G37/E37 -> 0.57534247 | I37: =IF(AND(H37>=50%, E37>100), "Pass", "Fail") -> Pass | M37: 673291 | N37: 0.1044
A38: True Protein | B38: trueprotein.com.au | C38: Protein/Supplements | D38: AU | E38: 560 | F38: 250 | G38: 290 | H38: =G38/E38 -> 0.51785714 | I38: =IF(AND(H38>=30%, E38>100), "Pass", "Fail") -> Pass | J38: View details | K38: 5 | L38: 935 | M38: 147912 | N38: 0.6751 | O38: 75 | P38: =K38/G38 -> 0.017241379 | Q38: =O38*2.5%*(M38*N38) -> 187228.86 | R38: =Q38/E38 -> 334.33725 | S38: FALSE
A39: HealthKart | B39: healthkart.com | C39: Supplements/Health | D39: IN | E39: 320 | F39: 210 | G39: 110 | H39: =G39/E39 -> 0.34375 | I39: =IF(AND(H39>=30%, E39>100), "Pass", "Fail") -> Pass | J39: View details | K39: 0 | M39: 1.246M | N39: 0.1802 | O39: 28
A40: Lonvera | B40: lonvera.com | C40: Health/Supplement | D40: US | E40: 1400 | F40: 770 | G40: 600 | H40: =G40/E40 -> 0.42857143 | I40: =IF(AND(H40>=30%, E40>100), "Pass", "Fail") -> Pass | J40: View details | K40: {=XLOOKUP("*" & B40 & "*", Prelander!$B$2:$B$55, Prelander!$D$2:$D$55, "Không tìm thấy", 2)} -> 5 | L40: 1 | M40: 110817 | N40: 1 | O40: 78 | P40: =K40/G40 -> 0.0083333333 | Q40: =O40*2.5%*(M40*N40) -> 216093.15 | R40: =Q40/E40 -> 154.35225 | S40: FALSE
A41: Rejuvia | B41: rejuvia.co | C41: Health & Wellness | D41: US | E41: 540 | F41: 130 | G41: 410 | H41: =G41/E41 -> 0.75925926 | I41: =IF(AND(H41>=30%, E41>100), "Pass", "Fail") -> Pass | J41: View details | K41: {=XLOOKUP("*" & B41 & "*", Prelander!$B$2:$B$55, Prelander!$D$2:$D$55, "Không tìm thấy", 2)} -> 41 | L41: 0 | M41: 99129 | N41: 0.99 | O41: 88 | P41: =K41/G41 -> 0.1 | Q41: =O41*2.5%*(M41*N41) -> 215902.96 | R41: =Q41/E41 -> 399.8203 | S41: FALSE
A42: 1st Phorm | B42: 1stphorm.com | C42: Sports Nutrition | D42: US | E42: 260 | F42: 160 | G42: 86 | H42: =G42/E42 -> 0.33076923 | I42: =IF(AND(H42>=30%, E42>100), "Pass", "Fail") -> Pass | J42: View details | K42: 0 | M42: 444530 | N42: 0.3808 | O42: 85
A43: Zenith | B43: taste-zenith.com | C43: Retailer/Supplement | D43: US | E43: 190 | F43: 47 | G43: 130 | H43: =G43/E43 -> 0.68421053 | I43: =IF(AND(H43>=30%, E43>100), "Pass", "Fail") -> Pass | J43: View details | K43: 13 | M43: 82495 | N43: 1 | O43: 45 | P43: =K43/G43 -> 0.1 | Q43: =O43*2.5%*(M43*N43) -> 92806.875 | R43: =Q43/E43 -> 488.45724 | S43: FALSE
A44: Rejuveen | B44: rejuveen.com | C44: Women's Wellness | D44: US | E44: 1600 | F44: 490 | G44: 1100 | H44: =G44/E44 -> 0.6875 | I44: =IF(AND(H44>=30%, E44>100), "Pass", "Fail") -> Pass | J44: View details | K44: {=XLOOKUP("*" & B44 & "*", Prelander!$B$2:$B$55, Prelander!$D$2:$D$55, "Không tìm thấy", 2)} -> 316 | L44: 14 | M44: 74939 | N44: 0.9752 | O44: 72 | P44: =K44/G44 -> 0.28727273 | Q44: =O44*2.5%*(M44*N44) -> 131544.92 | R44: =Q44/E44 -> 82.215577 | S44: FALSE | T44: Shopify
A45: NOW Foods | B45: nowfoods.com | C45: Health/Supplement | D45: US | E45: 170 | F45: 79 | G45: 100 | H45: =G45/E45 -> 0.58823529 | I45: =IF(AND(H45>=50%, E45>100), "Pass", "Fail") -> Pass | M45: 546285 | N45: 0
A46: Legion Athletics | B46: legionathletics.com | C46: Sports Nutrition | D46: US | E46: 860 | F46: 500 | G46: 310 | H46: =G46/E46 -> 0.36046512 | I46: =IF(AND(H46>=30%, E46>100), "Pass", "Fail") -> Pass | J46: View details | K46: 0 | L46: 0 | M46: 582213 | N46: 0.0462 | O46: 90 | P46: =K46/G46 -> 0 | Q46: =O46*2.5%*(M46*N46) -> 60521.041 | R46: =Q46/E46 -> 70.373304
A47: Transparent Labs | B47: transparentlabs.com | C47: Sports Nutrition | D47: US | E47: 280 | F47: 100 | G47: 180 | H47: =G47/E47 -> 0.64285714 | I47: =IF(AND(H47>=50%, E47>100), "Pass", "Fail") -> Pass | M47: 1.153M | N47: 0.2667
A48: iHerb | B48: iherb.com | C48: Retailer/Supplement | D48: US | E48: 6700 | F48: 3500 | G48: 3100 | H48: =G48/E48 -> 0.46268657 | I48: =IF(AND(H48>=30%, E48>100), "Pass", "Fail") -> Pass | J48: View details | K48: 0 | L48: 0 | M48: =41.77*1000000 -> 41770000 | N48: 0.3875 | O48: 112 | P48: =K48/G48 -> 0 | Q48: =O48*2.5%*(M48*N48) -> 45320450 | R48: =Q48/E48 -> 6764.2463
A49: Trynomend | B49: Trynomend.com | C49: Health & Wellness | D49: US | E49: 170 | F49: 82 | G49: 91 | H49: =G49/E49 -> 0.53529412 | I49: =IF(AND(H49>=30%, E49>100), "Pass", "Fail") -> Pass | J49: View details | K49: {=XLOOKUP("*" & B49 & "*", Prelander!$B$2:$B$55, Prelander!$D$2:$D$55, "Không tìm thấy", 2)} -> 23 | L49: 1 | M49: 68029 | N49: 0.983 | O49: 76 | P49: =K49/G49 -> 0.25274725 | Q49: =O49*2.5%*(M49*N49) -> 127057.76 | R49: =Q49/E49 -> 747.39861 | S49: FALSE
A50: WelleCo | B50: welleco.com | C50: Wellness | D50: AU | E50: 380 | F50: 130 | G50: 240 | H50: =G50/E50 -> 0.63157895 | I50: =IF(AND(H50>=30%, E50>100), "Pass", "Fail") -> Pass | J50: View details | K50: 6 | L50: 690 | M50: 62219 | N50: 0.8476 | O50: 105 | P50: =K50/G50 -> 0.025 | Q50: =O50*2.5%*(M50*N50) -> 138434.16 | R50: =Q50/E50 -> 364.30043 | S50: FALSE
A51: MuscleBlaze | B51: muscleblaze.com | C51: Sports Nutrition | D51: IN | E51: 1200 | F51: 660 | G51: 460 | H51: =G51/E51 -> 0.38333333 | I51: =IF(AND(H51>=30%, E51>100), "Pass", "Fail") -> Pass | J51: View details | K51: 0 | L51: 0 | M51: =3.959*1000000 -> 3959000 | N51: 0.106 | O51: 32 | P51: =K51/G51 -> 0 | Q51: =O51*2.5%*(M51*N51) -> 335723.2 | R51: =Q51/E51 -> 279.76933
A52: Trysaphire | B52: trysaphire.com | C52: Personal Care | D52: US | E52: 900 | F52: 550 | G52: 360 | H52: =G52/E52 -> 0.4 | I52: =IF(AND(H52>=30%, E52>100), "Pass", "Fail") -> Pass | J52: View details | K52: {=XLOOKUP("*" & B52 & "*", Prelander!$B$2:$B$55, Prelander!$D$2:$D$55, "Không tìm thấy", 2)} -> 56 | L52: 1 | M52: 54609 | N52: 0.9831 | O52: 85 | P52: =K52/G52 -> 0.15555556 | Q52: =O52*2.5%*(M52*N52) -> 114082.98 | R52: =Q52/E52 -> 126.75887 | S52: FALSE
A53: Nutrabay | B53: nutrabay.com | C53: Sports Nutrition | D53: IN | E53: 110 | F53: 58 | G53: 51 | H53: =G53/E53 -> 0.46363636 | I53: =IF(AND(H53>=30%, E53>100), "Pass", "Fail") -> Pass | J53: View details | K53: 0 | L53: 0 | M53: =3.787*1000000 -> 3787000 | N53: 0.335 | O53: 25 | P53: =K53/G53 -> 0 | Q53: =O53*2.5%*(M53*N53) -> 792903.12 | R53: =Q53/E53 -> 7208.2102
A54: OmniCreatine | B54: omnicreatine.com | C54: MEN's Health | D54: US | E54: 320 | F54: 160 | G54: 160 | H54: =G54/E54 -> 0.5 | I54: =IF(AND(H54>=30%, E54>100), "Pass", "Fail") -> Pass | J54: View details | K54: 13 | L54: 4 | M54: 32862 | N54: 0.999 | O54: 74 | P54: =K54/G54 -> 0.08125 | Q54: =O54*2.5%*(M54*N54) -> 60733.905 | R54: =Q54/E54 -> 189.79345 | S54: FALSE
A55: Spnutrition | B55: https://spnutrition-us.com/ | C55: Personal Care | D55: US | E55: 1400 | F55: 430 | G55: 980 | H55: =G55/E55 -> 0.7 | I55: =IF(AND(H55>=30%, E55>100), "Pass", "Fail") -> Pass | J55: View details | K55: {=XLOOKUP("*" & B55 & "*", Prelander!$B$2:$B$55, Prelander!$D$2:$D$55, "Không tìm thấy", 2)} -> 139 | L55: 7 | M55: 22519 | N55: 0.86 | O55: 84 | P55: =K55/G55 -> 0.14183673 | Q55: =O55*2.5%*(M55*N55) -> 40669.314 | R55: =Q55/E55 -> 29.04951 | S55: FALSE | T55: Shopify
A56: Zenther | B56: zenther.co | C56: Health/Supplement | D56: US | E56: 1100 | F56: 71 | G56: 1000 | H56: =G56/E56 -> 0.90909091 | I56: =IF(AND(H56>=30%, E56>100), "Pass", "Fail") -> Pass | J56: View details | K56: {=XLOOKUP("*" & B56 & "*", Prelander!$B$2:$B$55, Prelander!$D$2:$D$55, "Không tìm thấy", 2)} -> 162 | L56: 1 | M56: 20263 | N56: 0.989 | O56: 115 | P56: =K56/G56 -> 0.162 | Q56: =O56*2.5%*(M56*N56) -> 57615.308 | R56: =Q56/E56 -> 52.377552 | S56: FALSE | T56: Shopify
A57: Mivourr | B57: mivourr.com | C57: Health & Wellness | D57: US | E57: 220 | F57: 15 | G57: 170 | H57: =G57/E57 -> 0.77272727 | I57: =IF(AND(H57>=30%, E57>100), "Pass", "Fail") -> Pass | J57: View details | K57: {=XLOOKUP("*" & B57 & "*", Prelander!$B$2:$B$55, Prelander!$D$2:$D$55, "Không tìm thấy", 2)} -> 198 | L57: 0 | M57: 15287 | N57: 0.5919 | O57: 125 | P57: =K57/G57 -> 1.1647059 | Q57: =O57*2.5%*(M57*N57) -> 28276.173 | R57: =Q57/E57 -> 128.52806 | S57: FALSE
A58: MindBodyGreen | B58: mindbodygreen.com | C58: Wellness | D58: US | E58: 460 | F58: 210 | G58: 240 | H58: =G58/E58 -> 0.52173913 | I58: =IF(AND(H58>=50%, E58>100), "Pass", "Fail") -> Pass | M58: 2.233M | N58: 0.1919
A59: Martinclinic | B59: us.martinclinic.com | C59: Health/Supplement | D59: US | E59: 370 | F59: 14 | G59: 360 | H59: =G59/E59 -> 0.97297297 | I59: =IF(AND(H59>=30%, E59>100), "Pass", "Fail") -> Pass | J59: View details | K59: 24 | L59: 320 | M59: 5503 | N59: 1 | O59: 94 | P59: =K59/G59 -> 0.066666667 | Q59: =O59*2.5%*(M59*N59) -> 12932.05 | R59: =Q59/E59 -> 34.951486 | S59: FALSE
A60: Blymeskinsystems | B60: blymeskinsystems.com | C60: Health & Beauty | D60: US | E60: 170 | F60: 0 | G60: 170 | H60: =G60/E60 -> 1 | I60: =IF(AND(H60>=30%, E60>100), "Pass", "Fail") -> Pass | J60: View details | K60: 8 | L60: 2 | M60: 4999 | N60: 0.8308 | O60: 68 | P60: =K60/G60 -> 0.047058824 | Q60: =O60*2.5%*(M60*N60) -> 7060.3876 | R60: =Q60/E60 -> 41.531692 | S60: FALSE
A61: Soovera | B61: soovera.com | C61: Health & Wellness | D61: US | E61: 420 | F61: 150 | G61: 260 | H61: =G61/E61 -> 0.61904762 | I61: =IF(AND(H61>=30%, E61>100), "Pass", "Fail") -> Pass | J61: View details | K61: 68 | L61: 1 | M61: 3832 | N61: 1 | O61: 64 | P61: =K61/G61 -> 0.26153846 | Q61: =O61*2.5%*(M61*N61) -> 6131.2 | R61: =Q61/E61 -> 14.598095 | S61: FALSE
A62: Huel | B62: huel.com | C62: Nutrition | D62: UK | E62: 810 | F62: 270 | G62: 500 | H62: =G62/E62 -> 0.61728395 | I62: =IF(AND(H62>=50%, E62>100), "Pass", "Fail") -> Pass | M62: 2.106M | N62: 0.2575
A63: Organifi | B63: organifi.com | C63: Greens/Superfood | D63: US | E63: 58 | F63: 41 | G63: 17 | H63: =G63/E63 -> 0.29310345 | I63: =IF(AND(H63>=30%, E63>100), "Pass", "Fail") -> Fail
A64: Trulean | B64: trulean.com | C64: Protein/Weight Loss | D64: US | E64: 27 | F64: 26 | G64: 1 | H64: =G64/E64 -> 0.037037037 | I64: =IF(AND(H64>=30%, E64>100), "Pass", "Fail") -> Fail
A65: Vitable | B65: vitable.com.au | C65: Personalized Vitamins | D65: AU | E65: 170 | F65: 75 | G65: 96 | H65: =G65/E65 -> 0.56470588 | I65: =IF(AND(H65>=50%, E65>100), "Pass", "Fail") -> Pass | M65: 39123 | N65: 0
A66: ThriveCo | B66: thriveco.in | C66: Hair Health | D66: IN | E66: 56 | F66: 13 | G66: 41 | H66: =G66/E66 -> 0.73214286 | I66: =IF(AND(H66>=30%, E66>100), "Pass", "Fail") -> Fail
A67: Ancient Nutrition | B67: ancientnutrition.com | C67: Collagen/Superfood | D67: US | E67: 36 | F67: 20 | G67: 16 | H67: =G67/E67 -> 0.44444444 | I67: =IF(AND(H67>=30%, E67>100), "Pass", "Fail") -> Fail
A68: Momentous | B68: livemomentous.com | C68: Sports Nutrition | D68: US | E68: 150 | F68: 110 | G68: 30 | H68: =G68/E68 -> 0.2 | I68: =IF(AND(H68>=30%, E68>100), "Pass", "Fail") -> Fail
A69: Beam Organics | B69: shopbeam.com | C69: Sleep/Wellness | D69: US | E69: 85 | F69: 48 | G69: 37 | H69: =G69/E69 -> 0.43529412 | I69: =IF(AND(H69>=30%, E69>100), "Pass", "Fail") -> Fail
A70: Onnit | B70: onnit.com | C70: Nootropics/Sports Nutrition | D70: US | E70: 71 | F70: 42 | G70: 27 | H70: =G70/E70 -> 0.38028169 | I70: =IF(AND(H70>=30%, E70>100), "Pass", "Fail") -> Fail
A71: Vitauthority | B71: vitauthority.com | C71: Collagen/Wellness | D71: US | E71: 36 | F71: 11 | G71: 24 | H71: =G71/E71 -> 0.66666667 | I71: =IF(AND(H71>=30%, E71>100), "Pass", "Fail") -> Fail
A72: LivOn Labs | B72: livonlabs.com | C72: Collagen/Wellness | D72: US | E72: 16 | F72: 16 | G72: 0 | H72: =G72/E72 -> 0 | I72: =IF(AND(H72>=30%, E72>100), "Pass", "Fail") -> Fail
A73: Four Sigmatic | B73: foursigmatic.com | C73: Functional Mushroom | D73: US | E73: 61 | F73: 22 | G73: 37 | H73: =G73/E73 -> 0.60655738 | I73: =IF(AND(H73>=30%, E73>100), "Pass", "Fail") -> Fail
A74: Codeage | B74: codeage.com | C74: Collagen/Wellness | D74: US | E74: 76 | F74: 13 | G74: 63 | H74: =G74/E74 -> 0.82894737 | I74: =IF(AND(H74>=30%, E74>100), "Pass", "Fail") -> Fail
A75: Bulk Nutrients | B75: bulknutrients.com.au | C75: Sports Nutrition | D75: AU | E75: 220 | F75: 99 | G75: 120 | H75: =G75/E75 -> 0.54545455 | I75: =IF(AND(H75>=50%, E75>100), "Pass", "Fail") -> Pass | M75: 920349 | N75: 0.042
A76: Nuzest | B76: nuzest.com | C76: Protein/Wellness | D76: US | E76: 140 | F76: 120 | G76: 18 | H76: =G76/E76 -> 0.12857143 | I76: =IF(AND(H76>=30%, E76>100), "Pass", "Fail") -> Fail
A77: Perfect Keto | B77: perfectketo.com | C77: Keto/Supplements | D77: US | E77: 18 | F77: 10 | G77: 8 | H77: =G77/E77 -> 0.44444444 | I77: =IF(AND(H77>=30%, E77>100), "Pass", "Fail") -> Fail
A78: Muscle & Strength | B78: muscleandstrength.com | C78: Sports Nutrition | D78: US | E78: 51 | F78: 8 | G78: 42 | H78: =G78/E78 -> 0.82352941 | I78: =IF(AND(H78>=30%, E78>100), "Pass", "Fail") -> Fail
A79: Garden of Life | B79: gardenoflife.com | C79: Organic/Wellness | D79: US | E79: 27 | F79: 10 | G79: 17 | H79: =G79/E79 -> 0.62962963 | I79: =IF(AND(H79>=30%, E79>100), "Pass", "Fail") -> Fail
A80: Nutrabay | B80: nutrabay.com | C80: Sports Nutrition | D80: IN | E80: 110 | F80: 58 | G80: 51 | H80: =G80/E80 -> 0.46363636 | I80: =IF(AND(H80>=30%, E80>100), "Pass", "Fail") -> Pass | J80: View details | K80: 0 | L80: 0 | M80: =3.787*1000000 -> 3787000 | N80: 0.334 | O80: 25 | P80: =K80/G80 -> 0 | Q80: =O80*2.5%*(M80*N80) -> 790536.25 | R80: =Q80/E80 -> 7186.6932
A81: PhenQ | B81: phenq.com | C81: Weight Loss | D81: US | E81: 12 | F81: 1 | G81: 10 | H81: =G81/E81 -> 0.83333333 | I81: =IF(AND(H81>=30%, E81>100), "Pass", "Fail") -> Fail
A82: Myprotein | B82: myprotein.com | C82: Sports Nutrition | D82: UK | E82: 1300 | F82: 290 | G82: 1000 | H82: =G82/E82 -> 0.76923077 | I82: =IF(AND(H82>=50%, E82>100), "Pass", "Fail") -> Pass | M82: 5.616M | N82: 0.2223
A83: PROMIX Nutrition | B83: promix.com | C83: Protein/Supplements | D83: US | E83: 1400 | F83: 1000 | G83: 390 | H83: =G83/E83 -> 0.27857143 | I83: =IF(AND(H83>=30%, E83>100), "Pass", "Fail") -> Fail
A84: Vital Proteins | B84: vitalproteins.com | C84: Collagen/Protein | D84: US | E84: 81 | F84: 38 | G84: 41 | H84: =G84/E84 -> 0.50617284 | I84: =IF(AND(H84>=30%, E84>100), "Pass", "Fail") -> Fail
A85: Kaged | B85: kaged.com | C85: Sports Nutrition | D85: US | E85: 22 | F85: 13 | G85: 6 | H85: =G85/E85 -> 0.27272727 | I85: =IF(AND(H85>=30%, E85>100), "Pass", "Fail") -> Fail
A86: Orgain | B86: orgain.com | C86: General Supplements | D86: US | E86: 190 | F86: 85 | G86: 100 | H86: =G86/E86 -> 0.52631579 | I86: =IF(AND(H86>=50%, E86>100), "Pass", "Fail") -> Pass | M86: 253379 | N86: 0.1952
A87: Bloom Nutrition | B87: bloomnu.com | C87: Women's Wellness | D87: US | E87: 50 | F87: 16 | G87: 34 | H87: =G87/E87 -> 0.68 | I87: =IF(AND(H87>=30%, E87>100), "Pass", "Fail") -> Fail
A88: Swolverine | B88: swolverine.com | C88: Sports Nutrition | D88: US | E88: 2 | F88: 2 | G88: 0 | H88: =G88/E88 -> 0 | I88: =IF(AND(H88>=30%, E88>100), "Pass", "Fail") -> Fail
A89: MuscleTech | B89: muscletech.com | C89: Sports Nutrition | D89: US | E89: 660 | F89: 94 | G89: 550 | H89: =G89/E89 -> 0.83333333 | I89: =IF(AND(H89>=50%, E89>100), "Pass", "Fail") -> Pass | M89: 228070 | N89: 0
A90: Onnit | B90: onnit.com | C90: Nootropics/Supplements | D90: US | E90: 71 | F90: 42 | G90: 27 | H90: =G90/E90 -> 0.38028169 | I90: =IF(AND(H90>=30%, E90>100), "Pass", "Fail") -> Fail
A91: Optimum Nutrition | B91: optimumnutrition.com | C91: Sports Nutrition | D91: US | E91: 190 | F91: 130 | G91: 66 | H91: =G91/E91 -> 0.34736842 | I91: =IF(AND(H91>=30%, E91>100), "Pass", "Fail") -> Pass | J91: View details | K91: 1 | L91: 0 | M91: 716971 | N91: 0.014 | O91: 72 | P91: =K91/G91 -> 0.015151515 | Q91: =O91*2.5%*(M91*N91) -> 18067.669 | R91: =Q91/E91 -> 95.092996
A92: DrinkLMNT | B92: drinklmnt.com | C92: Electrolytes | D92: US | E92: 120 | F92: 98 | G92: 14 | H92: =G92/E92 -> 0.11666667 | I92: =IF(AND(H92>=30%, E92>100), "Pass", "Fail") -> Fail
A93: MusclePharm | B93: musclepharm.com | C93: Sports Nutrition | D93: US | E93: 3 | F93: 0 | G93: 2 | H93: =G93/E93 -> 0.66666667 | I93: =IF(AND(H93>=30%, E93>100), "Pass", "Fail") -> Fail
A94: Gundry MD | B94: gundrymd.com | C94: Health/Supplements | D94: US | E94: 25 | F94: 0 | G94: 25 | H94: =G94/E94 -> 1 | I94: =IF(AND(H94>=30%, E94>100), "Pass", "Fail") -> Fail
A95: Gaspari Nutrition | B95: gaspari.com | C95: Sports Nutrition | D95: US | E95: 82 | F95: 32 | G95: 51 | H95: =G95/E95 -> 0.62195122 | I95: =IF(AND(H95>=30%, E95>100), "Pass", "Fail") -> Fail
A96: Swanson Vitamins | B96: swansonvitamins.com | C96: Health/Supplement | D96: US | E96: 50 | F96: 30 | G96: 15 | H96: =G96/E96 -> 0.3 | I96: =IF(AND(H96>=30%, E96>100), "Pass", "Fail") -> Fail
A97: Four Sigmatic | B97: foursigmatic.com | C97: Functional Food | D97: US | E97: 61 | F97: 22 | G97: 37 | H97: =G97/E97 -> 0.60655738 | I97: =IF(AND(H97>=30%, E97>100), "Pass", "Fail") -> Fail
A98: Pendulum | B98: pendulum.life | C98: Gut Health | D98: US | E98: 1200 | F98: 980 | G98: 210 | H98: =G98/E98 -> 0.175 | I98: =IF(AND(H98>=30%, E98>100), "Pass", "Fail") -> Fail
A99: Purity Products | B99: purityproducts.com | C99: Health/Supplement | D99: US | E99: 25 | F99: 2 | G99: 22 | H99: =G99/E99 -> 0.88 | I99: =IF(AND(H99>=30%, E99>100), "Pass", "Fail") -> Fail
A100: Higher DOSE | B100: higherdose.com | C100: Wellness | D100: US | E100: 50 | F100: 3 | G100: 48 | H100: =G100/E100 -> 0.96 | I100: =IF(AND(H100>=30%, E100>100), "Pass", "Fail") -> Fail
A101: Ancient Nutrition | B101: ancientnutrition.com | C101: Protein/Wellness | D101: US | E101: 36 | F101: 20 | G101: 16 | H101: =G101/E101 -> 0.44444444 | I101: =IF(AND(H101>=30%, E101>100), "Pass", "Fail") -> Fail
...

Sheet Prelander
A1: Brand | B1: Prelander url | C1: Ads | D1: Total
A2: The BBCO | B2: https://thebbco.com/pages/ps-radiancy-listicle-dryness-sns | C2: 15 | D2: =SUM(C2:C8) -> 221
B3: https://thebbco.com/pages/radiancy-quiz-flow-2-bof | C3: 1
B4: https://thebbco.com/pages/radiancy-sns-v2 | C4: 1
B5: https://thebbco.com/pages/radiancy-quiz-flow-1 | C5: 9
B6: https://thebbco.com/pages/pp-radiancy-collagen | C6: 104
B7: https://thebbco.com/pages/ps-radiancy-listicle-dryness-pt | C7: 89
B8: https://thebbco.com/pages/pp-provitalize-mttrt2 | C8: 2
A9: Innosupps | B9: https://www.innosupps.com/pages/nitro-wood-magnum-quiz-g | C9: 3 | D9: =SUM(C9:C10) -> 5
B10: https://www.innosupps.com/pages/nitro-wood-magnum-quiz-b | C10: 2
A11: Mivourr | B11: https://mivourr.com/pages/listicle-marriage-back | C11: 1 | D11: =SUM(C11:C17) -> 198
B12: https://mivourr.com/pages/listicle-pain | C12: 1
B13: https://mivourr.com/pages/listicle-tried-everything | C13: 4
B14: https://mivourr.com/pages/listicle-nothing-works | C14: 2
B15: https://mivourr.com/pages/listicle-dryness | C15: 1
B16: https://mivourr.com/pages/listicle | C16: 9
B17: https://thebbco.com/pages/pp-radiancy-collagen | C17: 180
A18: Zenther | B18: https://zenther.co/pages/b085-congruent-listicle | C18: 14 | D18: =SUM(C18:C26) -> 162
B19: https://zenther.co/pages/listicle-ed | C19: 56
B20: https://zenther.co/pages/bp-meds-still-high-numbers | C20: 9
B21: https://zenther.co/pages/dr-who-retired | C21: 2
B22: https://zenther.co/pages/5-reasons-why-cold-extracted-beetroot-could-restore-your-circulation | C22: 1
B23: https://zenther.co/pages/anxiety | C23: 53
B24: https://zenther.co/pages/dropped-40-points-in-3-weeks | C24: 20
B25: https://zenther.co/pages/osbplpa | C25: 3
B26: https://zenther.co/pages/solution-may-be-too-effective | C26: 4
A27: Rejuveen | B27: rejuveen.com/pages/sp-osteva-lumbar | C27: 160 | D27: =SUM(C27:C32) -> 316
B28: https://rejuveen.com/pages/sp-osteva-sns | C28: 4
B29: https://rejuveen.com/pages/anti-rebound-protocol-cpl | C29: 59
B30: https://rejuveen.com/pages/sp-keralush-g | C30: 8
B31: https://rejuveen.com/pages/anti-rebound-protocol-ncpl | C31: 59
B32: https://rejuveen.com/pages/5-ways-glp-1-causes-muscle-wasting | C32: 26
A33: Rejuvia | B33: https://www.rejuvia.co/pages/rejuvia-introduction-listicle | C33: 31 | D33: =SUM(C33:C37) -> 41
B34: https://www.rejuvia.co/pages/veterans | C34: 2
B35: https://www.rejuvia.co/pages/lp2 | C35: 3
B36: https://www.rejuvia.co/pages/lp3 | C36: 3
B37: https://www.rejuvia.co/pages/bogo | C37: 2
A38: Lonvera | B38: https://lonvera.com/pages/vital-bull-lp-1-advertorial | C38: 5 | D38: =SUM(C38) -> 5
A39: Trysaphire | B39: https://trysaphire.com/pages/cl-quiz | C39: 3 | D39: =SUM(C39:C43) -> 56
B40: https://trysaphire.com/pages/bridging-appetite-advertorial-cc-test | C40: 1
B41: https://trysaphire.com/pages/gummies-kid-quiz | C41: 46
B42: https://trysaphire.com/pages/sleep-listicle | C42: 3
B43: https://trysaphire.com/pages/quiz-page | C43: 3
A44: Trynomend | B44: https://trynomend.com/pages/soph-5-listicle-ll-ultra-bfcm | C44: 3 | D44: =SUM(C44:C47) -> 23
B45: https://trynomend.com/pages/soph-5-listicle-ll-ultra | C45: 17
B46: https://trynomend.com/pages/skinny-fat-listicle-ll-ultra | C46: 1
B47: https://trynomend.com/pages/ll-ultra-advertorial-hormonal-belly | C47: 2
A48: Ploise | B48: https://ploise.vercel.app/instant-landing-page-aug-12-01-59-38 | C48: 1 | D48: =SUM(C48:C54) -> 97
B49: https://ploise.vercel.app/ILPdda3 | C49: 3
B50: https://ploise.vercel.app/ilp10 | C50: 77
B51: https://ploise.vercel.app/ilp7 | C51: 2
B52: https://ploise.vercel.app/ilp2 | C52: 1
B53: https://ploise.vercel.app/ilp4 | C53: 5
B54: https://ploise.com/pages/ploise-listicle-1 | C54: 8
A55: Spnutrition | B55: https://spnutrition-us.com/pages/advertorial-magnesium | C55: 139 | D55: =SUM(C55) -> 139
A56: Norse Organics | B56: https://norseorganics.co/pages/10-reasons-why-ritual-1 | C56: 1 | D56: =SUM(C56:C61) -> 75
B57: https://norseorganics.co/pages/stop-acne-teens-2-0 | C57: 6
B58: https://norseorganics.co/pages/stop-acne-lp | C58: 14
B59: https://norseorganics.co/pages/acne | C59: 3
B60: https://norseorganics.co/pages/quiz-v1 | C60: 1
B61: https://norseorganics.co/pages/10-reasons-why-ritual-2 | C61: 50
A62: Froya Organics | B62: https://froyaorganics.com/pages/11-reasons-why-clinical-trial | C62: 9 | D62: =SUM(C62:C67) -> 350
B63: https://froyaorganics.com/pages/eczema | C63: 5
B64: https://froyaorganics.com/pages/psoriasis-eczema-5-reasons-why | C64: 14
B65: https://froyaorganics.com/pages/arctic-skincare-life-saver | C65: 1
B66: https://froyaorganics.com/pages/the-complete-system-for-mature-hair-scalp-advertorial-hair | C66: 1
B67: https://froyaorganics.com/pages/10-reason-why-aging | C67: 320
A68: Happy Mammoth | B68: https://happymammoth.com/pages/feel-balanced | C68: 22 | D68: =sum(C68:C74) -> 172
B69: https://happymammoth.com/pages/hormone-assessment | C69: 0
B70: https://store.happymammoth.com/pages/hormone-support-for-women | C70: 130
B71: https://store.happymammoth.com/pages/hormonal-weight-assist | C71: 13
B72: https://store.happymammoth.com/pages/feel-balanced | C72: 4
B73: https://eu.happymammoth.com/pages/feel-extra-slim | C73: 2
B74: https://happymammoth.com/pages/magnesium-reset | C74: 1
A75: Olavita | B75: https://try.olavita.co/v3/h4/facelift/exp | C75: 15 | D75: =sum(C75:C77) -> 60
B76: https://try.olavita.co/v3/facelift/exp | C76: 39
B77: https://try.olavita.co/pr/42-years-secret | C77: 6
A78: WelleCo | B78: https://www.welleco.com/pages/get-the-super-elixir-4 | C78: 6 | D78: 6
A79: True Protein | B79: trueprotein.com.au/pages/quiz | C79: 5 | D79: 5
A80: Tryrosabella | B80: get.tryrosabella.com/beetroot/subtxt/mm-hbp-sp | C80: 180 | D80: =C80 -> 180
A81: OmniCreatine | B81: https://www.thefitnessaddiction.com/pages/best-creatine-gummies | C81: 13 | D81: =C81 -> 13
A82: Fiera Cosmetic | B82: get.fieracosmetics.com/scq/quiz | C82: 20 | D82: =C82 -> 20
A83: Taste zenith | B83: https://taste-zenith.com/superfoods/adv/new | C83: 4 | D83: =C83 -> 4
A84: Rejuvacare | B84: https://secure.rejuvacare.com/adv-rc-sm-ig-us-v11-geo | C84: 180 | D84: =C84 -> 180
A85: Blymeskinsystems | B85: https://go.blymeskinsystems.com/linda-story | C85: 8 | D85: =C85 -> 8
A86: Martinclinic | B86: https://us.martinclinic.com/pages/cortisol-control-sleep | C86: 24 | D86: 24
A87: Soovera | B87: https://soovera.com/pages/listicle-in-1 | C87: 62 | D87: =SUM(C87:C88) -> 68
B88: https://soovera.com/pages/thermorelief-listicle | C88: 6
A89: Zenith | B89: https://taste-zenith.com/superfoods/adv | C89: 13 | D89: 13
A90: Luxeresearchlab | B90: https://try.luxeresearchlab.com/adv1 | C90: 52 | D90: =SUM(C90:C92) -> 74
B91: https://try.luxeresearchlab.com/advquiz | C91: 18
B92: https://try.luxeresearchlab.com/adv-esp | C92: 4
A93: Myoro | B93: https://myoro.co/pages/uproas | C93: 8 | D93: =SUM(C93:C95) -> 48
B94: https://myoro.co/pages/apexdrive | C94: 26
B95: https://myoro.co/pages/wave1 | C95: 14
A96: Marmens | B96: https://mengotomars.com/pages/quiz-v6 | C96: 38 | D96: =SUM(C96:C97) -> 68
B97: https://mengotomars.com/pages/10-reasons | C97: 30
A98: Primal King | B98: https://primalviking.com/pages/quiz-v1 | C98: 10 | D98: =SUM(C98:C101) -> 40
B99: https://primalviking.com/pages/man-boobs-transformation-cta | C99: 10
B100: https://primalviking.com/pages/10-reasons-man-boobs | C100: 10
...

Sheet Proposal
A1: Quiz | B1: % | C1: Note | D1: Landing | F1: Checkout
A2: https://shop.try-sprtn.com/main-quiz | B2: =193/216 -> 0.89351852 | D2: https://try.cupids.com/products/hypnosis-3 | E2: 1
A3: https://shop.try-forge.com/mens-lifestyle-essentials-1 | B3: =73/250 -> 0.292 | D3: https://secure.try-forge.com/bridge-a1-simple-a1 | E3: =73/273 -> 0.26739927
A4: https://secure.getquietlab.com/sp-m1 | B4: =70/250 -> 0.28 | D4: https://trysculptique.com/pages/top-doctor-i-found-the-real-reason-why-your-foamy-urine-wont-clear | E4: 0.58
A5: https://mengotomars.com/pages/quiz-v6 | B5: 0.124 | D5: https://mengotomars.com/products/30-day-supply-starter-kit | E5: 0.26
A6: Listicle
A7: https://shop.try-forge.com/listicle-eyebags | B7: 0.17
A8: https://mengotomars.com/pages/10-reasons | B8: 0.42
A9: https://www.rejuvia.co/pages/rejuvia-introduction-listicle | B9: 0.6138
A10: Advertorial
A11: https://secure.rejuvacare.com/adv-rc-sm-ig-us-v10-geo | C11: 100% adv
D15: Prelander filter | E15: Traffic filter | G15: Overall
A16: Mars Men | D16: TRUE | E16: https://pro.similarweb.com/?utm_source=addon#/digitalsuite/websiteanalysis/overview/website-performance/*/999/1m?webSource=Total&key=mengotomars.com | F16: TRUE | G16: FALSE
A17: https://mengotomars.com/pages/quiz-v6 | B17: 0.124 | C17: Quiz
A18: https://mengotomars.com/pages/10-reasons | B18: 0.42 | C18: Listicle
A19: https://mengotomars.com/products/30-day-supply-starter-kit | B19: 0.26 | C19: Landing
A22: Forge Men | D22: TRUE | E22: https://pro.similarweb.com/?utm_source=addon#/digitalsuite/websiteanalysis/overview/website-performance/*/999/1m?webSource=Total&key=shop.try-forge.com | F22: TRUE | G22: TRUE
A23: https://shop.try-forge.com/mens-lifestyle-essentials-1 | B23: =73/250 -> 0.292 | C23: Quiz
A24: https://shop.try-forge.com/listicle-eyebags | B24: 0.17 | C24: Listicle
A25: https://secure.try-forge.com/bridge-a1-simple-a1 | B25: =73/273 -> 0.26739927 | C25: Landing
A26: https://shop.try-forge.com/quizpage
A27: https://shop.try-forge.com/listicles-sales-page
D28: FALSE | F28: FALSE | G28: FALSE
A29: Rejuvacare | D29: FALSE | F29: FALSE | G29: FALSE
A30: https://secure.rejuvacare.com/adv-rc-sm-ig-us-v10-geo | B30: 1 | C30: VSL + Advertorial
A32: Tryscultique | D32: FALSE | F32: FALSE | G32: FALSE
A33: https://trysculptique.com/pages/top-doctor-i-found-the-real-reason-why-your-foamy-urine-wont-clear | B33: 0.58 | C33: VSL + ADV + CC's checkout

Sheet Scoring Guide
A1: ADSCORE RUBRIC - SCORING GUIDE
A2: AdScore = (Funnel x 0.30) + (Impressions x 0.25) + (Variations x 0.20) + (Creative x 0.15) + (Longevity x 0.10)
A4: Criterion | B4: Score | C4: Description | D4: Weight
A5: Funnel Sophistication | B5: 1 | C5: No clear funnel. Direct link to generic product page | D5: 30%
B6: 2 | C6: Basic product page with minimal optimization
B7: 3 | C7: Decent LP with clear CTA, some social proof
B8: 4 | C8: Optimized funnel with upsells, strong LP, subscription
B9: 5 | C9: Elite: quiz/advertorial, post-purchase flow, retention loop
A11: Est. Impressions/Spend | B11: 1 | C11: Very low activity, few ads, likely small budget | D11: 25%
B12: 2 | C12: Some traction, moderate ad count
B13: 3 | C13: Consistent activity, medium budget signals
B14: 4 | C14: High activity, many active ads, strong spend signals
B15: 5 | C15: Massive scale, very high ad volume, dominant presence
A17: Ad Variations/Iterations | B17: 1 | C17: 1-2 static versions, no testing signal | D17: 20%
B18: 2 | C18: 3-5 versions with minor changes
B19: 3 | C19: 6-10 versions, clear A/B testing
B20: 4 | C20: 11-20 versions, systematic iteration
B21: 5 | C21: 20+ versions, aggressive testing cadence
A23: Creative Quality | B23: 1 | C23: Low quality, stock-looking, weak copy | D23: 15%
B24: 2 | C24: Acceptable but generic design and messaging
B25: 3 | C25: Good design, decent hooks, clear value prop
B26: 4 | C26: Strong design, compelling hooks, strategic copy
B27: 5 | C27: Outstanding: thumb-stopping, pattern-interrupt, elite copy
A29: Ad Longevity | B29: 1 | C29: 30-45 days (minimum threshold) | D29: 10%
B30: 2 | C30: 45-60 days
B31: 3 | C31: 60-90 days
B32: 4 | C32: 90-180 days
B33: 5 | C33: 180+ days (evergreen performer)
A36: DECISION THRESHOLDS
A37: 3.50 - 5.00 | B37: DEEP DIVE | C37: Approved for full funnel research via AntiGravity
A38: 2.50 - 3.49 | B38: WATCH LIST | C38: Monitor for changes, may revisit later
A39: 1.00 - 2.49 | B39: SKIP | C39: Does not meet criteria, filtered out

Sheet Comet Workflow
A1: COMET (PERPLEXITY) WORKFLOW GUIDE
A4: HOW TO USE THIS SYSTEM WITH COMET
A6: STEP 1: Paste the system instruction (ADS_FUNNEL_INTELLIGENCE_SYSTEM_v3_COMET.md) into Comet
A7: STEP 2: Comet will confirm it understands the pipeline and check browser access
A8: STEP 3: Use one of the commands below to start
A10: --- COMMANDS ---
A12: SCOUT (Discovery + Filter + Score):
A13: "Scout D2C supplement brands running image ads on Meta"
A14: "Scout creatine brands in the US market"
A15: "Scout gut health supplement brands"
A17: DEEP DIVE (Full funnel research on approved brand):
A18: "Deep dive ColonBroom"
... A86: Start with Meta Ads Library now. Report what you find as you go.

Sheet Try-Forge ads system
A1: STT | B1: Page | C1: ID | E1: Ad library | F1: Ads count
A2: 1 | B2: https://www.facebook.com/profile.php?id=61582691356528# | C2: Real men Real Story | D2: TRUE | E2: https://www.facebook.com/ads/library/?active_status=active&ad_type=all&country=ALL&is_targeted_country=false&media_type=all&search_type=page&sort_data[mode]=total_impressions&sort_data[direction]=desc&source=page-transparency-widget&view_all_page_id=841202209076612 | F2: 42
A3: 2 | B3: https://www.facebook.com/profile.php?id=61583113801975# | C3: Mens Daily Steals | D3: FALSE | E3: https://www.facebook.com/ads/library/?active_status=active&ad_type=all&country=ALL&is_targeted_country=false&media_type=all&search_type=page&sort_data[mode]=total_impressions&sort_data[direction]=desc&source=page-transparency-widget&view_all_page_id=899263093259951 | F3: 7
A4: 3 | B4: https://www.facebook.com/profile.php?id=61556636866808# | C4: Men's Lifestyle Essentials | D4: TRUE | E4: https://www.facebook.com/ads/library/?active_status=active&ad_type=all&country=ALL&is_targeted_country=false&media_type=all&search_type=page&sort_data[mode]=total_impressions&sort_data[direction]=desc&source=page-transparency-widget&view_all_page_id=197462513459777 | F4: 37
A5: 4 | B5: https://www.facebook.com/profile.php?id=61578850988287# | C5: The Elite Man | D5: TRUE | E5: https://www.facebook.com/ads/library/?active_status=active&ad_type=all&country=ALL&is_targeted_country=false&media_type=all&search_type=page&sort_data[mode]=total_impressions&sort_data[direction]=desc&source=page-transparency-widget&view_all_page_id=781556828366952 | F5: 55
A6: 5 | B6: https://www.facebook.com/profile.php?id=61582904922136# | C6: The Everyday Man | D6: TRUE | E6: https://www.facebook.com/ads/library/?active_status=active&ad_type=all&country=ALL&is_targeted_country=false&media_type=all&search_type=page&sort_data[mode]=total_impressions&sort_data[direction]=desc&source=page-transparency-widget&view_all_page_id=768328883041750 | F6: 34
A7: 6 | B7: https://www.facebook.com/profile.php?id=61583129138493# | C7: Better Performance | D7: TRUE | E7: https://www.facebook.com/ads/library/?active_status=active&ad_type=all&country=ALL&is_targeted_country=false&media_type=all&search_type=page&sort_data[mode]=total_impressions&sort_data[direction]=desc&source=page-transparency-widget&view_all_page_id=892916470563125 | F7: 89
A8: 7 | B8: https://www.facebook.com/profile.php?id=61582935845409# | C8: David Grant | D8: TRUE | E8: https://www.facebook.com/ads/library/?active_status=active&ad_type=all&country=ALL&is_targeted_country=false&media_type=all&search_type=page&sort_data[mode]=total_impressions&sort_data[direction]=desc&source=page-transparency-widget&view_all_page_id=770968199443688 | F8: 18
A9: 8 | B9: https://www.facebook.com/profile.php?id=61560871530927# | C9: Dr. Michael Reed | D9: TRUE | E9: https://www.facebook.com/ads/library/?active_status=active&ad_type=all&country=ALL&is_targeted_country=false&media_type=all&search_type=page&sort_data[mode]=total_impressions&sort_data[direction]=desc&source=page-transparency-widget&view_all_page_id=372402992615401 | F9: 110
A10: 9 | B10: https://www.facebook.com/profile.php?id=61552996366957# | C10: Forge Men | D10: TRUE | E10: https://www.facebook.com/ads/library/?active_status=active&ad_type=all&country=ALL&is_targeted_country=false&media_type=all&search_type=page&sort_data[mode]=total_impressions&sort_data[direction]=desc&source=page-transparency-widget&view_all_page_id=132584606613853 | F10: 60
F11: =sum(F2:F10) -> 452

Sheet try-forge Ads (OLD)
A1: Library ID | B1: Page Name | C1: Start Date | D1: Ad Type | E1: Title | F1: Primary Text | G1: Description | H1: Landing Page | I1: CTA | J1: Media URL | K1: Brand | L1: Facebook Page ID
A2: 843655715426302 | B2: Forge Men | C2: 46098 | D2: Video | E2: ⏰LAST CHANCE!⏰Sale Ends at Midnight... | F2: 🌼BIGGEST Spring Sale EVER!🌼 Get 50% OFF our Beef Tallow Balm, PLUS an EXTRA 20% with code 'SPRING20'! Our Beef Tallow Balm: ✔️Tightens wrinkles QUICKLY ✔️Reduces eye bags and dark spots ✔️Makes your skin thicker, stronger, & hydrated ✔️Helps you go from "tired face" to "sharp & refreshed" Don’t let this one-time deal slip away... an offer this big won’t come back a second time! Tap the button below to get your discount now 👇 | G2: BIGGEST Sale Of The Year! | H2: https://shop.try-forge.com/mens-lifestyle-essentials-1 | I2: Shop now | J2: https://video.fsgn5-3.fna.fbcdn.net/o1/v/t2/f2/m412/AQO24YzBrItZMohpaoG0NucU2KN3jtPLS1xZPDrrjWBgvTWWLyA5e3IEi15x7laWELhAnVO9UVOWdNLn7vpGEogFU0jnan0RkoSsN_HQwA.mp4?_nc_cat=104&_nc_oc=AdoU3NOfMsrKNhcxjp-zTPJULUdn5C9Vxn4mI6Q4MK6xdsYAEqZvLRd-RMw8CREULoQ&_nc_sid=8bf8fe&_nc_ht=video.fsgn5-3.fna.fbcdn.net&_nc_ohc=ltQDEfiXTn0Q7kNvwElwRt3&efg=eyJ2ZW5jb2RlX3RhZyI6Inhwdl9wcm9ncmVzc2l2ZS5WSV9VU0VDQVNFX1BST0RVQ1RfVFlQRS4uQzMuMzYwLnN2ZV9zZCIsInhwdl9hc3NldF9pZCI6MTI3ODYxMzQzNDE0ODk1MCwiYXNzZXRfYWdlX2RheXMiOjIxLCJ2aV91c2VjYXNlX2lkIjoxMDEzOSwiZHVyYXRpb25fcyI6NjQsInVybGdlbl9zb3VyY2UiOiJ3d3cifQ%3D%3D&ccb=17-1&_nc_gid=Bp1XYkM11Sb96VrtMEK0aA&_nc_ss=7a389&_nc_zt=28&oh=00_Af1YbKldRjrETj5BF_T0eG-xn1iS51geSz6o7gwdCHl6Rg&oe=69DAFEC6 | K2: shop.try-forge.com | L2: 132584606613853
A3: 909950778461922 | B3: Forge Men | C3: 46094 | D3: Video | E3: ⏰LAST CHANCE!⏰Sale Ends at Midnight... | F3: 🌼BIGGEST Spring Sale EVER!🌼 Get 50% OFF our Beef Tallow Balm, PLUS an EXTRA 20% with code 'SPRING20'! Our Beef Tallow Balm: ✔️Tightens wrinkles QUICKLY ✔️Reduces eye bags and dark spots ✔️Makes your skin thicker, stronger, & hydrated ✔️Helps you go from "tired face" to "sharp & refreshed" Don’t let this one-time deal slip away... an offer this big won’t come back a second time! Tap the button below to get your discount now 👇 | G3: BIGGEST Sale Of The Year! | H3: https://shop.try-forge.com/mens-lifestyle-essentials-1 | I3: Shop now | J3: https://video.fsgn5-12.fna.fbcdn.net/o1/v/t2/f2/m412/AQOLDxz_ZQ5s2PkMrGeA1jWDf_gTLz5K2kTYT7vgeQYKcAqik5Rz2DsQM8Inp7SAXSbvOHQfbGTKS1wjlFQWbTzpjzjtzerrlfSg6UNJkA.mp4?_nc_cat=103&_nc_oc=AdqSe3RGGGdG0ezLW9Plz8kH5mYbJgTALUKIfFkHLbzB8zKJsLNaPlR0p5RCc_zahPs&_nc_sid=8bf8fe&_nc_ht=video.fsgn5-12.fna.fbcdn.net&_nc_ohc=lCjYy2MCeokQ7kNvwGkJA7d&efg=eyJ2ZW5jb2RlX3RhZyI6Inhwdl9wcm9ncmVzc2l2ZS5WSV9VU0VDQVNFX1BST0RVQ1RfVFlQRS4uQzMuMzYwLnN2ZV9zZCIsInhwdl9hc3NldF9pZCI6MTI3OTk1ODI1NDA4OTc5NSwiYXNzZXRfYWdlX2RheXMiOjI0LCJ2aV91c2VjYXNlX2lkIjoxMDEzOSwiZHVyYXRpb25fcyI6NjYsInVybGdlbl9zb3VyY2UiOiJ3d3cifQ%3D%3D&ccb=17-1&_nc_gid=Bp1XYkM11Sb96VrtMEK0aA&_nc_ss=7a389&_nc_zt=28&oh=00_Af0noGVyaE6ng7ucC6U_w65ku_FWvj1nNAIwtwBVPOgrkg&oe=69DAE3E7 | K3: shop.try-forge.com | L3: 132584606613853
A4: 773401529168938 | B4: Forge Men | C4: 46094 | D4: Image | E4: ⏰LAST CHANCE!⏰Sale Ends at Midnight... | F4: 🌼BIGGEST Spring Sale EVER!🌼 Get 50% OFF our Beef Tallow Balm, PLUS an EXTRA 20% with code 'SPRING20'! Our Beef Tallow Balm: ✔️Tightens wrinkles QUICKLY ✔️Reduces eye bags and dark spots ✔️Makes your skin thicker, stronger, & hydrated ✔️Helps you go from "tired face" to "sharp & refreshed" Don’t let this one-time deal slip away... an offer this big won’t come back a second time! Tap the button below to get your discount now 👇 | G4: BIGGEST Sale Of The Year! | H4: https://shop.try-forge.com/mens-lifestyle-essentials-1 | I4: Shop now | J4: https://scontent.fsgn5-11.fna.fbcdn.net/v/t39.35426-6/651698010_1490025502729327_4252020054043767452_n.jpg?stp=dst-jpg_s600x600_tt6&_nc_cat=110&ccb=1-7&_nc_sid=c53f8f&_nc_ohc=alwwRX-I8K4Q7kNvwFLum-9&_nc_oc=AdqEDX0i_7VZT93zHdIPLcXbpNYKlD7igpH_IIzjzT45KFMhpKErEtiT1CxABIOyGKA&_nc_zt=14&_nc_ht=scontent.fsgn5-11.fna&_nc_gid=Bp1XYkM11Sb96VrtMEK0aA&_nc_ss=7a389&oh=00_Af19QwGwGMWPFVHeqNTcYMafmsetyu_jfo0D7_lAUdtznw&oe=69DB05E9 | K4: shop.try-forge.com | L4: 132584606613853
A5: 2011434282767087 | B5: Forge Men | C5: 46094 | D5: Image | E5: ⏰LAST CHANCE!⏰Sale Ends at Midnight... | F5: 🌼BIGGEST Spring Sale EVER!🌼 Get 50% OFF our Beef Tallow Balm, PLUS an EXTRA 20% with code 'SPRING20'! Our Beef Tallow Balm: ✔️Tightens wrinkles QUICKLY ✔️Reduces eye bags and dark spots ✔️Makes your skin thicker, stronger, & hydrated ✔️Helps you go from "tired face" to "sharp & refreshed" Don’t let this one-time deal slip away... an offer this big won’t come back a second time! Tap the button below to get your discount now 👇 | G5: BIGGEST Sale Of The Year! | H5: https://shop.try-forge.com/mens-lifestyle-essentials-1 | I5: Shop now | J5: https://scontent.fsgn5-3.fna.fbcdn.net/v/t39.35426-6/650237591_2941341806220919_3409998216645146078_n.jpg?stp=dst-jpg_s600x600_tt6&_nc_cat=104&ccb=1-7&_nc_sid=c53f8f&_nc_ohc=Re44RZ-0HPcQ7kNvwGgK9JB&_nc_oc=Adpne6uh3zFwRYpFO8dq4OIRlnLuMmto6K2t1IPrIhQbLgvFuBDB5mngXaS3kbFMjMs&_nc_zt=14&_nc_ht=scontent.fsgn5-3.fna&_nc_gid=Bp1XYkM11Sb96VrtMEK0aA&_nc_ss=7a389&oh=00_Af3NxG6xvv8WffWQZmMTdwWxHXl7GWNIZvlI_hCHtpXDvw&oe=69DAF743 | K5: shop.try-forge.com | L5: 132584606613853
A6: 1837211846969103 | B6: Forge Men | C6: 46099 | D6: Image | E6: ⏰LAST CHANCE!⏰Sale Ends at Midnight... | F6: 🌼BIGGEST Spring Sale EVER!🌼 Get 50% OFF our Beef Tallow Balm, PLUS an EXTRA 20% with code 'SPRING20'! Our Beef Tallow Balm: ✔️Tightens wrinkles QUICKLY ✔️Reduces eye bags and dark spots ✔️Makes your skin thicker, stronger, & hydrated ✔️Helps you go from "tired face" to "sharp & refreshed" Don’t let this one-time deal slip away... an offer this big won’t come back a second time! Tap the button below to get your discount now 👇 | G6: BIGGEST Sale Of The Year! | H6: https://shop.try-forge.com/mens-lifestyle-essentials-1 | I6: Shop now | J6: https://scontent.fsgn5-12.fna.fbcdn.net/v/t39.35426-6/651160290_913306771553528_8225281892631199161_n.jpg?stp=dst-jpg_s600x600_tt6&_nc_cat=105&ccb=1-7&_nc_sid=c53f8f&_nc_ohc=dn7_Ra3QzwgQ7kNvwHo2OxU&_nc_oc=Adrz2Cv8r6oQ9jZK9MAN0iSE3S7rWSjdoL8echcFxj5BHh5bujp_xG-_2OmL4j501tA&_nc_zt=14&_nc_ht=scontent.fsgn5-12.fna&_nc_gid=Bp1XYkM11Sb96VrtMEK0aA&_nc_ss=7a389&oh=00_Af3cTYzCOywpGNZ4H8kkB58zXbt2ceLOzbJefTZRyQ9pRg&oe=69DAE18D | K6: shop.try-forge.com | L6: 132584606613853
A7: 2130137494484715 | B7: Forge Men | C7: 46094 | D7: Image | E7: ⏰LAST CHANCE!⏰Sale Ends at Midnight... | F7: BIGGEST Spring Sale EVER! Get 50% OFF our Beef Organ Complex, PLUS an EXTRA 20% with code ‘SPRING20’! Our Beef Organ Complex: ✔️Crushes afternoon energy crashes FAST ✔️Supports healthy testosterone & masculine drive ✔️Sharpens focus and clears brain fog ✔️Helps you go from “dragging through the day” to “firing on all cylinders” Don’t let this one-time deal slip away... an offer this big won’t come back a second time! Tap the button below to get your discount now 👇 | G7: BIGGEST Sale Of The Year! | H7: https://secure.try-forge.com/bridge-a1-simple | I7: Shop now | J7: https://scontent.fsgn5-5.fna.fbcdn.net/v/t39.35426-6/650202832_1425841362282294_1227244675989920267_n.jpg?stp=dst-jpg_s600x600_tt6&_nc_cat=102&ccb=1-7&_nc_sid=c53f8f&_nc_ohc=Om8hYqGnmPsQ7kNvwFUdEz_&_nc_oc=AdoaDg-CRmMieQGsElZiNQ_Qgr6-ctlSdb3Dur28Z9yO_k4hKN32R1fHOuWkA3eDsbM&_nc_zt=14&_nc_ht=scontent.fsgn5-5.fna&_nc_gid=Bp1XYkM11Sb96VrtMEK0aA&_nc_ss=7a389&oh=00_Af3VoVjrst2wicA_6gDEV2iUnT83nY7SdK4-tlcOhYM1fA&oe=69DAFB68 | K7: shop.try-forge.com | L7: 132584606613853
A8: 927980013212752 | B8: Forge Men | C8: 46094 | D8: Image | E8: ⏰LAST CHANCE!⏰Sale Ends at Midnight... | F8: BIGGEST Spring Sale EVER! Get 50% OFF our Beef Organ Complex, PLUS an EXTRA 20% with code ‘SPRING20’! Our Beef Organ Complex: ✔️Crushes afternoon energy crashes FAST ✔️Supports healthy testosterone & masculine drive ✔️Sharpens focus and clears brain fog ✔️Helps you go from “dragging through the day” to “firing on all cylinders” Don’t let this one-time deal slip away... an offer this big won’t come back a second time! Tap the button below to get your discount now 👇 | G8: BIGGEST Sale Of The Year! | H8: https://secure.try-forge.com/bridge-a1-simple | I8: Shop now | J8: https://scontent.fsgn5-3.fna.fbcdn.net/v/t39.35426-6/650247889_925083479928355_2170574637019682351_n.jpg?stp=dst-jpg_s600x600_tt6&_nc_cat=104&ccb=1-7&_nc_sid=c53f8f&_nc_ohc=vDgckAZ0zMoQ7kNvwGQ9dML&_nc_oc=AdpaZ4NCujqS1ZPF4zadFs8zdRcx29TrEHbebURMUFvQCYoZgU0Sr6gLTOpHHs5gEA0&_nc_zt=14&_nc_ht=scontent.fsgn5-3.fna&_nc_gid=Bp1XYkM11Sb96VrtMEK0aA&_nc_ss=7a389&oh=00_Af1Q9tfbSAmQ5G6IEYXKZiXiOYpDfRhpJxa5JOsEhby4_A&oe=69DADBAB | K8: shop.try-forge.com | L8: 132584606613853
A9: 957514440143624 | B9: Forge Men | C9: 46098 | D9: Video | E9: ⏰LAST CHANCE!⏰Sale Ends at Midnight... | F9: 🌼BIGGEST Spring Sale EVER!🌼 Get 50% OFF our Beef Tallow Balm, PLUS an EXTRA 20% with code 'SPRING20'! Our Beef Tallow Balm: ✔️Tightens wrinkles QUICKLY ✔️Reduces eye bags and dark spots ✔️Makes your skin thicker, stronger, & hydrated ✔️Helps you go from "tired face" to "sharp & refreshed" Don’t let this one-time deal slip away... an offer this big won’t come back a second time! Tap the button below to get your discount now 👇 | G9: BIGGEST Sale Of The Year! | H9: https://shop.try-forge.com/mens-lifestyle-essentials-1 | I9: Shop now | J9: https://video.fsgn5-5.fna.fbcdn.net/o1/v/t2/f2/m412/AQPat1MGGFIPLge2kJcJA4OIbSp04p3ePyhK-ePjbMVTtYlF03Bw2OrrX3xcWNDE2vxgi4ohx_pmDjfM4Wf-zhFYjDZsrRGr1OyBtAAaJQ.mp4?_nc_cat=102&_nc_oc=Ado2t4V7NRTf_F2NaDCupeV-hbOr4k76LIBYhcrv6dbYtK7d1GQW36GjyxEUEpaJK4k&_nc_sid=8bf8fe&_nc_ht=video.fsgn5-5.fna.fbcdn.net&_nc_ohc=1LKcSQShl8gQ7kNvwEdqdcn&efg=eyJ2ZW5jb2RlX3RhZyI6Inhwdl9wcm9ncmVzc2l2ZS5WSV9VU0VDQVNFX1BST0RVQ1RfVFlQRS4uQzMuMzYwLnN2ZV9zZCIsInhwdl9hc3NldF9pZCI6MjQ3NDgxODgwMDgyMTMxMjIsImFzc2V0X2FnZV9kYXlzIjoyMSwidmlfdXNlY2FzZV9pZCI6MTAxMzksImR1cmF0aW9uX3MiOjY0LCJ1cmxnZW5fc291cmNlIjoid3d3In0%3D&ccb=17-1&_nc_gid=Bp1XYkM11Sb96VrtMEK0aA&_nc_ss=7a389&_nc_zt=28&oh=00_Af2ZVCgPryfj8NK0GC5D0YWy2njl-WTYv3PlSOtLHOyAhQ&oe=69DB067C | K9: shop.try-forge.com | L9: 132584606613853
A10: 1397620872131162 | B10: Forge Men | C10: 46094 | D10: Video | E10: ⏰LAST CHANCE!⏰Sale Ends at Midnight... | F10: 🌼BIGGEST Spring Sale EVER!🌼 Get 50% OFF our Beef Tallow Balm, PLUS an EXTRA 20% with code 'SPRING20'! Our Beef Tallow Balm: ✔️Tightens wrinkles QUICKLY ✔️Reduces eye bags and dark spots ✔️Makes your skin thicker, stronger, & hydrated ✔️Helps you go from "tired face" to "sharp & refreshed" Don’t let this one-time deal slip away... an offer this big won’t come back a second time! Tap the button below to get your discount now 👇 | G10: BIGGEST Sale Of The Year! | H10: https://shop.try-forge.com/mens-lifestyle-essentials-1 | I10: Shop now | J10: https://video.fsgn5-11.fna.fbcdn.net/o1/v/t2/f2/m412/AQNMHpmkDcDjCZR6C2pl8JlfEvxpsG1-EIn_bLGPVgfTbesGteDZnEGGNzpNBJW33HgAbriMu_fhofIFAYIa-7NhXPGJWdeB3QVdxZdtwg.mp4?_nc_cat=111&_nc_oc=AdoAgK1y6CY1xIAoyqfRA8CbdVB1IU7WkPOnM8BNVBirtVpduKUtUUJ9khGcvZ7XB9Y&_nc_sid=8bf8fe&_nc_ht=video.fsgn5-11.fna.fbcdn.net&_nc_ohc=T98g980kMUgQ7kNvwEfr5Lq&efg=eyJ2ZW5jb2RlX3RhZyI6Inhwdl9wcm9ncmVzc2l2ZS5WSV9VU0VDQVNFX1BST0RVQ1RfVFlQRS4uQzMuMzYwLnN2ZV9zZCIsInhwdl9hc3NldF9pZCI6MjE1OTkxMTA2ODA3ODY5NCwiYXNzZXRfYWdlX2RheXMiOjI0LCJ2aV91c2VjYXNlX2lkIjoxMDEzOSwiZHVyYXRpb25fcyI6NjYsInVybGdlbl9zb3VyY2UiOiJ3d3cifQ%3D%3D&ccb=17-1&_nc_gid=Bp1XYkM11Sb96VrtMEK0aA&_nc_ss=7a389&_nc_zt=28&oh=00_Af00-DcKuVzSV4Vb5j3GiYoPBSTONOrPtNZtECLsvy-Fmg&oe=69DAD52B | K10: shop.try-forge.com | L10: 132584606613853
A11: 905282632379710 | B11: Forge Men | C11: 46094 | D11: Image | E11: ⏰LAST CHANCE!⏰Sale Ends at Midnight... | F11: BIGGEST Spring Sale EVER! Get 50% OFF our Beef Organ Complex, PLUS an EXTRA 20% with code ‘SPRING20’! Our Beef Organ Complex: ✔️Crushes afternoon energy crashes FAST ✔️Supports healthy testosterone & masculine drive ✔️Sharpens focus and clears brain fog ✔️Helps you go from “dragging through the day” to “firing on all cylinders” Don’t let this one-time deal slip away... an offer this big won’t come back a second time! Tap the button below to get your discount now 👇 | G11: BIGGEST Sale Of The Year! | H11: https://secure.try-forge.com/bridge-a1-simple | I11: Shop now | J11: https://scontent.fsgn5-10.fna.fbcdn.net/v/t39.35426-6/650657925_2277926586029021_2430066128123840261_n.jpg?stp=dst-jpg_s600x600_tt6&_nc_cat=106&ccb=1-7&_nc_sid=c53f8f&_nc_ohc=0zVbOY4nTd8Q7kNvwFWxVeX&_nc_oc=AdrrNFguGy84gxGVWExFgk40BysNqz1lc049_s6OKJsAECvyAkD89PF9LL6Vx9jjcKI&_nc_zt=14&_nc_ht=scontent.fsgn5-10.fna&_nc_gid=Bp1XYkM11Sb96VrtMEK0aA&_nc_ss=7a389&oh=00_Af0ABjl00f9O9NSA2N11ZnRA5YOWYwEvG9hIN3n11FuT_g&oe=69DAFF28 | K11: shop.try-forge.com | L11: 132584606613853
A12: 902392829230146 | B12: Forge Men | C12: 46094 | D12: Image | E12: ⏰LAST CHANCE!⏰Sale Ends at Midnight... | F12: BIGGEST Spring Sale EVER! Get 50% OFF our Beef Organ Complex, PLUS an EXTRA 20% with code ‘SPRING20’! Our Beef Organ Complex: ✔️Crushes afternoon energy crashes FAST ✔️Supports healthy testosterone & masculine drive ✔️Sharpens focus and clears brain fog ✔️Helps you go from “dragging through the day” to “firing on all cylinders” Don’t let this one-time deal slip away... an offer this big won’t come back a second time! Tap the button below to get your discount now 👇 | G12: BIGGEST Sale Of The Year! | H12: https://secure.try-forge.com/bridge-a1-simple | I12: Shop now | J12: https://scontent.fsgn5-5.fna.fbcdn.net/v/t39.35426-6/650255937_879864838360202_1793124271261789682_n.jpg?stp=dst-jpg_s600x600_tt6&_nc_cat=108&ccb=1-7&_nc_sid=c53f8f&_nc_ohc=buKSq7RQnRwQ7kNvwHHfuUy&_nc_oc=AdoDvXp7le-izn3v--fvt04ck2oKIbx8VFGDDNAkdx0novc1Zap74SfNrVdmqt0jidM&_nc_zt=14&_nc_ht=scontent.fsgn5-5.fna&_nc_gid=Bp1XYkM11Sb96VrtMEK0aA&_nc_ss=7a389&oh=00_Af0pXA-TGelc8LlNe-pjdvPOQSUq7L8n5j63FEJTqavFdQ&oe=69DAFE77 | K12: shop.try-forge.com | L12: 132584606613853
A13: 1481656907003862 | B13: Forge Men | C13: 46094 | D13: Image | E13: ⏰LAST CHANCE!⏰Sale Ends at Midnight... | F13: BIGGEST Spring Sale EVER! Get 50% OFF our Beef Organ Complex, PLUS an EXTRA 20% with code ‘SPRING20’! Our Beef Organ Complex: ✔️Crushes afternoon energy crashes FAST ✔️Supports healthy testosterone & masculine drive ✔️Sharpens focus and clears brain fog ✔️Helps you go from “dragging through the day” to “firing on all cylinders” Don’t let this one-time deal slip away... an offer this big won’t come back a second time! Tap the button below to get your discount now 👇 | G13: BIGGEST Sale Of The Year! | H13: https://secure.try-forge.com/bridge-a1-simple | I13: Shop now | J13: https://scontent.fsgn5-10.fna.fbcdn.net/v/t39.35426-6/649889788_1699320851449282_2840904895628147779_n.jpg?stp=dst-jpg_s600x600_tt6&_nc_cat=106&ccb=1-7&_nc_sid=c53f8f&_nc_ohc=a6Ok2NLNY0kQ7kNvwE57aYr&_nc_oc=AdpYI1GepwgUEYJyIZyBs081WbF--iBjl4z_WHMpRESgdapspICJ35yDYSqILq4FSJw&_nc_zt=14&_nc_ht=scontent.fsgn5-10.fna&_nc_gid=Bp1XYkM11Sb96VrtMEK0aA&_nc_ss=7a389&oh=00_Af1DR7QUa_teJDgfQuIJvO8Oyi3Z1Z8bxG011cUCowPfVg&oe=69DB09CF | K13: shop.try-forge.com | L13: 132584606613853
A14: 1284198983637393 | B14: Forge Men | C14: 46094 | D14: Image | E14: ⏰LAST CHANCE!⏰Sale Ends at Midnight... | F14: 🌼BIGGEST Spring Sale EVER!🌼 Get 50% OFF our Beef Tallow Balm, PLUS an EXTRA 20% with code 'SPRING20'! Our Beef Tallow Balm: ✔️Tightens wrinkles QUICKLY ✔️Reduces eye bags and dark spots ✔️Makes your skin thicker, stronger, & hydrated ✔️Helps you go from "tired face" to "sharp & refreshed" Don’t let this one-time deal slip away... an offer this big won’t come back a second time! Tap the button below to get your discount now 👇 | G14: BIGGEST Sale Of The Year! | H14: https://shop.try-forge.com/mens-lifestyle-essentials-1 | I14: Shop now | J14: https://scontent.fsgn5-12.fna.fbcdn.net/v/t39.35426-6/650799648_1311126447742807_6393639188288997208_n.jpg?stp=dst-jpg_s600x600_tt6&_nc_cat=105&ccb=1-7&_nc_sid=c53f8f&_nc_ohc=W4VJHuqu9D8Q7kNvwFAnarK&_nc_oc=AdqW2UYMAxSILtfVqjPc9JD4waEjlfycQtxhTZR08SJPYV6BiZY8__JtTYUl0VtpuqE&_nc_zt=14&_nc_ht=scontent.fsgn5-12.fna&_nc_gid=Bp1XYkM11Sb96VrtMEK0aA&_nc_ss=7a389&oh=00_Af3GJdhkP9wNOUtaw4DJCgblEO5U9MPmPzQvKaivwQaP4A&oe=69DAE9EF | K14: shop.try-forge.com | L14: 132584606613853
A15: 945618348165381 | B15: Forge Men | C15: 46099 | D15: Image | E15: ⏰LAST CHANCE!⏰Sale Ends at Midnight... | F15: 🌼BIGGEST Spring Sale EVER!🌼 Get 50% OFF our Beef Tallow Balm, PLUS an EXTRA 20% with code 'SPRING20'! Our Beef Tallow Balm: ✔️Tightens wrinkles QUICKLY ✔️Reduces eye bags and dark spots ✔️Makes your skin thicker, stronger, & hydrated ✔️Helps you go from "tired face" to "sharp & refreshed" Don’t let this one-time deal slip away... an offer this big won’t come back a second time! Tap the button below to get your discount now 👇 | G15: BIGGEST Sale Of The Year! | H15: https://shop.try-forge.com/mens-lifestyle-essentials-1 | I15: Shop now | J15: https://scontent.fsgn5-5.fna.fbcdn.net/v/t39.35426-6/649990795_1627752558575053_3330639560471977331_n.jpg?stp=dst-jpg_s600x600_tt6&_nc_cat=102&ccb=1-7&_nc_sid=c53f8f&_nc_ohc=YxUKKSdm1swQ7kNvwHA278N&_nc_oc=Adrcv8pu3HG0sosA5klZT5d-64EH9Xof5fnQsXW4CD8z11j8eR8X4A8evCgYOX7tpVs&_nc_zt=14&_nc_ht=scontent.fsgn5-5.fna&_nc_gid=Bp1XYkM11Sb96VrtMEK0aA&_nc_ss=7a389&oh=00_Af25d5oPIL0eYQVklBKK8uJkrPpIsLtXI2eAviizWmnA8Q&oe=69DB0388 | K15: shop.try-forge.com | L15: 132584606613853
A16: 948710774475097 | B16: Forge Men | C16: 46113 | D16: Image | E16: ⏰LAST CHANCE!⏰Sale Ends Soon... | F16: 🐰 BIGGEST Easter Sale EVER! 🥚 Get 50% OFF our Beef Tallow Balm, PLUS an EXTRA 20% with code 'EASTER20'! Our Beef Tallow Balm: ✔️Tightens wrinkles QUICKLY ✔️Reduces eye bags and dark spots ✔️Makes your skin thicker, stronger, & hydrated ✔️Helps you go from "tired face" to "sharp & refreshed" Don’t let this one-time deal slip away... an offer this big won’t come back a second time! Tap the button below to get your discount now 👇 | G16: BIGGEST Sale Of The Year! | H16: https://shop.try-forge.com/mens-lifestyle-essentials-1 | I16: Shop now | J16: https://scontent.fsgn5-10.fna.fbcdn.net/v/t39.35426-6/659051336_1626736981980218_8729193912544773036_n.jpg?stp=dst-jpg_s600x600_tt6&_nc_cat=106&ccb=1-7&_nc_sid=c53f8f&_nc_ohc=y-OJsD62w6MQ7kNvwFY_x1H&_nc_oc=AdpHgtOTXyYGnuIfzkedn1gh2sbGjBEzCQ6_rhilDwEzxWTzMsVrtka_eGTKvMJmgkU&_nc_zt=14&_nc_ht=scontent.fsgn5-10.fna&_nc_gid=Bp1XYkM11Sb96VrtMEK0aA&_nc_ss=7a389&oh=00_Af2kg2Up0uT22m3cJgMdkI9fvmDMTT3L6xOfBlvQYwP4GA&oe=69DAF159 | K16: shop.try-forge.com | L16: 132584606613853
A17: 1252746123180726 | B17: Forge Men | C17: 46114 | D17: Video | E17: ⏰LAST CHANCE!⏰Sale Ends Soon... | F17: 🐰 BIGGEST Easter Sale EVER! 🥚 Get 50% OFF our Beef Tallow Balm, PLUS an EXTRA 20% with code 'EASTER20'! Our Beef Tallow Balm: ✔️Tightens wrinkles QUICKLY ✔️Reduces eye bags and dark spots ✔️Makes your skin thicker, stronger, & hydrated ✔️Helps you go from "tired face" to "sharp & refreshed" Don’t let this one-time deal slip away... an offer this big won’t come back a second time! Tap the button below to get your discount now 👇 | G17: BIGGEST Sale Of The Year! | H17: https://shop.try-forge.com/mens-lifestyle-essentials-1 | I17: Shop now | J17: https://video.fsgn5-5.fna.fbcdn.net/o1/v/t2/f2/m412/AQPihg-jfLvQ3NTjy4_xr3vcm5kqoe8XLYv1sYPLf8c1cJm9TbdbpJkVakgPM6r4U4nOADPR4BxFs9ZvErTioein8VcS4pKmjlkMBH7O5A.mp4?_nc_cat=102&_nc_oc=Adq5NYjMThc4LPe0nLrbIseZku-Vnj24mX-vzURjyO0h8zxu3CeU-HN4CbLn-1kIOQg&_nc_sid=8bf8fe&_nc_ht=video.fsgn5-5.fna.fbcdn.net&_nc_ohc=UrFMfKqpLLIQ7kNvwFsJOW1&efg=eyJ2ZW5jb2RlX3RhZyI6Inhwdl9wcm9ncmVzc2l2ZS5WSV9VU0VDQVNFX1BST0RVQ1RfVFlQRS4uQzMuMzYwLnN2ZV9zZCIsInhwdl9hc3NldF9pZCI6ODMzMDYyNDQ5MDg5OTIyLCJhc3NldF9hZ2VfZGF5cyI6NCwidmlfdXNlY2FzZV9pZCI6MTAxMzksImR1cmF0aW9uX3MiOjY3LCJ1cmxnZW5fc291cmNlIjoid3d3In0%3D&ccb=17-1&_nc_gid=Bp1XYkM11Sb96VrtMEK0aA&_nc_ss=7a389&_nc_zt=28&oh=00_Af2XVHDpQjil7cdBHSGWLify0p60wSRiivzSYwh-azRUfg&oe=69DB09B8 | K17: shop.try-forge.com | L17: 132584606613853
A18: 916239317696652 | B18: Forge Men | C18: 46094 | D18: Image | E18: ⏰LAST CHANCE!⏰Sale Ends at Midnight... | F18: BIGGEST Spring Sale EVER! Get 50% OFF our Beef Organ Complex, PLUS an EXTRA 20% with code ‘SPRING20’! Our Beef Organ Complex: ✔️Crushes afternoon energy crashes FAST ✔️Supports healthy testosterone & masculine drive ✔️Sharpens focus and clears brain fog ✔️Helps you go from “dragging through the day” to “firing on all cylinders” Don’t let this one-time deal slip away... an offer this big won’t come back a second time! Tap the button below to get your discount now 👇 | G18: BIGGEST Sale Of The Year! | H18: https://secure.try-forge.com/bridge-a1-simple | I18: Shop now | J18: https://scontent.fsgn5-12.fna.fbcdn.net/v/t39.35426-6/651002120_921382560536549_2502828550064374180_n.jpg?stp=dst-jpg_s600x600_tt6&_nc_cat=105&ccb=1-7&_nc_sid=c53f8f&_nc_ohc=MBOi8Dyr1hsQ7kNvwEhUgtN&_nc_oc=Adrrv3OPweQ9x6NPhZVhWmR0T4DH40A4koBW--NPZne-nEIioYT-r8_RyatUtVcDDpM&_nc_zt=14&_nc_ht=scontent.fsgn5-12.fna&_nc_gid=Bp1XYkM11Sb96VrtMEK0aA&_nc_ss=7a389&oh=00_Af12oo-AsvPHi50n5DGo3BRYvHZ5N5128ePsiSciHdYkdQ&oe=69DADECC | K18: shop.try-forge.com | L18: 132584606613853
A19: 1680981013063841 | B19: Forge Men | C19: 46094 | D19: Image | E19: ⏰LAST CHANCE!⏰Sale Ends at Midnight... | F19: BIGGEST Spring Sale EVER! Get 50% OFF our Beef Organ Complex, PLUS an EXTRA 20% with code ‘SPRING20’! Our Beef Organ Complex: ✔️Crushes afternoon energy crashes FAST ✔️Supports healthy testosterone & masculine drive ✔️Sharpens focus and clears brain fog ✔️Helps you go from “dragging through the day” to “firing on all cylinders” Don’t let this one-time deal slip away... an offer this big won’t come back a second time! Tap the button below to get your discount now 👇 | G19: BIGGEST Sale Of The Year! | H19: https://secure.try-forge.com/bridge-a1-simple | I19: Shop now | J19: https://scontent.fsgn5-3.fna.fbcdn.net/v/t39.35426-6/651727991_1893364691364283_2807277306464139448_n.jpg?stp=dst-jpg_s600x600_tt6&_nc_cat=104&ccb=1-7&_nc_sid=c53f8f&_nc_ohc=YycorbmiXHUQ7kNvwGEqKPk&_nc_oc=AdosoPjILl9YVV4p7TQYtnvmNoCwmJVTRdfq6FsW58DDyLLVqJSqsyayppRGAUcqYSk&_nc_zt=14&_nc_ht=scontent.fsgn5-3.fna&_nc_gid=Bp1XYkM11Sb96VrtMEK0aA&_nc_ss=7a389&oh=00_Af2ALJN6WBfyE1ZGofa8C6AhWhhKMKNRX_iJiGkI9LpOzA&oe=69DAD303 | K19: shop.try-forge.com | L19: 132584606613853
A20: 2176465009781882 | B20: Forge Men | C20: 46115 | D20: Video | E20: ⏰LAST CHANCE!⏰Sale Ends Soon... | F20: 🐰 BIGGEST Easter Sale EVER! 🥚 Get 50% OFF our Beef Tallow Balm, PLUS an EXTRA 20% with code 'EASTER20'! Our Beef Tallow Balm: ✔️Tightens wrinkles QUICKLY ✔️Reduces eye bags and dark spots ✔️Makes your skin thicker, stronger, & hydrated ✔️Helps you go from "tired face" to "sharp & refreshed" Don’t let this one-time deal slip away... an offer this big won’t come back a second time! Tap the button below to get your discount now 👇 | G20: BIGGEST Sale Of The Year! | H20: https://shop.try-forge.com/mens-lifestyle-essentials-1 | I20: Shop now | J20: https://video.fsgn5-10.fna.fbcdn.net/o1/v/t2/f2/m412/AQPyYhVC5sSOTwk_h_H-oKaNDeErPwfOeDSwB7im2gfXB3NmwxqiPqqhs97-SogYD7P-7pU8Zsrudsf6aknEVrVJX9N3ZmtVTzhFRPRvWA.mp4?_nc_cat=101&_nc_oc=AdqqAw1-yw-RqtLOsPCKkUS-fBrbGZDUfsbrmC1XSzJOiCRml0L-ngl_EPLOjKDDkp0&_nc_sid=8bf8fe&_nc_ht=video.fsgn5-10.fna.fbcdn.net&_nc_ohc=XtokDp2joH4Q7kNvwFtKfQ3&efg=eyJ2ZW5jb2RlX3RhZyI6Inhwdl9wcm9ncmVzc2l2ZS5WSV9VU0VDQVNFX1BST0RVQ1RfVFlQRS4uQzMuMzYwLnN2ZV9zZCIsInhwdl9hc3NldF9pZCI6MzQ3NDUyMDc0MjE3NjA3OTksImFzc2V0X2FnZV9kYXlzIjo0LCJ2aV91c2VjYXNlX2lkIjoxMDEzOSwiZHVyYXRpb25fcyI6ODEsInVybGdlbl9zb3VyY2UiOiJ3d3cifQ%3D%3D&ccb=17-1&_nc_gid=Bp1XYkM11Sb96VrtMEK0aA&_nc_ss=7a389&_nc_zt=28&oh=00_Af1p3zk5webgnxglBVbBs1s2n1YSnnjRJ0YJ0ncI6n1kvQ&oe=69DAE4A9 | K20: shop.try-forge.com | L20: 132584606613853
A21: 947524904899748 | B21: Forge Men | C21: 46113 | D21: Image | E21: ⏰LAST CHANCE!⏰Sale Ends Soon... | F21: 🐰 BIGGEST Easter Sale EVER! 🥚 Get 50% OFF our Beef Tallow Balm, PLUS an EXTRA 20% with code 'EASTER20'! Our Beef Tallow Balm: ✔️Tightens wrinkles QUICKLY ✔️Reduces eye bags and dark spots ✔️Makes your skin thicker, stronger, & hydrated ✔️Helps you go from "tired face" to "sharp & refreshed" Don’t let this one-time deal slip away... an offer this big won’t come back a second time! Tap the button below to get your discount now 👇 | G21: BIGGEST Sale Of The Year! | H21: https://shop.try-forge.com/mens-lifestyle-essentials-1 | I21: Shop now | J21: https://scontent.fsgn5-11.fna.fbcdn.net/v/t39.35426-6/658350462_936511149092790_9139663075594128929_n.jpg?stp=dst-jpg_s600x600_tt6&_nc_cat=110&ccb=1-7&_nc_sid=c53f8f&_nc_ohc=xz3G_kUxDeIQ7kNvwFOQRhx&_nc_oc=AdqodAwQ12pBqWXd8REx2NlNg69OMY074LedFIkMqmf3xutl9jNY9lPptGN6Vrfwn4c&_nc_zt=14&_nc_ht=scontent.fsgn5-11.fna&_nc_gid=Bp1XYkM11Sb96VrtMEK0aA&_nc_ss=7a389&oh=00_Af31MKjSIPijCgeGbm3XDOYm5NmNVRIlHRDH-LYPn2hvJQ&oe=69DAD74A | K21: shop.try-forge.com | L21: 132584606613853
A22: 2053124882086804 | B22: Forge Men | C22: 46094 | D22: Video | E22: ⏰LAST CHANCE!⏰Sale Ends at Midnight... | F22: 🌼BIGGEST Spring Sale EVER!🌼 Get 50% OFF our Beef Tallow Balm, PLUS an EXTRA 20% with code 'SPRING20'! Our Beef Tallow Balm: ✔️Tightens wrinkles QUICKLY ✔️Reduces eye bags and dark spots ✔️Makes your skin thicker, stronger, & hydrated ✔️Helps you go from "tired face" to "sharp & refreshed" Don’t let this one-time deal slip away... an offer this big won’t come back a second time! Tap the button below to get your discount now 👇 | G22: BIGGEST Sale Of The Year! | H22: https://shop.try-forge.com/mens-lifestyle-essentials-1 | I22: Shop now | J22: https://video.fsgn5-3.fna.fbcdn.net/o1/v/t2/f2/m412/AQMnHzqx1BM-ixJ3zyMIXsL-nB8WcQnW1TLZEWJ1IwbRFN-g1CCHAkviYj1M8WGPWz91mkSekq9KvJx2VqmNqABrLCgbRbhS-NFvg7GJCg.mp4?_nc_cat=104&_nc_oc=Adr9azCOhO2cSqeYKgA08hc0JCPFzq75YeDem-S-DeAMNssJGoV6z7ulGCnN7eh3-UE&_nc_sid=8bf8fe&_nc_ht=video.fsgn5-3.fna.fbcdn.net&_nc_ohc=6OQ6ncsA2HAQ7kNvwEl-k6m&efg=eyJ2ZW5jb2RlX3RhZyI6Inhwdl9wcm9ncmVzc2l2ZS5WSV9VU0VDQVNFX1BST0RVQ1RfVFlQRS4uQzMuMzYwLnN2ZV9zZCIsInhwdl9hc3NldF9pZCI6MTQ4Nzg1NDA4Mjk0NTQ0MCwiYXNzZXRfYWdlX2RheXMiOjI0LCJ2aV91c2VjYXNlX2lkIjoxMDEzOSwiZHVyYXRpb25fcyI6NjcsInVybGdlbl9zb3VyY2UiOiJ3d3cifQ%3D%3D&ccb=17-1&_nc_gid=Bp1XYkM11Sb96VrtMEK0aA&_nc_ss=7a389&_nc_zt=28&oh=00_Af1aiaa7E98C1JXHpYO6tRL_6jG51R1VhTCXECjyZJYCBA&oe=69DAE346 | K22: shop.try-forge.com | L22: 132584606613853
A23: 3711652668976619 | B23: Forge Men | C23: 46094 | D23: Image | E23: ⏰LAST CHANCE!⏰Sale Ends at Midnight... | F23: BIGGEST Spring Sale EVER! Get 50% OFF our Beef Organ Complex, PLUS an EXTRA 20% with code ‘SPRING20’! Our Beef Organ Complex: ✔️Crushes afternoon energy crashes FAST ✔️Supports healthy testosterone & masculine drive ✔️Sharpens focus and clears brain fog ✔️Helps you go from “dragging through the day” to “firing on all cylinders” Don’t let this one-time deal slip away... an offer this big won’t come back a second time! Tap the button below to get your discount now 👇 | G23: BIGGEST Sale Of The Year! | H23: https://secure.try-forge.com/bridge-a1-simple | I23: Shop now | J23: https://scontent.fsgn5-8.fna.fbcdn.net/v/t39.35426-6/651190181_966175842724266_1564437706204956915_n.jpg?stp=dst-jpg_s600x600_tt6&_nc_cat=109&ccb=1-7&_nc_sid=c53f8f&_nc_ohc=QxZEOZVI128Q7kNvwH2YRzc&_nc_oc=Adrezunt7qGnYE01J7MnGZRTVAXj1BztMDeqxVnOv-xA53uVs1YZnjVNriUNXZBnn5s&_nc_zt=14&_nc_ht=scontent.fsgn5-8.fna&_nc_gid=Bp1XYkM11Sb96VrtMEK0aA&_nc_ss=7a389&oh=00_Af1x_ZwyjHhCzn6LdsRJXtFQsXEMFee688f-tyGEga7Aqw&oe=69DAF090 | K23: shop.try-forge.com | L23: 132584606613853
A24: 913434535005139 | B24: Forge Men | C24: 46098 | D24: Video | E24: ⏰LAST CHANCE!⏰Sale Ends at Midnight... | F24: 🌼BIGGEST Spring Sale EVER!🌼 Get 50% OFF our Beef Tallow Balm, PLUS an EXTRA 20% with code 'SPRING20'! Our Beef Tallow Balm: ✔️Tightens wrinkles QUICKLY ✔️Reduces eye bags and dark spots ✔️Makes your skin thicker, stronger, & hydrated ✔️Helps you go from "tired face" to "sharp & refreshed" Don’t let this one-time deal slip away... an offer this big won’t come back a second time! Tap the button below to get your discount now 👇 | G24: BIGGEST Sale Of The Year! | H24: https://shop.try-forge.com/mens-lifestyle-essentials-1 | I24: Shop now | J24: https://video.fsgn5-12.fna.fbcdn.net/o1/v/t2/f2/m412/AQNnYOHdLZwKZqJ-_AnVd5N7OIYGzn7SzffAfWUPCQcgiHbhXgC1ABoNhmTdGd3s3iMH4yyUXRH1nTcNk0qTEgUSzLowxvaisfKQc9z_zg.mp4?_nc_cat=105&_nc_oc=AdoZzNFmapZG99_MrnSqQqCPx1INeIKlTfNO83CMb8ga3DXi7_3DmINlKEtFn6FAV4A&_nc_sid=8bf8fe&_nc_ht=video.fsgn5-12.fna.fbcdn.net&_nc_ohc=ohoCL4Vbq5sQ7kNvwEr6th9&efg=eyJ2ZW5jb2RlX3RhZyI6Inhwdl9wcm9ncmVzc2l2ZS5WSV9VU0VDQVNFX1BST0RVQ1RfVFlQRS4uQzMuMzYwLnN2ZV9zZCIsInhwdl9hc3NldF9pZCI6MTMxODI5MjMwNjc4ODM4OSwiYXNzZXRfYWdlX2RheXMiOjIxLCJ2aV91c2VjYXNlX2lkIjoxMDEzOSwiZHVyYXRpb25fcyI6NjQsInVybGdlbl9zb3VyY2UiOiJ3d3cifQ%3D%3D&ccb=17-1&_nc_gid=Bp1XYkM11Sb96VrtMEK0aA&_nc_ss=7a389&_nc_zt=28&oh=00_Af3sQQJxFV74WviiqqY_HQPbcCPzyvqCXOxKvqfkDSVhCA&oe=69DAEA9D | K24: shop.try-forge.com | L24: 132584606613853
A25: 2300706067088213 | B25: Forge Men | C25: 46113 | D25: Image | E25: ⏰LAST CHANCE!⏰Sale Ends Soon... | F25: 🐰 BIGGEST Easter Sale EVER! 🥚 Get 50% OFF our Beef Tallow Balm, PLUS an EXTRA 20% with code 'EASTER20'! Our Beef Tallow Balm: ✔️Tightens wrinkles QUICKLY ✔️Reduces eye bags and dark spots ✔️Makes your skin thicker, stronger, & hydrated ✔️Helps you go from "tired face" to "sharp & refreshed" Don’t let this one-time deal slip away... an offer this big won’t come back a second time! Tap the button below to get your discount now 👇 | G25: BIGGEST Sale Of The Year! | H25: https://shop.try-forge.com/mens-lifestyle-essentials-1 | I25: Shop now | J25: https://scontent.fsgn5-3.fna.fbcdn.net/v/t39.35426-6/662096970_2220988795337986_6661381080865781676_n.jpg?stp=dst-jpg_s600x600_tt6&_nc_cat=104&ccb=1-7&_nc_sid=c53f8f&_nc_ohc=XIF8YRHumy8Q7kNvwHYeE3A&_nc_oc=AdokSvuZHTQzpUFF9h_y9BBKaNiNQe8FCdocAB2w0SjcLafG8A8fndNZQvQJO8yM2EQ&_nc_zt=14&_nc_ht=scontent.fsgn5-3.fna&_nc_gid=Bp1XYkM11Sb96VrtMEK0aA&_nc_ss=7a389&oh=00_Af3bWGR_todRFDiYRFQhgQ0qjOABKiFGBlFS9dWh5BwNyA&oe=69DB0A26 | K25: shop.try-forge.com | L25: 132584606613853
A26: 1166126992242272 | B26: Forge Men | C26: 46114 | D26: Video | E26: ⏰LAST CHANCE!⏰Sale Ends Soon... | F26: 🐰 BIGGEST Easter Sale EVER! 🥚 Get 50% OFF our Beef Tallow Balm, PLUS an EXTRA 20% with code 'EASTER20'! Our Beef Tallow Balm: ✔️Tightens wrinkles QUICKLY ✔️Reduces eye bags and dark spots ✔️Makes your skin thicker, stronger, & hydrated ✔️Helps you go from "tired face" to "sharp & refreshed" Don’t let this one-time deal slip away... an offer this big won’t come back a second time! Tap the button below to get your discount now 👇 | G26: BIGGEST Sale Of The Year! | H26: https://shop.try-forge.com/mens-lifestyle-essentials-1 | I26: Shop now | J26: https://video.fsgn5-10.fna.fbcdn.net/o1/v/t2/f2/m412/AQMZWIeWpLHc2kJknSGyrahaAnCYc95wrHsh4Q1bXXYPn_U3kXo3tSCqnwOsSRjz_WAe80GH3wCC9Wec4qsHU2lttit0lsHRllq4fpXJIQ.mp4?_nc_cat=101&_nc_oc=AdoCiHMWFWsTik5oT6vrgnxWVtT0m8p7WSECJ5UbCWBAv6Hti50t7_1Kp9cK6JWQKbo&_nc_sid=8bf8fe&_nc_ht=video.fsgn5-10.fna.fbcdn.net&_nc_ohc=uHrUsMi-ZTQQ7kNvwF2EfNG&efg=eyJ2ZW5jb2RlX3RhZyI6Inhwdl9wcm9ncmVzc2l2ZS5WSV9VU0VDQVNFX1BST0RVQ1RfVFlQRS4uQzMuMzYwLnN2ZV9zZCIsInhwdl9hc3NldF9pZCI6MTg0MDM5MDMwMzMxNjkyMiwiYXNzZXRfYWdlX2RheXMiOjQsInZpX3VzZWNhc2VfaWQiOjEwMTM5LCJkdXJhdGlvbl9zIjoxNTIsInVybGdlbl9zb3VyY2UiOiJ3d3cifQ%3D%3D&ccb=17-1&_nc_gid=Bp1XYkM11Sb96VrtMEK0aA&_nc_ss=7a389&_nc_zt=28&oh=00_Af19JxgbshrkP8ITEoIB5pL7LTdBgpjiN9HgQvw7xxgKXg&oe=69DAED51 | K26: shop.try-forge.com | L26: 132584606613853
A27: 1761288351504493 | B27: Forge Men | C27: 46114 | D27: Video | E27: ⏰LAST CHANCE!⏰Sale Ends Soon... | F27: 🐰 BIGGEST Easter Sale EVER! 🥚 Get 50% OFF our Beef Tallow Balm, PLUS an EXTRA 20% with code 'EASTER20'! Our Beef Tallow Balm: ✔️Tightens wrinkles QUICKLY ✔️Reduces eye bags and dark spots ✔️Makes your skin thicker, stronger, & hydrated ✔️Helps you go from "tired face" to "sharp & refreshed" Don’t let this one-time deal slip away... an offer this big won’t come back a second time! Tap the button below to get your discount now 👇 | G27: BIGGEST Sale Of The Year! | H27: https://shop.try-forge.com/mens-lifestyle-essentials-1 | I27: Shop now | J27: https://video.fsgn5-5.fna.fbcdn.net/o1/v/t2/f2/m412/AQNjoK3LGaJoTEF0ErrA2J6hRvdb1AmRW6lYgiykjQOStAVnU-7ZqGv1xxtL7q2QeMtBi-otA3s0ZRByRPCxFSUSq0sR59O48VZ6La5Rpw.mp4?_nc_cat=108&_nc_oc=AdqXsaetrQntcxEO8SsRfGzu7u-B4vbXymDjvjOlEt_x0moqLsla0FK4SFnfpOvHaiY&_nc_sid=8bf8fe&_nc_ht=video.fsgn5-5.fna.fbcdn.net&_nc_ohc=2fQx_zpBH1wQ7kNvwEWuZZQ&efg=eyJ2ZW5jb2RlX3RhZyI6Inhwdl9wcm9ncmVzc2l2ZS5WSV9VU0VDQVNFX1BST0RVQ1RfVFlQRS4uQzMuMzU2LnN2ZV9zZCIsInhwdl9hc3NldF9pZCI6OTYyODg2OTUyNzUwODk1LCJhc3NldF9hZ2VfZGF5cyI6NCwidmlfdXNlY2FzZV9pZCI6MTAxMzksImR1cmF0aW9uX3MiOjYwLCJ1cmxnZW5fc291cmNlIjoid3d3In0%3D&ccb=17-1&_nc_gid=Bp1XYkM11Sb96VrtMEK0aA&_nc_ss=7a389&_nc_zt=28&oh=00_Af07mVS_fkZyQpRm13wF6nQWgLF5Mhu0hg1y3Y8TAzDkoQ&oe=69DB0312 | K27: shop.try-forge.com | L27: 132584606613853
A28: 1967867417159438 | B28: Forge Men | C28: 46094 | D28: Image | E28: ⏰LAST CHANCE!⏰Sale Ends at Midnight... | F28: BIGGEST Spring Sale EVER! Get 50% OFF our Beef Organ Complex, PLUS an EXTRA 20% with code ‘SPRING20’! Our Beef Organ Complex: ✔️Crushes afternoon energy crashes FAST ✔️Supports healthy testosterone & masculine drive ✔️Sharpens focus and clears brain fog ✔️Helps you go from “dragging through the day” to “firing on all cylinders” Don’t let this one-time deal slip away... an offer this big won’t come back a second time! Tap the button below to get your discount now 👇 | G28: BIGGEST Sale Of The Year! | H28: https://secure.try-forge.com/bridge-a1-simple | I28: Shop now | J28: https://scontent.fsgn5-12.fna.fbcdn.net/v/t39.35426-6/652300469_1640641947113661_2141458782018142170_n.jpg?stp=dst-jpg_s600x600_tt6&_nc_cat=105&ccb=1-7&_nc_sid=c53f8f&_nc_ohc=cOH06Ga7nAYQ7kNvwETRhGs&_nc_oc=AdpnFByDzpJq3dDOidNYP_YhX1y7THILQOiKrvim8hL3FRHu33SYTUIVTAk7RqkNNoI&_nc_zt=14&_nc_ht=scontent.fsgn5-12.fna&_nc_gid=Bp1XYkM11Sb96VrtMEK0aA&_nc_ss=7a389&oh=00_Af0TtwysOhWZiowEsgVtqhweq-Jf3YI3h17fqOntNNv2JA&oe=69DB055B | K28: shop.try-forge.com | L28: 132584606613853
A29: 1665648061228868 | B29: Forge Men | C29: 46114 | D29: Image | E29: Attractive Skin in 3 Weeks | F29: How can beef tallow rejuvenate and revitalize your skin, making you look years younger quickly? Because it contains 12 out of the 16 essential nutrients your skin needs. Vitamins, fatty acids, and so much more... ✔ Tightens wrinkles QUICKLY ✔ Hydrates and repairs the skin ✔ Clears up dark spots ✔ Reduces eye bags ✔ 100% natural Want to try it out? Click the link below to get your pure beef tallow balm now! 👇 | G29: Very Few Men Know This... | H29: https://shop.try-forge.com/listicle-eyebags | I29: Shop now | J29: https://scontent.fsgn5-3.fna.fbcdn.net/v/t39.35426-6/663252330_1278136693643455_1861334060485578405_n.jpg?stp=dst-jpg_s600x600_tt6&_nc_cat=104&ccb=1-7&_nc_sid=c53f8f&_nc_ohc=NZvxxD1AdckQ7kNvwFPxGps&_nc_oc=AdpmqARs3cVLDss6LSuaA4vh4UmNNrSPvGZ8kfvQesfm292GwxKz5SQWOQIK-qowJ0M&_nc_zt=14&_nc_ht=scontent.fsgn5-3.fna&_nc_gid=Bp1XYkM11Sb96VrtMEK0aA&_nc_ss=7a389&oh=00_Af1MwjE-S4LIpzx05Be4vEwjgd-tiZdPdfytGtmbWl8rSA&oe=69DB0706 | K29: shop.try-forge.com | L29: 132584606613853
A30: 892568207139827 | B30: Forge Men | C30: 46113 | D30: Image | E30: Attractive Skin in 3 Weeks | F30: How can beef tallow rejuvenate and revitalize your skin, making you look years younger quickly? Because it contains 12 out of the 16 essential nutrients your skin needs. Vitamins, fatty acids, and so much more... ✔ Tightens wrinkles QUICKLY ✔ Hydrates and repairs the skin ✔ Clears up dark spots ✔ Reduces eye bags ✔ 100% natural Want to try it out? Click the link below to get your pure beef tallow balm now! 👇 | G30: Very Few Men Know This... | H30: https://shop.try-forge.com/listicle-eyebags | I30: Shop now | J30: https://scontent.fsgn5-5.fna.fbcdn.net/v/t39.35426-6/659790895_2765316850498612_3125233694347133088_n.jpg?stp=dst-jpg_s600x600_tt6&_nc_cat=100&ccb=1-7&_nc_sid=c53f8f&_nc_ohc=vwZDMol0aAkQ7kNvwE2iQsE&_nc_oc=AdrXKASg15sfVq7eqnIBml78hSeayTWPfDZg7Lg_p51wqlgMEw7dE9U8aVCLT9dmHEc&_nc_zt=14&_nc_ht=scontent.fsgn5-5.fna&_nc_gid=Bp1XYkM11Sb96VrtMEK0aA&_nc_ss=7a389&oh=00_Af1ZYXsIF54CmlekoF9N4KSvttgqxLJkJp_WrPGB8UMuLw&oe=69DAE076 | K30: shop.try-forge.com | L30: 132584606613853
A31: 914815317850290 | B31: Forge Men | C31: 46114 | D31: Video | E31: ⏰LAST CHANCE!⏰Sale Ends Soon... | F31: 🐰 BIGGEST Easter Sale EVER! 🥚 Get 50% OFF our Beef Tallow Balm, PLUS an EXTRA 20% with code 'EASTER20'! Our Beef Tallow Balm: ✔️Tightens wrinkles QUICKLY ✔️Reduces eye bags and dark spots ✔️Makes your skin thicker, stronger, & hydrated ✔️Helps you go from "tired face" to "sharp & refreshed" Don’t let this one-time deal slip away... an offer this big won’t come back a second time! Tap the button below to get your discount now 👇 | G31: BIGGEST Sale Of The Year! | H31: https://shop.try-forge.com/mens-lifestyle-essentials-1 | I31: Shop now | J31: https://video.fsgn5-11.fna.fbcdn.net/o1/v/t2/f2/m412/AQOos4chBNikLckm6kQCIbxnFb6vYsMHIoYDUdGWQ_tZ-JE9eAUbQK_h4FDg8ueDN7wipYclHhCViXikBs9tIx2iezkeNbKLpPfiNZkIVg.mp4?_nc_cat=111&_nc_oc=AdriFks7dNAUsi2L8T369UOx3IEQ63WVoZZugoTFP5fWfSif-ND4H8n3ExWifI73MFs&_nc_sid=8bf8fe&_nc_ht=video.fsgn5-11.fna.fbcdn.net&_nc_ohc=pB_60uzcwPkQ7kNvwFq7Al9&efg=eyJ2ZW5jb2RlX3RhZyI6Inhwdl9wcm9ncmVzc2l2ZS5WSV9VU0VDQVNFX1BST0RVQ1RfVFlQRS4uQzMuMzU2LnN2ZV9zZCIsInhwdl9hc3NldF9pZCI6MTUwNjc0NTUyNDUwMzk5NiwiYXNzZXRfYWdlX2RheXMiOjQsInZpX3VzZWNhc2VfaWQiOjEwMTM5LCJkdXJhdGlvbl9zIjo1NywidXJsZ2VuX3NvdXJjZSI6Ind3dyJ9&ccb=17-1&_nc_gid=Bp1XYkM11Sb96VrtMEK0aA&_nc_ss=7a389&_nc_zt=28&oh=00_Af3rvJrdGu5ERys_NJrOtUwc1BeGmWcUww9N5aCJxcwtVg&oe=69DAE037 | K31: shop.try-forge.com | L31: 132584606613853
A32: 1.4780247e+15 | B32: Forge Men | C32: 46113 | D32: Image | E32: ⏰LAST CHANCE!⏰Sale Ends Soon... | F32: 🐰 BIGGEST Easter Sale EVER! 🥚 Get 50% OFF our Beef Tallow Balm, PLUS an EXTRA 20% with code 'EASTER20'! Our Beef Tallow Balm: ✔️Tightens wrinkles QUICKLY ✔️Reduces eye bags and dark spots ✔️Makes your skin thicker, stronger, & hydrated ✔️Helps you go from "tired face" to "sharp & refreshed" Don’t let this one-time deal slip away... an offer this big won’t come back a second time! Tap the button below to get your discount now 👇 | G32: BIGGEST Sale Of The Year! | H32: https://shop.try-forge.com/mens-lifestyle-essentials-1 | I32: Shop now | J32: https://scontent.fsgn5-5.fna.fbcdn.net/v/t39.35426-6/658083403_1260362419062828_4946547708521292945_n.jpg?stp=dst-jpg_s600x600_tt6&_nc_cat=100&ccb=1-7&_nc_sid=c53f8f&_nc_ohc=UZcuXMfHLCwQ7kNvwEsxU4w&_nc_oc=AdqjsK2IuYhWVmOiDMSrPRB72EJc9ig5vPdOERCPec1SpHQ13SvJdzWyLEdteQzU3xw&_nc_zt=14&_nc_ht=scontent.fsgn5-5.fna&_nc_gid=ClwIPkHLQ5LFDAxEMsXxxQ&_nc_ss=7a389&oh=00_Af0TpK9QetUYnYdJXW4wd0x-gfI-e8DISB3LSF8lpUimiw&oe=69DAF7A0 | K32: shop.try-forge.com | L32: 132584606613853
A33: 929134080075400 | B33: Forge Men | C33: 46113 | D33: Image | E33: Attractive Skin in 3 Weeks | F33: How can beef tallow rejuvenate and revitalize your skin, making you look years younger quickly? Because it contains 12 out of the 16 essential nutrients your skin needs. Vitamins, fatty acids, and so much more... ✔ Tightens wrinkles QUICKLY ✔ Hydrates and repairs the skin ✔ Clears up dark spots ✔ Reduces eye bags ✔ 100% natural Want to try it out? Click the link below to get your pure beef tallow balm now! 👇 | G33: Very Few Men Know This... | H33: https://shop.try-forge.com/listicle-eyebags | I33: Shop now | J33: https://scontent.fsgn5-8.fna.fbcdn.net/v/t39.35426-6/658357656_1723705045652405_7854580813788767763_n.jpg?stp=dst-jpg_s600x600_tt6&_nc_cat=109&ccb=1-7&_nc_sid=c53f8f&_nc_ohc=Nf5M0KnaK_8Q7kNvwFNNeJk&_nc_oc=AdqNqFiunaGETgXU_W6thRWwcBHFcY_qu8XiLXtI4l15iQEokzG28wcHm70FcIrRoUU&_nc_zt=14&_nc_ht=scontent.fsgn5-8.fna&_nc_gid=ClwIPkHLQ5LFDAxEMsXxxQ&_nc_ss=7a389&oh=00_Af1IvRZwg6OuogAJ9fE5i4jXwAOmlCUfY2cxKlAqgbHINQ&oe=69DAEAC1 | K33: shop.try-forge.com | L33: 132584606613853
A34: 944143921597723 | B34: Forge Men | C34: 46113 | D34: Image | E34: Attractive Skin in 3 Weeks | F34: How can beef tallow rejuvenate and revitalize your skin, making you look years younger quickly? Because it contains 12 out of the 16 essential nutrients your skin needs. Vitamins, fatty acids, and so much more... ✔ Tightens wrinkles QUICKLY ✔ Hydrates and repairs the skin ✔ Clears up dark spots ✔ Reduces eye bags ✔ 100% natural Want to try it out? Click the link below to get your pure beef tallow balm now! 👇 | G34: Very Few Men Know This... | H34: https://shop.try-forge.com/listicle-eyebags | I34: Shop now | J34: https://scontent.fsgn5-8.fna.fbcdn.net/v/t39.35426-6/659811299_3215254672007894_1446292478779220877_n.jpg?stp=dst-jpg_s600x600_tt6&_nc_cat=109&ccb=1-7&_nc_sid=c53f8f&_nc_ohc=iMWwgoh00UoQ7kNvwE3Jqr0&_nc_oc=AdpplIRBfwAjLHaGhBW_6tswUi3UWWnXeO9L_YvXNa9cp-ZnSvzFM0gf8NuU9q0ohwQ&_nc_zt=14&_nc_ht=scontent.fsgn5-8.fna&_nc_gid=ClwIPkHLQ5LFDAxEMsXxxQ&_nc_ss=7a389&oh=00_Af238jarsrrhU9-rwQM10h9dGuw84u9ll00p4dJQRuzbBg&oe=69DAFEBA | K34: shop.try-forge.com | L34: 132584606613853
A35: 2309765512833844 | B35: Forge Men | C35: 46114 | D35: Image | E35: Attractive Skin in 3 Weeks | F35: How can beef tallow rejuvenate and revitalize your skin, making you look years younger quickly? Because it contains 12 out of the 16 essential nutrients your skin needs. Vitamins, fatty acids, and so much more... ✔ Tightens wrinkles QUICKLY ✔ Hydrates and repairs the skin ✔ Clears up dark spots ✔ Reduces eye bags ✔ 100% natural Want to try it out? Click the link below to get your pure beef tallow balm now! 👇 | G35: Very Few Men Know This... | H35: https://shop.try-forge.com/listicle-eyebags | I35: Shop now | J35: https://scontent.fsgn5-5.fna.fbcdn.net/v/t39.35426-6/658158696_1362395802444931_8343953542959280058_n.jpg?stp=dst-jpg_s600x600_tt6&_nc_cat=108&ccb=1-7&_nc_sid=c53f8f&_nc_ohc=3F5AH0JzFRwQ7kNvwHcGcTV&_nc_oc=AdqVXCXC1Zh-yJHbwLee7PSylpio3KT4jFC14c0ifwZH92ZzeFa0TDdzTGS9h3yOuyY&_nc_zt=14&_nc_ht=scontent.fsgn5-5.fna&_nc_gid=ClwIPkHLQ5LFDAxEMsXxxQ&_nc_ss=7a389&oh=00_Af1CTJh1_phVLu1uHz98sm3cCEPNaLBVZJ0WhAW_gfuaTQ&oe=69DAD38B | K35: shop.try-forge.com | L35: 132584606613853
A36: 1720237599338323 | B36: Forge Men | C36: 46114 | D36: Video | E36: ⏰LAST CHANCE!⏰Sale Ends Soon... | F36: 🐰 BIGGEST Easter Sale EVER! 🥚 Get 50% OFF our Beef Tallow Balm, PLUS an EXTRA 20% with code 'EASTER20'! Our Beef Tallow Balm: ✔️Tightens wrinkles QUICKLY ✔️Reduces eye bags and dark spots ✔️Makes your skin thicker, stronger, & hydrated ✔️Helps you go from "tired face" to "sharp & refreshed" Don’t let this one-time deal slip away... an offer this big won’t come back a second time! Tap the button below to get your discount now 👇 | G36: BIGGEST Sale Of The Year! | H36: https://shop.try-forge.com/mens-lifestyle-essentials-1 | I36: Shop now | J36: https://video.fsgn5-12.fna.fbcdn.net/o1/v/t2/f2/m412/AQM6l-7ItkcMU1jkQCOKLDfs3gP-DGSyupcdiwp3qvsBQzyhbgfi7hkChR9Nrzq73mNeuTFLSyZHivTC5CIgqp6RxTX4owGyKmJ1DRLmkg.mp4?_nc_cat=105&_nc_oc=Adq8US1rjca7P1oXldfqG8PXK3n3ToEggS-J0_vTiBjXeBkJQVEytLeMpnGns6Z_skQ&_nc_sid=8bf8fe&_nc_ht=video.fsgn5-12.fna.fbcdn.net&_nc_ohc=N1zo5OcATYUQ7kNvwFXdcD2&efg=eyJ2ZW5jb2RlX3RhZyI6Inhwdl9wcm9ncmVzc2l2ZS5WSV9VU0VDQVNFX1BST0RVQ1RfVFlQRS4uQzMuMzU2LnN2ZV9zZCIsInhwdl9hc3NldF9pZCI6MTYyNTM3MDQ1OTI2MDA3NCwiYXNzZXRfYWdlX2RheXMiOjQsInZpX3VzZWNhc2VfaWQiOjEwMTM5LCJkdXJhdGlvbl9zIjo1NiwidXJsZ2VuX3NvdXJjZSI6Ind3dyJ9&ccb=17-1&_nc_gid=ClwIPkHLQ5LFDAxEMsXxxQ&_nc_ss=7a389&_nc_zt=28&oh=00_Af0BwrmQXL9Bu__HNg8ps_gUC2pWAxxk76-Z8EwM4RjdQg&oe=69DAE125 | K36: shop.try-forge.com | L36: 132584606613853
A37: 884891277886785 | B37: Forge Men | C37: 46098 | D37: Video | E37: ⏰LAST CHANCE!⏰Sale Ends at Midnight... | F37: 🌼BIGGEST Spring Sale EVER!🌼 Get 50% OFF our Beef Tallow Balm, PLUS an EXTRA 20% with code 'SPRING20'! Our Beef Tallow Balm: ✔️Tightens wrinkles QUICKLY ✔️Reduces eye bags and dark spots ✔️Makes your skin thicker, stronger, & hydrated ✔️Helps you go from "tired face" to "sharp & refreshed" Don’t let this one-time deal slip away... an offer this big won’t come back a second time! Tap the button below to get your discount now 👇 | G37: BIGGEST Sale Of The Year! | H37: https://shop.try-forge.com/mens-lifestyle-essentials-1 | I37: Shop now | J37: https://video.fsgn5-11.fna.fbcdn.net/o1/v/t2/f2/m412/AQMkVmJmVHNnXYxeBekkinai_brvaK2kW4r_VodB4AKPi9vTdotrXiLa2C0-XnCgOfSl12Ry3cIGn1xbI8_1IOLYSLVh4Ip3fXayqwSSbA.mp4?_nc_cat=110&_nc_oc=AdpDJiUpV8x8WlZA6Xoht8AWTLm493KU_iKehCSSCzlLlah2IG31zi3aqcChHuOid-A&_nc_sid=8bf8fe&_nc_ht=video.fsgn5-11.fna.fbcdn.net&_nc_ohc=Ov8QCjPXcXMQ7kNvwGHa9-4&efg=eyJ2ZW5jb2RlX3RhZyI6Inhwdl9wcm9ncmVzc2l2ZS5WSV9VU0VDQVNFX1BST0RVQ1RfVFlQRS4uQzMuMzYwLnN2ZV9zZCIsInhwdl9hc3NldF9pZCI6MjQ4MzkzNjIxMjAyNTUyOCwiYXNzZXRfYWdlX2RheXMiOjIxLCJ2aV91c2VjYXNlX2lkIjoxMDEzOSwiZHVyYXRpb25fcyI6NjQsInVybGdlbl9zb3VyY2UiOiJ3d3cifQ%3D%3D&ccb=17-1&_nc_gid=ClwIPkHLQ5LFDAxEMsXxxQ&_nc_ss=7a389&_nc_zt=28&oh=00_Af1Qt_STlMymxWQe45hqwH3w-z4wN_fmN6vII0zTi1_smA&oe=69DAD94C | K37: shop.try-forge.com | L37: 132584606613853
A38: 3379588775550782 | B38: Forge Men | C38: 46113 | D38: Image | E38: Attractive Skin in 3 Weeks | F38: How can beef tallow rejuvenate and revitalize your skin, making you look years younger quickly? Because it contains 12 out of the 16 essential nutrients your skin needs. Vitamins, fatty acids, and so much more... ✔ Tightens wrinkles QUICKLY ✔ Hydrates and repairs the skin ✔ Clears up dark spots ✔ Reduces eye bags ✔ 100% natural Want to try it out? Click the link below to get your pure beef tallow balm now! 👇 | G38: Very Few Men Know This... | H38: https://shop.try-forge.com/listicle-eyebags | I38: Shop now | J38: https://scontent.fsgn5-5.fna.fbcdn.net/v/t39.35426-6/660180362_2069812410244188_493873610239351651_n.jpg?stp=dst-jpg_s600x600_tt6&_nc_cat=108&ccb=1-7&_nc_sid=c53f8f&_nc_ohc=T42tbuQd-w8Q7kNvwEuRqpt&_nc_oc=AdofumBBQ-NEhLY-M5le5qRJ_Lm_r2i8ziAkuukJ5mjZsHe_Q4tzBKQo1CNpX9yd00o&_nc_zt=14&_nc_ht=scontent.fsgn5-5.fna&_nc_gid=ClwIPkHLQ5LFDAxEMsXxxQ&_nc_ss=7a389&oh=00_Af0BXqsZBUAfqsVbcR_DaFGNAXIkg5KNf5Wh-nrl3vW18A&oe=69DAE976 | K38: shop.try-forge.com | L38: 132584606613853
A39: 1432220118100598 | B39: Forge Men | C39: 46114 | D39: Image | E39: Attractive Skin in 3 Weeks | F39: How can beef tallow rejuvenate and revitalize your skin, making you look years younger quickly? Because it contains 12 out of the 16 essential nutrients your skin needs. Vitamins, fatty acids, and so much more... ✔ Tightens wrinkles QUICKLY ✔ Hydrates and repairs the skin ✔ Clears up dark spots ✔ Reduces eye bags ✔ 100% natural Want to try it out? Click the link below to get your pure beef tallow balm now! 👇 | G39: Very Few Men Know This... | H39: https://shop.try-forge.com/listicle-eyebags | I39: Shop now | J39: https://scontent.fsgn5-8.fna.fbcdn.net/v/t39.35426-6/660405553_2147998156018041_3916122953508550200_n.jpg?stp=dst-jpg_s600x600_tt6&_nc_cat=109&ccb=1-7&_nc_sid=c53f8f&_nc_ohc=BZQsUAVYOSwQ7kNvwFoszpP&_nc_oc=AdqYErl8VAHd2SbuSOFw6YSsqUtvuRUp6YTPkLYiJqZ80lKih2n4SevvtVIvqbYSuIs&_nc_zt=14&_nc_ht=scontent.fsgn5-8.fna&_nc_gid=ClwIPkHLQ5LFDAxEMsXxxQ&_nc_ss=7a389&oh=00_Af2mpSjqc20FiTfnbVqmcXVCGCv6LA7_mu7_hk-tpjnsZA&oe=69DAD750 | K39: shop.try-forge.com | L39: 132584606613853
A40: 1518479522946745 | B40: Forge Men | C40: 46114 | D40: Image | E40: Attractive Skin in 3 Weeks | F40: How can beef tallow rejuvenate and revitalize your skin, making you look years younger quickly? Because it contains 12 out of the 16 essential nutrients your skin needs. Vitamins, fatty acids, and so much more... ✔ Tightens wrinkles QUICKLY ✔ Hydrates and repairs the skin ✔ Clears up dark spots ✔ Reduces eye bags ✔ 100% natural Want to try it out? Click the link below to get your pure beef tallow balm now! 👇 | G40: Very Few Men Know This... | H40: https://shop.try-forge.com/listicle-eyebags | I40: Shop now | J40: https://scontent.fsgn5-11.fna.fbcdn.net/v/t39.35426-6/661991765_705793502624236_511366626552855888_n.jpg?stp=dst-jpg_s600x600_tt6&_nc_cat=110&ccb=1-7&_nc_sid=c53f8f&_nc_ohc=0qqHw0LZS5MQ7kNvwFmg-DP&_nc_oc=AdqZdI6Q1jGLr1rPwdbfUfxTMQTUp-kbJhD2HmznIPlkdVIQYocYGbsvz5e5XretdNE&_nc_zt=14&_nc_ht=scontent.fsgn5-11.fna&_nc_gid=ClwIPkHLQ5LFDAxEMsXxxQ&_nc_ss=7a389&oh=00_Af0CkKU5MoPpx-aFr1a9zL7lPbDvuOSt92g6KoKU-wheFA&oe=69DAEDC6 | K40: shop.try-forge.com | L40: 132584606613853
A41: 1530151418672866 | B41: Forge Men | C41: 46114 | D41: Video | E41: ⏰LAST CHANCE!⏰Sale Ends Soon... | F41: 🥚 BIGGEST Easter Sale EVER! 🥩 Get 50% OFF our Beef Organ Complex, PLUS an EXTRA 20% with code 'EASTER20'! Our 5-in-1 Beef Organ Supplements: ✔️Burn stubborn belly fat & man boobs ✔️Support testosterone & lean muscles ✔️Rebuild & strengthen joints ✔️Boost all-day energy & digestion ✔️Helps you go from "dad bod" to "strong & powerful" Don’t let this one-time deal slip away... an offer this big won’t come back a second time! Tap the button below to get your discount now 👇 | G41: BIGGEST Sale Of The Year! | H41: https://secure.try-forge.com/bridge-a1-simple | I41: Shop now | J41: https://video.fsgn5-5.fna.fbcdn.net/o1/v/t2/f2/m412/AQNMQ3V7tDb8iNrSGfL2Hqau8_kNw9eoIXgXnmMkeYk7ogyP0-VbBbwnR_xftfzAyzYAGAHs03Gdk5D_fSEUhq-k5279OuGeAK6fv3FOaQ.mp4?_nc_cat=108&_nc_oc=AdovpeaOjYswq1X3h18uNzUiOx1h1Tt5FYhoyDj2W5H-DVDA9Mjmcyf_L7XTU7kfpvU&_nc_sid=8bf8fe&_nc_ht=video.fsgn5-5.fna.fbcdn.net&_nc_ohc=zNWoDQVcqYoQ7kNvwFyuOoH&efg=eyJ2ZW5jb2RlX3RhZyI6Inhwdl9wcm9ncmVzc2l2ZS5WSV9VU0VDQVNFX1BST0RVQ1RfVFlQRS4uQzMuMzYwLnN2ZV9zZCIsInhwdl9hc3NldF9pZCI6MjY0NjY2MDA4NzI5NzcxNTAsImFzc2V0X2FnZV9kYXlzIjo0LCJ2aV91c2VjYXNlX2lkIjoxMDc5OSwiZHVyYXRpb25fcyI6NzcsInVybGdlbl9zb3VyY2UiOiJ3d3cifQ%3D%3D&ccb=17-1&_nc_gid=ClwIPkHLQ5LFDAxEMsXxxQ&_nc_ss=7a389&_nc_zt=28&oh=00_Af3JeRtiFKxBw5WzwXkMuohO-QnP37Rn0jBKiFezjnRKMw&oe=69DB0266 | K41: shop.try-forge.com | L41: 132584606613853
A42: 1530605388402712 | B42: Forge Men | C42: 46114 | D42: Image | E42: Attractive Skin in 3 Weeks | F42: How can beef tallow rejuvenate and revitalize your skin, making you look years younger quickly? Because it contains 12 out of the 16 essential nutrients your skin needs. Vitamins, fatty acids, and so much more... ✔ Tightens wrinkles QUICKLY ✔ Hydrates and repairs the skin ✔ Clears up dark spots ✔ Reduces eye bags ✔ 100% natural Want to try it out? Click the link below to get your pure beef tallow balm now! 👇 | G42: Very Few Men Know This... | H42: https://shop.try-forge.com/listicle-eyebags | I42: Shop now | J42: https://scontent.fsgn5-8.fna.fbcdn.net/v/t39.35426-6/659451255_917389344507409_2702011470098946167_n.jpg?stp=dst-jpg_s600x600_tt6&_nc_cat=109&ccb=1-7&_nc_sid=c53f8f&_nc_ohc=8_GFKb7lmGoQ7kNvwHLvmx9&_nc_oc=AdqVEdApe3Pgsb5zbV89h0ZoT08op-fWEB0r-Aau42IlErD1WBzvjud8VvLveeAdJOs&_nc_zt=14&_nc_ht=scontent.fsgn5-8.fna&_nc_gid=jd4chRm1-qqEGk7_v6HBvQ&_nc_ss=7a389&oh=00_Af1eXX1HjS4QNYvWhcL-mWw6YuCmwy0qAg0-RoClI7aTIA&oe=69DAD8FF | K42: shop.try-forge.com | L42: 132584606613853
A43: 979814668061152 | B43: Forge Men | C43: 46114 | D43: Video | E43: ⏰LAST CHANCE!⏰Sale Ends Soon... | F43: 🐰 BIGGEST Easter Sale EVER! 🥚 Get 50% OFF our Beef Tallow Balm, PLUS an EXTRA 20% with code 'EASTER20'! Our Beef Tallow Balm: ✔️Tightens wrinkles QUICKLY ✔️Reduces eye bags and dark spots ✔️Makes your skin thicker, stronger, & hydrated ✔️Helps you go from "tired face" to "sharp & refreshed" Don’t let this one-time deal slip away... an offer this big won’t come back a second time! Tap the button below to get your discount now 👇 | G43: BIGGEST Sale Of The Year! | H43: https://shop.try-forge.com/mens-lifestyle-essentials-1 | I43: Shop now | J43: https://video.fsgn5-12.fna.fbcdn.net/o1/v/t2/f2/m412/AQOxmTL9hyRXW5_7avUjaAvvFp95El_OqOQEoqDTAqZruhv7BfKrhAGSLjKahqy3s_kalfEivR5lSr2o-KcxOJfI8kN1JlqKd1hj9qfMJA.mp4?_nc_cat=105&_nc_oc=AdqP31whgCxlf922yhvPDA_6S3jdq0Arv8TBOZmmFFjb_TVYlNxRP2nvP2_qps2omAE&_nc_sid=8bf8fe&_nc_ht=video.fsgn5-12.fna.fbcdn.net&_nc_ohc=C4-bcRUxvUQQ7kNvwFfO_gI&efg=eyJ2ZW5jb2RlX3RhZyI6Inhwdl9wcm9ncmVzc2l2ZS5WSV9VU0VDQVNFX1BST0RVQ1RfVFlQRS4uQzMuMzYwLnN2ZV9zZCIsInhwdl9hc3NldF9pZCI6MTQ0NjY3MTExMzMwODIzMSwiYXNzZXRfYWdlX2RheXMiOjQsInZpX3VzZWNhc2VfaWQiOjEwMTM5LCJkdXJhdGlvbl9zIjoxNTMsInVybGdlbl9zb3VyY2UiOiJ3d3cifQ%3D%3D&ccb=17-1&_nc_gid=jd4chRm1-qqEGk7_v6HBvQ&_nc_ss=7a389&_nc_zt=28&oh=00_Af0HF32HHUOBuZlqcDoCFG3SbBTO8fo8GWtUvKUri-84lQ&oe=69DAFAAD | K43: shop.try-forge.com | L43: 132584606613853
A44: 26320374384255792 | B44: Forge Men | C44: 46114 | D44: Video | E44: ⏰LAST CHANCE!⏰Sale Ends Soon... | F44: 🥚 BIGGEST Easter Sale EVER! 🥩 Get 50% OFF our Beef Organ Complex, PLUS an EXTRA 20% with code 'EASTER20'! Our 5-in-1 Beef Organ Supplements: ✔️Burn stubborn belly fat & man boobs ✔️Support testosterone & lean muscles ✔️Rebuild & strengthen joints ✔️Boost all-day energy & digestion ✔️Helps you go from "dad bod" to "strong & powerful" Don’t let this one-time deal slip away... an offer this big won’t come back a second time! Tap the button below to get your discount now 👇 | G44: BIGGEST Sale Of The Year! | H44: https://secure.try-forge.com/bridge-a1-simple | I44: Shop now | J44: https://video.fsgn5-10.fna.fbcdn.net/o1/v/t2/f2/m412/AQP0mg7tyZReVDU_mHGJ742cAGW_hgXmLzHFYdOl2tugS4ACMkuK78EidlPJd23T-IbZUaCsu1oBh1a6zRxai-as3KPUZBA6uFglfpq11w.mp4?_nc_cat=101&_nc_oc=AdrkC2w_9LE8xzXnPfMv2D5ZXZTEdxm6dlaubJ9GHvtMSHw08fAM1ivLagBU11VBp3U&_nc_sid=8bf8fe&_nc_ht=video.fsgn5-10.fna.fbcdn.net&_nc_ohc=qwxvFWavLsgQ7kNvwFvkVuL&efg=eyJ2ZW5jb2RlX3RhZyI6Inhwdl9wcm9ncmVzc2l2ZS5WSV9VU0VDQVNFX1BST0RVQ1RfVFlQRS4uQzMuMzYwLnN2ZV9zZCIsInhwdl9hc3NldF9pZCI6MjEzMTE4MDgyNDA5NzQzMywiYXNzZXRfYWdlX2RheXMiOjQsInZpX3VzZWNhc2VfaWQiOjEwNzk5LCJkdXJhdGlvbl9zIjo4MCwidXJsZ2VuX3NvdXJjZSI6Ind3dyJ9&ccb=17-1&_nc_gid=jd4chRm1-qqEGk7_v6HBvQ&_nc_ss=7a389&_nc_zt=28&oh=00_Af04MEsCMxKqECN2YU3fF37grL-wDlJWu2Edwj8NK63VRw&oe=69DADE61 | K44: shop.try-forge.com | L44: 132584606613853
A45: 1265470901741615 | B45: Forge Men | C45: 46114 | D45: Video | E45: ⏰LAST CHANCE!⏰Sale Ends Soon... | F45: 🐰 BIGGEST Easter Sale EVER! 🥚 Get 50% OFF our Beef Tallow Balm, PLUS an EXTRA 20% with code 'EASTER20'! Our Beef Tallow Balm: ✔️Tightens wrinkles QUICKLY ✔️Reduces eye bags and dark spots ✔️Makes your skin thicker, stronger, & hydrated ✔️Helps you go from "tired face" to "sharp & refreshed" Don’t let this one-time deal slip away... an offer this big won’t come back a second time! Tap the button below to get your discount now 👇 | G45: BIGGEST Sale Of The Year! | H45: https://shop.try-forge.com/mens-lifestyle-essentials-1 | I45: Shop now | J45: https://video.fsgn5-5.fna.fbcdn.net/o1/v/t2/f2/m412/AQNDMbWViKRuCn4KLN5VcsNz-tuFebduq4CKMSRHdUgQC_OZhzd1C9zKPVzPs_cAwUPqRdZMQsObBrwMRBYhDlrCXO63Acq362lfjGkZrw.mp4?_nc_cat=108&_nc_oc=AdqAMW1SZmkmt6XF3TbxKv-BeooUgiwfwau3yEp03I-UdYJmnOItpm7GcYfXJnNkzfA&_nc_sid=8bf8fe&_nc_ht=video.fsgn5-5.fna.fbcdn.net&_nc_ohc=lKugNzeIu-gQ7kNvwGgwvEX&efg=eyJ2ZW5jb2RlX3RhZyI6Inhwdl9wcm9ncmVzc2l2ZS5WSV9VU0VDQVNFX1BST0RVQ1RfVFlQRS4uQzMuMzYwLnN2ZV9zZCIsInhwdl9hc3NldF9pZCI6MjAxMjYzODc4NjA0NTQ4NSwiYXNzZXRfYWdlX2RheXMiOjQsInZpX3VzZWNhc2VfaWQiOjEwMTM5LCJkdXJhdGlvbl9zIjo2OSwidXJsZ2VuX3NvdXJjZSI6Ind3dyJ9&ccb=17-1&_nc_gid=jd4chRm1-qqEGk7_v6HBvQ&_nc_ss=7a389&_nc_zt=28&oh=00_Af1OTWBGkjtriOKpGRIsua3ynmJe07JM9KI3Qh8jCkOtDQ&oe=69DB08E2 | K45: shop.try-forge.com | L45: 132584606613853
A46: 954778077249937 | B46: Forge Men | C46: 46114 | D46: Video | E46: ⏰LAST CHANCE!⏰Sale Ends Soon... | F46: 🐰 BIGGEST Easter Sale EVER! 🥚 Get 50% OFF our Beef Tallow Balm, PLUS an EXTRA 20% with code 'EASTER20'! Our Beef Tallow Balm: ✔️Tightens wrinkles QUICKLY ✔️Reduces eye bags and dark spots ✔️Makes your skin thicker, stronger, & hydrated ✔️Helps you go from "tired face" to "sharp & refreshed" Don’t let this one-time deal slip away... an offer this big won’t come back a second time! Tap the button below to get your discount now 👇 | G46: BIGGEST Sale Of The Year! | H46: https://shop.try-forge.com/mens-lifestyle-essentials-1 | I46: Shop now | J46: https://video.fsgn5-10.fna.fbcdn.net/o1/v/t2/f2/m412/AQNc3xxamJrWybuwXxrcMgNLhQ2CULdtmPi1mMyW9fLYmAMV_Q66ynDdOtqeC07Pl7dgKsQg9OC1h_qTfliLDcXsEM2xHtKPyiEREm83_A.mp4?_nc_cat=106&_nc_oc=Ado85OLWzSQPpVV-1GvZ_AhT5igssvwbxkwV1pjJuMJucVqXulDH0HTsCA5ettWGPIc&_nc_sid=8bf8fe&_nc_ht=video.fsgn5-10.fna.fbcdn.net&_nc_ohc=WYUsbq9q0jkQ7kNvwHDIMYj&efg=eyJ2ZW5jb2RlX3RhZyI6Inhwdl9wcm9ncmVzc2l2ZS5WSV9VU0VDQVNFX1BST0RVQ1RfVFlQRS4uQzMuMzYwLnN2ZV9zZCIsInhwdl9hc3NldF9pZCI6MTY2MDY5MDQ3ODMwMzI0MCwiYXNzZXRfYWdlX2RheXMiOjQsInZpX3VzZWNhc2VfaWQiOjEwMTM5LCJkdXJhdGlvbl9zIjo2OCwidXJsZ2VuX3NvdXJjZSI6Ind3dyJ9&ccb=17-1&_nc_gid=jd4chRm1-qqEGk7_v6HBvQ&_nc_ss=7a389&_nc_zt=28&oh=00_Af1y90KVVd9AcAunzg1NiLrJ5COH3BTU-AFsq6pS0LONdA&oe=69DB0810 | K46: shop.try-forge.com | L46: 132584606613853
A47: 905079405682609 | B47: Forge Men | C47: 46113 | D47: Image | E47: ⏰LAST CHANCE!⏰Sale Ends Soon... | F47: 🐰 BIGGEST Easter Sale EVER! 🥚 Get 50% OFF our Beef Tallow Balm, PLUS an EXTRA 20% with code 'EASTER20'! Our Beef Tallow Balm: ✔️Tightens wrinkles QUICKLY ✔️Reduces eye bags and dark spots ✔️Makes your skin thicker, stronger, & hydrated ✔️Helps you go from "tired face" to "sharp & refreshed" Don’t let this one-time deal slip away... an offer this big won’t come back a second time! Tap the button below to get your discount now 👇 | G47: BIGGEST Sale Of The Year! | H47: https://shop.try-forge.com/mens-lifestyle-essentials-1 | I47: Shop now | J47: https://scontent.fsgn5-10.fna.fbcdn.net/v/t39.35426-6/661075157_934712709201483_3292044443405749015_n.jpg?stp=dst-jpg_s600x600_tt6&_nc_cat=106&ccb=1-7&_nc_sid=c53f8f&_nc_ohc=FGqE3YRCPCsQ7kNvwF2oOCa&_nc_oc=Adoqt1UwQEvqrqEyqRAoi_Bl7Pfky1Pez2j30XRnC0mt46nu0Aa1id3QZTRjB2-J7WQ&_nc_zt=14&_nc_ht=scontent.fsgn5-10.fna&_nc_gid=jd4chRm1-qqEGk7_v6HBvQ&_nc_ss=7a389&oh=00_Af1kE6F_yXg0CWP3VlvjLjTK9W6raNDe_2CH-z8iNMktsg&oe=69DAD6DC | K47: shop.try-forge.com | L47: 132584606613853
A48: 2174512653371714 | B48: Forge Men | C48: 46098 | D48: Video | E48: ⏰LAST CHANCE!⏰Sale Ends at Midnight... | F48: 🌼BIGGEST Spring Sale EVER!🌼 Get 50% OFF our Beef Tallow Balm, PLUS an EXTRA 20% with code 'SPRING20'! Our Beef Tallow Balm: ✔️Tightens wrinkles QUICKLY ✔️Reduces eye bags and dark spots ✔️Makes your skin thicker, stronger, & hydrated ✔️Helps you go from "tired face" to "sharp & refreshed" Don’t let this one-time deal slip away... an offer this big won’t come back a second time! Tap the button below to get your discount now 👇 | G48: BIGGEST Sale Of The Year! | H48: https://shop.try-forge.com/mens-lifestyle-essentials-1 | I48: Shop now | J48: https://video.fsgn5-8.fna.fbcdn.net/o1/v/t2/f2/m412/AQOQM_S0kdwJEkEyBrbjBrue2dHCpjTNc5ez8j5Xr6MGCWD6Dp2LYH3a6jSXSGC25x5SG3gC593haj92Ebu2TDFvRLZg4lwTNMTLGtJ-cg.mp4?_nc_cat=109&_nc_oc=Ado1ROLXRfuPaw1RWn_MDowzDMYrWizfBJd3aYsNJ6hrFBK7dr_DFaQ-64S6UcYnUb8&_nc_sid=8bf8fe&_nc_ht=video.fsgn5-8.fna.fbcdn.net&_nc_ohc=uS0wHdS6uA4Q7kNvwGqxTCI&efg=eyJ2ZW5jb2RlX3RhZyI6Inhwdl9wcm9ncmVzc2l2ZS5WSV9VU0VDQVNFX1BST0RVQ1RfVFlQRS4uQzMuMzYwLnN2ZV9zZCIsInhwdl9hc3NldF9pZCI6OTUyODg4ODkzODQ3MjA3LCJhc3NldF9hZ2VfZGF5cyI6MjEsInZpX3VzZWNhc2VfaWQiOjEwMTM5LCJkdXJhdGlvbl9zIjo2NSwidXJsZ2VuX3NvdXJjZSI6Ind3dyJ9&ccb=17-1&_nc_gid=jd4chRm1-qqEGk7_v6HBvQ&_nc_ss=7a389&_nc_zt=28&oh=00_Af1Tx98NfQS-EPNC4hv-TYidbosB1NGG0Y-A9h9ldmf_-A&oe=69DAE5AD | K48: shop.try-forge.com | L48: 132584606613853
A49: 923513543924654 | B49: Forge Men | C49: 46115 | D49: Video | E49: ⏰LAST CHANCE!⏰Sale Ends Soon... | F49: 🐰 BIGGEST Easter Sale EVER! 🥚 Get 50% OFF our Beef Tallow Balm, PLUS an EXTRA 20% with code 'EASTER20'! Our Beef Tallow Balm: ✔️Tightens wrinkles QUICKLY ✔️Reduces eye bags and dark spots ✔️Makes your skin thicker, stronger, & hydrated ✔️Helps you go from "tired face" to "sharp & refreshed" Don’t let this one-time deal slip away... an offer this big won’t come back a second time! Tap the button below to get your discount now 👇 | G49: BIGGEST Sale Of The Year! | H49: https://shop.try-forge.com/mens-lifestyle-essentials-1 | I49: Shop now | J49: https://video.fsgn5-12.fna.fbcdn.net/o1/v/t2/f2/m412/AQMWMAGNrl_S8DiDz9aGSkBwa6rLlwz5oz9cy2g7-e96irsD3rEv3ebXYdXseGffyPF3Coj1kI1x0Cm8vGhgSZMtIQFVixDVYhI3FbVuXg.mp4?_nc_cat=103&_nc_oc=AdrL3JuGZVjfcEFX9c3a5XmHgbxRvy7Z-H2MM-carLqEMx_cCW53Rqc2osU4b9tt4uU&_nc_sid=8bf8fe&_nc_ht=video.fsgn5-12.fna.fbcdn.net&_nc_ohc=an8eQ20UwBEQ7kNvwHjv2Iq&efg=eyJ2ZW5jb2RlX3RhZyI6Inhwdl9wcm9ncmVzc2l2ZS5WSV9VU0VDQVNFX1BST0RVQ1RfVFlQRS4uQzMuMzYwLnN2ZV9zZCIsInhwdl9hc3NldF9pZCI6NDQ2Njk1NTA2NjkyMTk0MiwiYXNzZXRfYWdlX2RheXMiOjQsInZpX3VzZWNhc2VfaWQiOjEwMTM5LCJkdXJhdGlvbl9zIjo4MSwidXJsZ2VuX3NvdXJjZSI6Ind3dyJ9&ccb=17-1&_nc_gid=jd4chRm1-qqEGk7_v6HBvQ&_nc_ss=7a389&_nc_zt=28&oh=00_Af37RA579zhYZjd0NaZfqwRiiJBhssSJzjpZcSwSTd48Kw&oe=69DAE227 | K49: shop.try-forge.com | L49: 132584606613853
A50: 1455143436052461 | B50: Forge Men | C50: 46114 | D50: Video | E50: ⏰LAST CHANCE!⏰Sale Ends Soon... | F50: 🥚 BIGGEST Easter Sale EVER! 🥩 Get 50% OFF our Beef Organ Complex, PLUS an EXTRA 20% with code 'EASTER20'! Our 5-in-1 Beef Organ Supplements: ✔️Burn stubborn belly fat & man boobs ✔️Support testosterone & lean muscles ✔️Rebuild & strengthen joints ✔️Boost all-day energy & digestion ✔️Helps you go from "dad bod" to "strong & powerful" Don’t let this one-time deal slip away... an offer this big won’t come back a second time! Tap the button below to get your discount now 👇 | G50: BIGGEST Sale Of The Year! | H50: https://secure.try-forge.com/bridge-a1-simple | I50: Shop now | J50: https://video.fsgn5-10.fna.fbcdn.net/o1/v/t2/f2/m412/AQOO9XHd9LWV-knd8ro50irQwrkyQwKv5lQwv9fL2CoKHR-rG1Ctn-cUlwP3WycAEoG_Q1qzAFI-IW9zNvWUdjyfteYeI8_l0YhCS6tSjQ.mp4?_nc_cat=106&_nc_oc=AdqJX5ITvjTwioCg6UaQGpSjxw_m42flOlEfDsgutMasnbs_4bzWccorsE6vvX7ZIQY&_nc_sid=8bf8fe&_nc_ht=video.fsgn5-10.fna.fbcdn.net&_nc_ohc=U0kyOWMyuTIQ7kNvwGdDwy9&efg=eyJ2ZW5jb2RlX3RhZyI6Inhwdl9wcm9ncmVzc2l2ZS5WSV9VU0VDQVNFX1BST0RVQ1RfVFlQRS4uQzMuMzYwLnN2ZV9zZCIsInhwdl9hc3NldF9pZCI6MTIxNDQ4NDA5MzgzMzQ0MSwiYXNzZXRfYWdlX2RheXMiOjQsInZpX3VzZWNhc2VfaWQiOjEwNzk5LCJkdXJhdGlvbl9zIjo3OSwidXJsZ2VuX3NvdXJjZSI6Ind3dyJ9&ccb=17-1&_nc_gid=jd4chRm1-qqEGk7_v6HBvQ&_nc_ss=7a389&_nc_zt=28&oh=00_Af0OA1sQEOcX3UvvPWgBo9jUG66mtHSF3xYsJ-1gZHOMog&oe=69DAEDB8 | K50: shop.try-forge.com | L50: 132584606613853
A51: 1592488381826797 | B51: Forge Men | C51: 46115 | D51: Video | E51: ⏰LAST CHANCE!⏰Sale Ends Soon... | F51: 🐰 BIGGEST Easter Sale EVER! 🥚 Get 50% OFF our Beef Tallow Balm, PLUS an EXTRA 20% with code 'EASTER20'! Our Beef Tallow Balm: ✔️Tightens wrinkles QUICKLY ✔️Reduces eye bags and dark spots ✔️Makes your skin thicker, stronger, & hydrated ✔️Helps you go from "tired face" to "sharp & refreshed" Don’t let this one-time deal slip away... an offer this big won’t come back a second time! Tap the button below to get your discount now 👇 | G51: BIGGEST Sale Of The Year! | H51: https://shop.try-forge.com/mens-lifestyle-essentials-1 | I51: Shop now | J51: https://video.fsgn5-3.fna.fbcdn.net/o1/v/t2/f2/m412/AQNdefvUHeRQMb_op6ufn46t2jlb05IV0_3rpFXGpldwM8favpp5E1-diQYeMpR9-IQjG8iq_mx2MC-E9XKDPJOVAkuwnBcM7Y8EAoKAVA.mp4?_nc_cat=104&_nc_oc=AdrnaOAMy1KlAdS5bT3KzIrN0BPo_KTtisASsNm44Y5Yb9SpRqp4mQbsu_C2e7hqrWY&_nc_sid=8bf8fe&_nc_ht=video.fsgn5-3.fna.fbcdn.net&_nc_ohc=vUL7R9WpnfYQ7kNvwFg_b-0&efg=eyJ2ZW5jb2RlX3RhZyI6Inhwdl9wcm9ncmVzc2l2ZS5WSV9VU0VDQVNFX1BST0RVQ1RfVFlQRS4uQzMuMzYwLnN2ZV9zZCIsInhwdl9hc3NldF9pZCI6MTQ2Nzk4NzYwMTM5NjQxMywiYXNzZXRfYWdlX2RheXMiOjQsInZpX3VzZWNhc2VfaWQiOjEwMTM5LCJkdXJhdGlvbl9zIjo4MSwidXJsZ2VuX3NvdXJjZSI6Ind3dyJ9&ccb=17-1&_nc_gid=jd4chRm1-qqEGk7_v6HBvQ&_nc_ss=7a389&_nc_zt=28&oh=00_Af23tFD7lmJVAqsPvi_cT6wCBkwSlunVbIQZhcmu2y6pxg&oe=69DAE6BE | K51: shop.try-forge.com | L51: 132584606613853
A52: 1272784990933408 | B52: Forge Men | C52: 46114 | D52: Video | E52: ⏰LAST CHANCE!⏰Sale Ends Soon... | F52: 🐰 BIGGEST Easter Sale EVER! 🥚 Get 50% OFF our Beef Tallow Balm, PLUS an EXTRA 20% with code 'EASTER20'! Our Beef Tallow Balm: ✔️Tightens wrinkles QUICKLY ✔️Reduces eye bags and dark spots ✔️Makes your skin thicker, stronger, & hydrated ✔️Helps you go from "tired face" to "sharp & refreshed" Don’t let this one-time deal slip away... an offer this big won’t come back a second time! Tap the button below to get your discount now 👇 | G52: BIGGEST Sale Of The Year! | H52: https://shop.try-forge.com/mens-lifestyle-essentials-1 | I52: Shop now | J52: https://video.fsgn5-5.fna.fbcdn.net/o1/v/t2/f2/m412/AQOOxkIA5ClyYN3Z26fgJTlF0RUQSZ6JpSojdIt1rzMr5l5RddciQWz2QBSIdVJycOGc8T-cOt57HyOVPe1ofNLf5nQbSnwP8PtG8XEgbw.mp4?_nc_cat=102&_nc_oc=AdrS0GgvPEyxdSJZQ6AUcf4Z35sVfjQzlFkd_73MglkCHTrJwE0sYy6IOlQWZvO8tvY&_nc_sid=8bf8fe&_nc_ht=video.fsgn5-5.fna.fbcdn.net&_nc_ohc=nBuWbpjC_gEQ7kNvwFSEwLI&efg=eyJ2ZW5jb2RlX3RhZyI6Inhwdl9wcm9ncmVzc2l2ZS5WSV9VU0VDQVNFX1BST0RVQ1RfVFlQRS4uQzMuMzYwLnN2ZV9zZCIsInhwdl9hc3NldF9pZCI6MTUwNDQ0Njc0MTI3NTk5NCwiYXNzZXRfYWdlX2RheXMiOjQsInZpX3VzZWNhc2VfaWQiOjEwMTM5LCJkdXJhdGlvbl9zIjoxNTQsInVybGdlbl9zb3VyY2UiOiJ3d3cifQ%3D%3D&ccb=17-1&_nc_gid=dG64M-PacbjgCP_GrM7ZLg&_nc_ss=7a389&_nc_zt=28&oh=00_Af212fY6NTeUv0ufUTpXElIDaX-5ViPPQMs_8tSJPwbJyA&oe=69DAD5B4 | K52: shop.try-forge.com | L52: 132584606613853
A53: 1460430805765557 | B53: Forge Men | C53: 46114 | D53: Video | E53: ⏰LAST CHANCE!⏰Sale Ends Soon... | F53: 🥚 BIGGEST Easter Sale EVER! 🥩 Get 50% OFF our Beef Organ Complex, PLUS an EXTRA 20% with code 'EASTER20'! Our 5-in-1 Beef Organ Supplements: ✔️Burn stubborn belly fat & man boobs ✔️Support testosterone & lean muscles ✔️Rebuild & strengthen joints ✔️Boost all-day energy & digestion ✔️Helps you go from "dad bod" to "strong & powerful" Don’t let this one-time deal slip away... an offer this big won’t come back a second time! Tap the button below to get your discount now 👇 | G53: BIGGEST Sale Of The Year! | H53: https://secure.try-forge.com/bridge-a1-simple | I53: Shop now | J53: https://video.fsgn5-3.fna.fbcdn.net/o1/v/t2/f2/m412/AQMvSGs4f0xk34TTMJcCFvA__71xX7C9gGsJZCajagl93YhpEzaphkfmkOOq_dkF5ftZT8IkfR5LWOzgQRr3GyDKzXblUqTGr1dzwLOC3g.mp4?_nc_cat=104&_nc_oc=AdoPqjlJrQ3rXjOpwYdyXTBlmIyW-o-Y32AygHJ7DbUXD_mnjUML1f7AumMzp6k-894&_nc_sid=8bf8fe&_nc_ht=video.fsgn5-3.fna.fbcdn.net&_nc_ohc=XIJAVx4FBWsQ7kNvwGuG_TC&efg=eyJ2ZW5jb2RlX3RhZyI6Inhwdl9wcm9ncmVzc2l2ZS5WSV9VU0VDQVNFX1BST0RVQ1RfVFlQRS4uQzMuMzYwLnN2ZV9zZCIsInhwdl9hc3NldF9pZCI6NDExNTM1Mzc3NTQyMjU1OSwiYXNzZXRfYWdlX2RheXMiOjQsInZpX3VzZWNhc2VfaWQiOjEwNzk5LCJkdXJhdGlvbl9zIjo4MSwidXJsZ2VuX3NvdXJjZSI6Ind3dyJ9&ccb=17-1&_nc_gid=dG64M-PacbjgCP_GrM7ZLg&_nc_ss=7a389&_nc_zt=28&oh=00_Af2_dMvrFts_JND1cSy0sWFTeW78clLROIft8gPmQ0EgtQ&oe=69DAFC7E | K53: shop.try-forge.com | L53: 132584606613853
A54: 910119105249937 | B54: Forge Men | C54: 46094 | D54: Video | E54: ⏰LAST CHANCE!⏰Sale Ends at Midnight... | F54: 🌼BIGGEST Spring Sale EVER!🌼 Get 50% OFF our Beef Tallow Balm, PLUS an EXTRA 20% with code 'SPRING20'! Our Beef Tallow Balm: ✔️Tightens wrinkles QUICKLY ✔️Reduces eye bags and dark spots ✔️Makes your skin thicker, stronger, & hydrated ✔️Helps you go from "tired face" to "sharp & refreshed" Don’t let this one-time deal slip away... an offer this big won’t come back a second time! Tap the button below to get your discount now 👇 | G54: BIGGEST Sale Of The Year! | H54: https://shop.try-forge.com/mens-lifestyle-essentials-1 | I54: Shop now | J54: https://video.fsgn5-12.fna.fbcdn.net/o1/v/t2/f2/m412/AQMVFfL20ekBi2jvY_uZzu7jRWqKCtfESzCj-D19Vtp1Ie3y3_wN2V8nUiKQveaBNXxHZX5wXVGgyF-TqX7q13L8CByXMa33qmexp7hlCQ.mp4?_nc_cat=103&_nc_oc=AdooWgo5_N1F0wq3CR0Mj2BviFt3kFqweZyjvq4Xl_SjPnnOTY9Tp5pJx2rnnyBp1qM&_nc_sid=8bf8fe&_nc_ht=video.fsgn5-12.fna.fbcdn.net&_nc_ohc=74KaJnPPhQAQ7kNvwHpcMGl&efg=eyJ2ZW5jb2RlX3RhZyI6Inhwdl9wcm9ncmVzc2l2ZS5WSV9VU0VDQVNFX1BST0RVQ1RfVFlQRS4uQzMuMzYwLnN2ZV9zZCIsInhwdl9hc3NldF9pZCI6OTM5NTAwNzk4NTc0NjAxLCJhc3NldF9hZ2VfZGF5cyI6MjQsInZpX3VzZWNhc2VfaWQiOjEwMTM5LCJkdXJhdGlvbl9zIjo2OCwidXJsZ2VuX3NvdXJjZSI6Ind3dyJ9&ccb=17-1&_nc_gid=dG64M-PacbjgCP_GrM7ZLg&_nc_ss=7a389&_nc_zt=28&oh=00_Af2gVBD_kXftkSFC_83ItN5peS5r_yYs7eO-yK0GUQWnZA&oe=69DAD6BF | K54: shop.try-forge.com | L54: 132584606613853
A55: 936873682456244 | B55: Forge Men | C55: 46115 | D55: Video | E55: ⏰LAST CHANCE!⏰Sale Ends Soon... | F55: 🐰 BIGGEST Easter Sale EVER! 🥚 Get 50% OFF our Beef Tallow Balm, PLUS an EXTRA 20% with code 'EASTER20'! Our Beef Tallow Balm: ✔️Tightens wrinkles QUICKLY ✔️Reduces eye bags and dark spots ✔️Makes your skin thicker, stronger, & hydrated ✔️Helps you go from "tired face" to "sharp & refreshed" Don’t let this one-time deal slip away... an offer this big won’t come back a second time! Tap the button below to get your discount now 👇 | G55: BIGGEST Sale Of The Year! | H55: https://shop.try-forge.com/mens-lifestyle-essentials-1 | I55: Shop now | J55: https://video.fsgn5-11.fna.fbcdn.net/o1/v/t2/f2/m412/AQO6GmILYZWlZxOJiDKZbPvyZbY2kUZrx50VTte8zwi_5fzQwZgppswsp2SSOvFAlhfv3wrUlp6VPqOhOgxD7Y4DZPjThKawC7z3AcGZRw.mp4?_nc_cat=111&_nc_oc=Adok8-IYw9HYtkcOCbO2DCGXVQsdQNVUpz0NOengNgC9-WysLEK1IB2m_nffcGMbt4k&_nc_sid=8bf8fe&_nc_ht=video.fsgn5-11.fna.fbcdn.net&_nc_ohc=XJA6rV1GTmkQ7kNvwGy0ptA&efg=eyJ2ZW5jb2RlX3RhZyI6Inhwdl9wcm9ncmVzc2l2ZS5WSV9VU0VDQVNFX1BST0RVQ1RfVFlQRS4uQzMuMzYwLnN2ZV9zZCIsInhwdl9hc3NldF9pZCI6MjM1Njc3Njg1MTQ4MTQyMSwiYXNzZXRfYWdlX2RheXMiOjQsInZpX3VzZWNhc2VfaWQiOjEwMTM5LCJkdXJhdGlvbl9zIjo4MSwidXJsZ2VuX3NvdXJjZSI6Ind3dyJ9&ccb=17-1&_nc_gid=dG64M-PacbjgCP_GrM7ZLg&_nc_ss=7a389&_nc_zt=28&oh=00_Af3hTmG6v498GKrELlCTymYWijiudtCcA_iP3Ansy_tnQw&oe=69DAF0FB | K55: shop.try-forge.com | L55: 132584606613853
A56: 955202186999201 | B56: The Everyday Man | C56: 46114 | D56: Image | E56: Attractive Skin in 3 Weeks | F56: How can beef tallow rejuvenate and revitalize your skin, making you look years younger quickly? Because it contains 12 out of the 16 essential nutrients your skin needs. Vitamins, fatty acids, and so much more... ✔ Tightens wrinkles QUICKLY ✔ Hydrates and repairs the skin ✔ Clears up dark spots ✔ Reduces eye bags ✔ 100% natural Want to try it out? Click the link below to get your pure beef tallow balm now! 👇 | G56: Very Few Men Know This... | H56: https://shop.try-forge.com/listicle-eyebags | I56: Shop now | J56: https://scontent.fsgn5-12.fna.fbcdn.net/v/t39.35426-6/659788010_1452848439955602_4487234627701999420_n.jpg?stp=dst-jpg_s600x600_tt6&_nc_cat=105&ccb=1-7&_nc_sid=c53f8f&_nc_ohc=-1zU0P-dYZwQ7kNvwERwyvf&_nc_oc=AdoxGE9UaG2ctflGvj0ry0zkOx57U6FB0SCUmBezmqzA-6tpIImy6v_S0TNuT2JN5dw&_nc_zt=14&_nc_ht=scontent.fsgn5-12.fna&_nc_gid=NXq84vVKPOq1xADBe7xB8A&_nc_ss=7a389&oh=00_Af2brQzLr-XL_N1zD8Q66TRzLeRIoiUwtMxFQprUQGUvng&oe=69DAFDCD | K56: shop.try-forge.com | L56: 768328883041750
A57: 1426097608781891 | B57: The Everyday Man | C57: 46114 | D57: Image | E57: Attractive Skin in 3 Weeks | F57: How can beef tallow rejuvenate and revitalize your skin, making you look years younger quickly? Because it contains 12 out of the 16 essential nutrients your skin needs. Vitamins, fatty acids, and so much more... ✔ Tightens wrinkles QUICKLY ✔ Hydrates and repairs the skin ✔ Clears up dark spots ✔ Reduces eye bags ✔ 100% natural Want to try it out? Click the link below to get your pure beef tallow balm now! 👇 | G57: Very Few Men Know This... | H57: https://shop.try-forge.com/listicle-eyebags | I57: Shop now | J57: https://scontent.fsgn5-5.fna.fbcdn.net/v/t39.35426-6/663034065_775314498780566_1558654352504408_n.jpg?stp=dst-jpg_s600x600_tt6&_nc_cat=100&ccb=1-7&_nc_sid=c53f8f&_nc_ohc=cRyKJkC54swQ7kNvwEzFt84&_nc_oc=Adp-Ia41YOwZkp493WyNr_AKqh_Y6OZWRNOI9Ujb4PXgaKCH73uWr0mw5cZ0NNvfuFA&_nc_zt=14&_nc_ht=scontent.fsgn5-5.fna&_nc_gid=NXq84vVKPOq1xADBe7xB8A&_nc_ss=7a389&oh=00_Af013bB87Zzs4PVsKY8XGW2lQfkoq520i8Gwn3zavsEAkA&oe=69DADD00 | K57: shop.try-forge.com | L57: 768328883041750
A58: 26889414330656621 | B58: The Everyday Man | C58: 46114 | D58: Image | E58: Attractive Skin in 3 Weeks | F58: How can beef tallow rejuvenate and revitalize your skin, making you look years younger quickly? Because it contains 12 out of the 16 essential nutrients your skin needs. Vitamins, fatty acids, and so much more... ✔ Tightens wrinkles QUICKLY ✔ Hydrates and repairs the skin ✔ Clears up dark spots ✔ Reduces eye bags ✔ 100% natural Want to try it out? Click the link below to get your pure beef tallow balm now! 👇 | G58: Very Few Men Know This... | H58: https://shop.try-forge.com/listicle-eyebags | I58: Shop now | J58: https://scontent.fsgn5-5.fna.fbcdn.net/v/t39.35426-6/658367303_941112998638132_7706141740951497852_n.jpg?stp=dst-jpg_s600x600_tt6&_nc_cat=102&ccb=1-7&_nc_sid=c53f8f&_nc_ohc=yXN5rKPAlmgQ7kNvwEPcfuj&_nc_oc=AdqTnRYwEpOZzrpC-W6BtzkDL5diulI4Jc1Xlefndf6WwBSwOOsTf0qaqxU-jUDIA_Y&_nc_zt=14&_nc_ht=scontent.fsgn5-5.fna&_nc_gid=NXq84vVKPOq1xADBe7xB8A&_nc_ss=7a389&oh=00_Af3VLLclP1PuS-4oSkemhyxin6qKxHYpUMgks-PRxYKZfg&oe=69DAF7DC | K58: shop.try-forge.com | L58: 768328883041750
A59: 828356336274649 | B59: The Everyday Man | C59: 46114 | D59: Image | E59: Attractive Skin in 3 Weeks | F59: How can beef tallow rejuvenate and revitalize your skin, making you look years younger quickly? Because it contains 12 out of the 16 essential nutrients your skin needs. Vitamins, fatty acids, and so much more... ✔ Tightens wrinkles QUICKLY ✔ Hydrates and repairs the skin ✔ Clears up dark spots ✔ Reduces eye bags ✔ 100% natural Want to try it out? Click the link below to get your pure beef tallow balm now! 👇 | G59: Very Few Men Know This... | H59: https://shop.try-forge.com/listicle-eyebags | I59: Shop now | J59: https://scontent.fsgn5-12.fna.fbcdn.net/v/t39.35426-6/659043481_961777046308560_2275574062600167369_n.jpg?stp=dst-jpg_s600x600_tt6&_nc_cat=103&ccb=1-7&_nc_sid=c53f8f&_nc_ohc=KVaVPK9MgYAQ7kNvwGejO0o&_nc_oc=Adp3lrZy8mydiwujxk4fECY6CwL649t8h2oJkfwjz-JaV_RqRhEkbo_I8hVmWu6YJic&_nc_zt=14&_nc_ht=scontent.fsgn5-12.fna&_nc_gid=NXq84vVKPOq1xADBe7xB8A&_nc_ss=7a389&oh=00_Af3XOqv_P5t6azJt8CqQ_WgeScScGVPBpmQTNgLDUb8YWQ&oe=69DADE4F | K59: shop.try-forge.com | L59: 768328883041750
A60: 832846685770578 | B60: The Everyday Man | C60: 46112 | D60: Video | E60: Attractive Skin in 3 Weeks | F60: How can beef tallow rejuvenate and revitalize your skin, making you look years younger quickly? Because it contains 12 out of the 16 essential nutrients your skin needs. Vitamins, fatty acids, and so much more... ✔ Tightens wrinkles QUICKLY ✔ Hydrates and repairs the skin ✔ Clears up dark spots ✔ Reduces eye bags ✔ 100% natural Want to try it out? Click the link below to get your pure beef tallow balm now! 👇 | G60: Very Few Men Know This... | H60: https://shop.try-forge.com/mens-lifestyle-essentials-1 | I60: Shop now | J60: https://video.fsgn5-3.fna.fbcdn.net/o1/v/t2/f2/m412/AQOlax1FUnxl0gYbaGdXANEvWLWKgMs4wfrNMCP21ROCUzYwkx2JDapw_xc_Y1WO7CLTaC9VDD7GjheMoKUHS92TWYCT_M4vvxPTzty8dg.mp4?_nc_cat=104&_nc_oc=AdrrkkWZzoM6PZoqmpWku9SwVrpm_ImPHo-PlXuus2kfsRwaGZeCK7XifxErCdG5sf0&_nc_sid=8bf8fe&_nc_ht=video.fsgn5-3.fna.fbcdn.net&_nc_ohc=VeLgELSdzlMQ7kNvwFnhOeq&efg=eyJ2ZW5jb2RlX3RhZyI6Inhwdl9wcm9ncmVzc2l2ZS5WSV9VU0VDQVNFX1BST0RVQ1RfVFlQRS4uQzMuMzU2LnN2ZV9zZCIsInhwdl9hc3NldF9pZCI6MTY2MDc1NjM0MjAxMTcwMywiYXNzZXRfYWdlX2RheXMiOjYsInZpX3VzZWNhc2VfaWQiOjEwMTM5LCJkdXJhdGlvbl9zIjoxMzAsInVybGdlbl9zb3VyY2UiOiJ3d3cifQ%3D%3D&ccb=17-1&_nc_gid=NXq84vVKPOq1xADBe7xB8A&_nc_ss=7a389&_nc_zt=28&oh=00_Af3UPFs--S5jqyA4ZogsbdL0x4Uy3jCgc2g3_HrykRW-Yg&oe=69DAFDB2 | K60: shop.try-forge.com | L60: 768328883041750
A61: 1.9820491e+15 | B61: The Everyday Man | C61: 46114 | D61: Image | E61: Attractive Skin in 3 Weeks | F61: How can beef tallow rejuvenate and revitalize your skin, making you look years younger quickly? Because it contains 12 out of the 16 essential nutrients your skin needs. Vitamins, fatty acids, and so much more... ✔ Tightens wrinkles QUICKLY ✔ Hydrates and repairs the skin ✔ Clears up dark spots ✔ Reduces eye bags ✔ 100% natural Want to try it out? Click the link below to get your pure beef tallow balm now! 👇 | G61: Very Few Men Know This... | H61: https://shop.try-forge.com/listicle-eyebags | I61: Shop now | J61: https://scontent.fsgn5-12.fna.fbcdn.net/v/t39.35426-6/659122182_910023448735587_3770444836334701257_n.jpg?stp=dst-jpg_s600x600_tt6&_nc_cat=105&ccb=1-7&_nc_sid=c53f8f&_nc_ohc=mlbr2UZc5YIQ7kNvwG1M-NA&_nc_oc=AdphSBMRoLdEQmWHUn0FeXX5ln218PvpeOe1NEXW3Q8i2R_gCQLa477Ebv7cYDxYBFU&_nc_zt=14&_nc_ht=scontent.fsgn5-12.fna&_nc_gid=NXq84vVKPOq1xADBe7xB8A&_nc_ss=7a389&oh=00_Af0IQQX_rCO38WJpDhin-iNlXXe3q72BwCVFJ0G680JmTQ&oe=69DAE633 | K61: shop.try-forge.com | L61: 768328883041750
A62: 1622784985434403 | B62: The Everyday Man | C62: 46114 | D62: Image | E62: Attractive Skin in 3 Weeks | F62: How can beef tallow rejuvenate and revitalize your skin, making you look years younger quickly? Because it contains 12 out of the 16 essential nutrients your skin needs. Vitamins, fatty acids, and so much more... ✔ Tightens wrinkles QUICKLY ✔ Hydrates and repairs the skin ✔ Clears up dark spots ✔ Reduces eye bags ✔ 100% natural Want to try it out? Click the link below to get your pure beef tallow balm now! 👇 | G62: Very Few Men Know This... | H62: https://shop.try-forge.com/listicle-eyebags | I62: Shop now | J62: https://scontent.fsgn5-5.fna.fbcdn.net/v/t39.35426-6/662584347_1687568915598320_3804527176087578584_n.jpg?stp=dst-jpg_s600x600_tt6&_nc_cat=102&ccb=1-7&_nc_sid=c53f8f&_nc_ohc=JhKdGHJDR2sQ7kNvwFeXBbn&_nc_oc=AdqbvLJ4qPbzBW-5vp-dlokG4XxBDSFDE8rrlCqTT98_sI8NIeM1xfC21PntVATxmQo&_nc_zt=14&_nc_ht=scontent.fsgn5-5.fna&_nc_gid=NXq84vVKPOq1xADBe7xB8A&_nc_ss=7a389&oh=00_Af1OeVCaTNtUP2aTK0Q301bHW7masYziiu2sOHFW8AUFFA&oe=69DB01C2 | K62: shop.try-forge.com | L62: 768328883041750
A63: 1867534341301537 | B63: The Everyday Man | C63: 46113 | D63: Image | E63: Attractive Skin in 3 Weeks | F63: How can beef tallow rejuvenate and revitalize your skin, making you look years younger quickly? Because it contains 12 out of the 16 essential nutrients your skin needs. Vitamins, fatty acids, and so much more... ✔ Tightens wrinkles QUICKLY ✔ Hydrates and repairs the skin ✔ Clears up dark spots ✔ Reduces eye bags ✔ 100% natural Want to try it out? Click the link below to get your pure beef tallow balm now! 👇 | G63: Very Few Men Know This... | H63: https://shop.try-forge.com/listicle-eyebags | I63: Shop now | J63: https://scontent.fsgn5-5.fna.fbcdn.net/v/t39.35426-6/658869972_2028463687743417_7060688717455947151_n.jpg?stp=dst-jpg_s600x600_tt6&_nc_cat=108&ccb=1-7&_nc_sid=c53f8f&_nc_ohc=NcK3tIww8VMQ7kNvwH35hML&_nc_oc=AdqJLUXc7d3VTEYSnUiui21WUQODTLkROoDUrNsW5nwllWrSDH-HK0SIVIMkmDoWAN4&_nc_zt=14&_nc_ht=scontent.fsgn5-5.fna&_nc_gid=NXq84vVKPOq1xADBe7xB8A&_nc_ss=7a389&oh=00_Af1uaE3Cnp6R_-rvyAZyibdYE48efK5PwCsPji8p--wh-w&oe=69DAD86E | K63: shop.try-forge.com | L63: 768328883041750
A64: 1937894073479815 | B64: The Everyday Man | C64: 46113 | D64: Image | E64: Attractive Skin in 3 Weeks | F64: How can beef tallow rejuvenate and revitalize your skin, making you look years younger quickly? Because it contains 12 out of the 16 essential nutrients your skin needs. Vitamins, fatty acids, and so much more... ✔ Tightens wrinkles QUICKLY ✔ Hydrates and repairs the skin ✔ Clears up dark spots ✔ Reduces eye bags ✔ 100% natural Want to try it out? Click the link below to get your pure beef tallow balm now! 👇 | G64: Very Few Men Know This... | H64: https://shop.try-forge.com/listicle-eyebags | I64: Shop now | J64: https://scontent.fsgn5-5.fna.fbcdn.net/v/t39.35426-6/662312723_872629875795630_8188668645222750474_n.jpg?stp=dst-jpg_s600x600_tt6&_nc_cat=108&ccb=1-7&_nc_sid=c53f8f&_nc_ohc=mCMoaQ-JXDYQ7kNvwGaNNqI&_nc_oc=AdrRGZdgJtLGFcXITtr4MyIQB4aYTlyb3U8ziWXFKGSDLHUdFAMJbUu6ADvFYcuBxoM&_nc_zt=14&_nc_ht=scontent.fsgn5-5.fna&_nc_gid=NXq84vVKPOq1xADBe7xB8A&_nc_ss=7a389&oh=00_Af1I-ioxKlT4Q065_Sv8xaNwhrNKdRQ13UP34Zlf-RRyfA&oe=69DB02EB | K64: shop.try-forge.com | L64: 768328883041750
A65: 791143443679456 | B65: The Everyday Man | C65: 46113 | D65: Image | E65: Attractive Skin in 3 Weeks | F65: How can beef tallow rejuvenate and revitalize your skin, making you look years younger quickly? Because it contains 12 out of the 16 essential nutrients your skin needs. Vitamins, fatty acids, and so much more... ✔ Tightens wrinkles QUICKLY ✔ Hydrates and repairs the skin ✔ Clears up dark spots ✔ Reduces eye bags ✔ 100% natural Want to try it out? Click the link below to get your pure beef tallow balm now! 👇 | G65: Very Few Men Know This... | H65: https://shop.try-forge.com/listicle-eyebags | I65: Shop now | J65: https://scontent.fsgn5-12.fna.fbcdn.net/v/t39.35426-6/659271548_1116016760680950_6609908154404518293_n.jpg?stp=dst-jpg_s600x600_tt6&_nc_cat=103&ccb=1-7&_nc_sid=c53f8f&_nc_ohc=zpvD3MWQcScQ7kNvwF4Xu7J&_nc_oc=AdrKnakniSm9H5IW6fllSmVUM5YukNpTXrbaiv4LgqG0Oge4GOYt1Fs_F9G9CGaf1mc&_nc_zt=14&_nc_ht=scontent.fsgn5-12.fna&_nc_gid=NXq84vVKPOq1xADBe7xB8A&_nc_ss=7a389&oh=00_Af1_nU_azm6ATm8JmMgI62qbdKLDLQzaKByTkrGgXRsnPg&oe=69DADAFF | K65: shop.try-forge.com | L65: 768328883041750
A66: 2068327570403208 | B66: The Everyday Man | C66: 46113 | D66: Image | E66: Attractive Skin in 3 Weeks | F66: How can beef tallow rejuvenate and revitalize your skin, making you look years younger quickly? Because it contains 12 out of the 16 essential nutrients your skin needs. Vitamins, fatty acids, and so much more... ✔ Tightens wrinkles QUICKLY ✔ Hydrates and repairs the skin ✔ Clears up dark spots ✔ Reduces eye bags ✔ 100% natural Want to try it out? Click the link below to get your pure beef tallow balm now! 👇 | G66: Very Few Men Know This... | H66: https://shop.try-forge.com/listicle-eyebags | I66: Shop now | J66: https://scontent.fsgn5-10.fna.fbcdn.net/v/t39.35426-6/658945836_1279935760233238_5826162448266592855_n.jpg?stp=dst-jpg_s600x600_tt6&_nc_cat=101&ccb=1-7&_nc_sid=c53f8f&_nc_ohc=I7m1OWC0BwAQ7kNvwE1_J4g&_nc_oc=AdrUxGM1AXZ_JpH-thAGQ0sYysD3qPjybtCRJdR1-SKKsEQwNEHG1urKciM571FcbCs&_nc_zt=14&_nc_ht=scontent.fsgn5-10.fna&_nc_gid=NXq84vVKPOq1xADBe7xB8A&_nc_ss=7a389&oh=00_Af25ou5HiWILS0U3gzy0wFTW99UJHjnnCqO_ddHKPqk4_g&oe=69DAE03E | K66: shop.try-forge.com | L66: 768328883041750
A67: 1656966502395823 | B67: The Everyday Man | C67: 46112 | D67: Video | E67: Attractive Skin in 3 Weeks | F67: How can beef tallow rejuvenate and revitalize your skin, making you look years younger quickly? Because it contains 12 out of the 16 essential nutrients your skin needs. Vitamins, fatty acids, and so much more... ✔ Tightens wrinkles QUICKLY ✔ Hydrates and repairs the skin ✔ Clears up dark spots ✔ Reduces eye bags ✔ 100% natural Want to try it out? Click the link below to get your pure beef tallow balm now! 👇 | G67: Very Few Men Know This... | H67: https://shop.try-forge.com/mens-lifestyle-essentials-1 | I67: Shop now | J67: https://video.fsgn5-10.fna.fbcdn.net/o1/v/t2/f2/m412/AQMY-VktegjLnTPBhvfN_UaF9heNeF8gK0QFxxunr9xJEXVhy2EhHIKR44L-CGb-prdtAftXWptcgl6RGOkOgVZ0RQx7w86t30O71xVh7w.mp4?_nc_cat=106&_nc_oc=AdpC1btibE-JdQz89NOJTdiCycdnjhc07Xs7L1H5owB0rS5QTGSGdsuxbRZOTBukX2k&_nc_sid=8bf8fe&_nc_ht=video.fsgn5-10.fna.fbcdn.net&_nc_ohc=Wn8qC4A55q0Q7kNvwEQzqwT&efg=eyJ2ZW5jb2RlX3RhZyI6Inhwdl9wcm9ncmVzc2l2ZS5WSV9VU0VDQVNFX1BST0RVQ1RfVFlQRS4uQzMuMzU2LnN2ZV9zZCIsInhwdl9hc3NldF9pZCI6MjIwMDYwNjkxNzM0MzY2NSwiYXNzZXRfYWdlX2RheXMiOjYsInZpX3VzZWNhc2VfaWQiOjEwMTM5LCJkdXJhdGlvbl9zIjoxMzAsInVybGdlbl9zb3VyY2UiOiJ3d3cifQ%3D%3D&ccb=17-1&_nc_gid=NXq84vVKPOq1xADBe7xB8A&_nc_ss=7a389&_nc_zt=28&oh=00_Af3-mUAGtl8s2kq9MHJJ7-XOIvtgrbjaoJ2WGWAH0PRylg&oe=69DAFEBC | K67: shop.try-forge.com | L67: 768328883041750
A68: 2122229611946797 | B68: The Everyday Man | C68: 46108 | D68: Image | E68: 45 Minutes Just Standing | F68: I was diagnosed with rheumatoid arthritis back in 2003. Hard to believe that was over 20 years ago now. From the very beginning, it was rough. But the mornings... God, the mornings were the worst. I'd wake up and my entire body felt like concrete. My fingers wouldn't bend. My knees felt locked in place. It took me 45 minutes just to get out of bed some days. The doctors put me on Enbrel and Methotrexate. Strong medications that were supposed to help with the morning stiffness. And I stayed on them for years. But here's the truth nobody tells you... I was still waking up like the Tin Man every single morning. Locked up. Frozen. Dreading those first movements. My wife would have to help me open pill bottles because my hands were so stiff I couldn't grip anything properly. Five years in, I hit my breaking point. That's when I heard about something called beef organ nutrition. And not some trendy superfood powder from Instagram. I'm talking about the actual organ meats our ancestors ate daily — the nutrients that built strong joints and flexible bodies. So I gave it a shot with something called Forge Beef Organ Complex. And slowly, something incredible happened. Those brutal morning episodes? They started getting shorter. Week by week, I was waking up with less stiffness. Until one morning... I got out of bed and walked straight to the bathroom without shuffling like an old man. No 45-minute warm-up period. No wife helping me open bottles. Just normal movement. Like a human being should move. And I'll tell you this... I've never looked back. Now here's the part most people don't realize: Your joints need the same nutrients your ancestors got from eating organ meats. The synthetic glucosamine at the drugstore? Forget it. Your body barely recognizes it. That's why I only take Forge now. It's the only thing I've found that actually works. 🥩 Beef heart — packed with CoQ10 for cellular energy and circulation 🥩 Beef liver — nature's multivitamin with bioavailable nutrients 🥩 Beef bone marrow — 20X more collagen than bone broth 🥩 Beef pancreas — digestive enzymes for better nutrient absorption 🥩 Beef testicles — testosterone support for muscle strength and recovery No synthetic garbage. No lab-created compounds. Just the same organ nutrition that kept our ancestors moving pain-free their entire lives. It's been part of my daily routine for years now. Two capsules with breakfast. That's it. And honestly? After decades of dreading every morning... These little capsules gave me back my life. If you're still waking up stiff, still taking 30+ minutes to feel human again, still shuffling around like you're 90 years old... Don't wait as long as I did. This changed my mornings and it could change yours too. Click the link below to see if Forge is still in stock. | G68: See the organ solution | H68: https://secure.try-forge.com/bridge-a1-simple | I68: Learn more | J68: https://scontent.fsgn5-10.fna.fbcdn.net/v/t39.35426-6/656522316_2763356820665386_3445476120755656559_n.jpg?stp=dst-jpg_s600x600_tt6&_nc_cat=101&ccb=1-7&_nc_sid=c53f8f&_nc_ohc=ebdmJV-7pG4Q7kNvwG2FNkY&_nc_oc=AdrBO-ng3na_B--_6B8wcp1Je4dEisCNESmEfAy7Dl146DCybC5Z7-TG19dle4S2vdw&_nc_zt=14&_nc_ht=scontent.fsgn5-10.fna&_nc_gid=NXq84vVKPOq1xADBe7xB8A&_nc_ss=7a389&oh=00_Af1e5jRhqaOM_m7VUqGQUJ1dNeQe96Nw2T982lInZzKDbg&oe=69DADC07 | K68: shop.try-forge.com | L68: 768328883041750
A69: 906480158881728 | B69: The Everyday Man | C69: 46113 | D69: Image | E69: Hair Loss Isn't Genetic For Most Men 🧬 | F69: Losing more hair every time you shower? 😬🔥 Before you blame genetics, read this. Most men assume hair loss is locked in their DNA. But new research shows that the majority of early hair thinning in men is driven by nutrient deficiencies, not genetics. Studies published in the Journal of Dermatological Science found that low levels of iron, zinc, biotin, B12, and vitamin A are directly linked to hair follicle shutdown. When these nutrients drop, your follicles literally starve and stop producing new hair 😤 And here is the part that makes it worse. The modern diet is completely stripped of these nutrients. Processed food, synthetic supplements your body barely absorbs, and low quality meat mean your hair follicles have been running on empty for years ⚠️ That is why beef organs work where other "hair supplements" fail 🥩💊 They deliver the exact bioavailable nutrients your follicles are starving for, in a form your body actually recognizes and uses. 🥩 Beef Liver for retinol vitamin A, B12, iron, and biotin that directly fuel hair follicle growth cycles 🫀️ Beef Heart for CoQ10 that improves blood circulation to your scalp and energizes follicle cells 💥 Beef Testicle for zinc, selenium, and peptides that support the hormonal balance behind healthy hair 🫘 Beef Pancreas for digestive enzymes that maximize absorption of every nutrient you take in 🦴 Bone Marrow for collagen, growth factors, and healthy fats that strengthen hair from the root When your follicles finally get what they need, the difference is real. 🔥 Less hair in the drain ⚡ Thicker strands that actually hold 💪 New growth in thinning areas 😌 Confidence when you look in the mirror 🧬 Your hair is responding to nutrition, not fighting genetics Your hair did not give up on you. Your diet gave up on your hair. Feed it right and watch what happens 🔥💪 | G69: Feed your follicles what they actually need 🥩 | H69: https://secure.try-forge.com/bridge-a1-simple | I69: Shop now | J69: https://scontent.fsgn5-8.fna.fbcdn.net/v/t39.35426-6/660532946_919234744204592_3916693862818953873_n.jpg?stp=dst-jpg_s600x600_tt6&_nc_cat=109&ccb=1-7&_nc_sid=c53f8f&_nc_ohc=uq5ZxKtzD_UQ7kNvwGDh0om&_nc_oc=AdqY4iybwldi2Q81gaq8Wn_h5f-SunmsBeGElFA95bxtm2Q2sjkVHy856hPrxp8rxdI&_nc_zt=14&_nc_ht=scontent.fsgn5-8.fna&_nc_gid=NXq84vVKPOq1xADBe7xB8A&_nc_ss=7a389&oh=00_Af3C09QAAdCB0Y-BfGr0e8nJoM9ha1McnGro3Wca_NexvA&oe=69DAE32A | K69: shop.try-forge.com | L69: 768328883041750
A70: 2135351933951366 | B70: The Everyday Man | C70: 46113 | D70: Image | E70: Bloated For No Reason? 🫃 | F70: Stomach hurting for no clear reason? Always tired? Nobody talks about this and it explains WAY more than people think. If you deal with stuff like 👇 Random stomach pain or bloating after eating 🤢 Feeling tired even when you sleep enough 😴 Brain fog, low focus, low patience 🧠 Cravings that feel out of control, especially sugar 🍩 Low energy, low drive, low motivation 😐 There's a chance it's not your diet, It's not stress. It could be parasites 😬🦠 You don't need to be dirty, travel the world, or drink bad water. Parasites can come from food, takeout, sushi, pets, vegetables... And they don't just mess with your stomach. They steal nutrients, drain your energy, mess with digestion, and keep your body stuck feeling weak and off. That's why some people eat clean, train, take supplements, and still feel horrible. Here's the part that clicked for me 👇 Parasites survive best when your body is undernourished. Low vitamins, low minerals, weak gut, low immune energy. So instead of just trying to "kill" them, you need to out-feed them 🥩🔥 That's why beef organs make sense. 🥩 Liver refills the vitamins parasites drain first. 🫀 Heart supports real cellular energy, not fake caffeine energy⚡ 🫘 Pancreas helps break down food properly so parasites have less to feed on. 🦴 Bone marrow supports gut repair and immune strength. 🥚 Testicles provide minerals men need for drive and resilience 💪 Once your body is properly fueled, it finally has the strength to push back. It's not magic, it's fixing something that's been quietly draining you. If your gut feels off and nothing makes sense anymore… This might be the missing piece 😮‍💨🔥 | G70: 97% feel a healtheir gut within 10 days ⚡ | H70: https://secure.try-forge.com/bridge-a1-simple | I70: Shop now | J70: https://scontent.fsgn5-5.fna.fbcdn.net/v/t39.35426-6/661630112_1297394522313393_3167870446868593800_n.jpg?stp=dst-jpg_s600x600_tt6&_nc_cat=108&ccb=1-7&_nc_sid=c53f8f&_nc_ohc=URrhVpe2Y7oQ7kNvwEAMC7s&_nc_oc=AdqtIlh5JdwaZJ5yuEVrK8homLvep6FfP3rHXGODYoBJk28RyGrPmBRa4f7cOe3Kmb8&_nc_zt=14&_nc_ht=scontent.fsgn5-5.fna&_nc_gid=NXq84vVKPOq1xADBe7xB8A&_nc_ss=7a389&oh=00_Af0Gy8W3qOB6gpM4nWwVxn2w4QWOOq8QzWuCRiRa4Pt1Ug&oe=69DAFFE1 | K70: shop.try-forge.com | L70: 768328883041750
A71: 3129363913914056 | B71: The Everyday Man | C71: 46113 | D71: Image | E71: Attractive Skin in 3 Weeks | F71: How can beef tallow rejuvenate and revitalize your skin, making you look years younger quickly? Because it contains 12 out of the 16 essential nutrients your skin needs. Vitamins, fatty acids, and so much more... ✔ Tightens wrinkles QUICKLY ✔ Hydrates and repairs the skin ✔ Clears up dark spots ✔ Reduces eye bags ✔ 100% natural Want to try it out? Click the link below to get your pure beef tallow balm now! 👇 | G71: Very Few Men Know This... | H71: https://shop.try-forge.com/listicle-eyebags | I71: Shop now | J71: https://scontent.fsgn5-5.fna.fbcdn.net/v/t39.35426-6/659580849_4323507317795800_1703307434765145357_n.jpg?stp=dst-jpg_s600x600_tt6&_nc_cat=108&ccb=1-7&_nc_sid=c53f8f&_nc_ohc=b22iG69HBKYQ7kNvwH24sfV&_nc_oc=AdoPWQGvsnOguMOwlpnGcwTyM6n38Mj6vmnp0DtT9Uo1uZuVOFvvPqyl6a3OHBmYFqM&_nc_zt=14&_nc_ht=scontent.fsgn5-5.fna&_nc_gid=NXq84vVKPOq1xADBe7xB8A&_nc_ss=7a389&oh=00_Af1kUJ961ibNOFxsXXAbHNYjnwD13RWFOnW2lvQVs3QbvQ&oe=69DB0319 | K71: shop.try-forge.com | L71: 768328883041750
A72: 909635618562401 | B72: The Everyday Man | C72: 46112 | D72: Video | E72: Attractive Skin in 3 Weeks | F72: How can beef tallow rejuvenate and revitalize your skin, making you look years younger quickly? Because it contains 12 out of the 16 essential nutrients your skin needs. Vitamins, fatty acids, and so much more... ✔ Tightens wrinkles QUICKLY ✔ Hydrates and repairs the skin ✔ Clears up dark spots ✔ Reduces eye bags ✔ 100% natural Want to try it out? Click the link below to get your pure beef tallow balm now! 👇 | G72: Very Few Men Know This... | H72: https://shop.try-forge.com/mens-lifestyle-essentials-1 | I72: Shop now | J72: https://video.fsgn5-5.fna.fbcdn.net/o1/v/t2/f2/m412/AQMOwQ8JnMV8eDefsjZXGxJWzo3AfMENbzOx7Lle-Xr2kZz89Flba0raPHiycuk94Ia2O6XHccSOnXchU2wf-GsHh01wKTfB-E52SGy1Ww.mp4?_nc_cat=102&_nc_oc=AdpbgfvzySoUGdsinNt4LTf1QVKG6ZQNQ2n-tnjezwWT7uH6tfNFPSSwHGnpeTSFikM&_nc_sid=8bf8fe&_nc_ht=video.fsgn5-5.fna.fbcdn.net&_nc_ohc=cvlpU30CdCwQ7kNvwHDjdvs&efg=eyJ2ZW5jb2RlX3RhZyI6Inhwdl9wcm9ncmVzc2l2ZS5WSV9VU0VDQVNFX1BST0RVQ1RfVFlQRS4uQzMuMzU2LnN2ZV9zZCIsInhwdl9hc3NldF9pZCI6MTQ3NjQ1MTk0NzQ3ODkzMSwiYXNzZXRfYWdlX2RheXMiOjYsInZpX3VzZWNhc2VfaWQiOjEwMTM5LCJkdXJhdGlvbl9zIjoxMzEsInVybGdlbl9zb3VyY2UiOiJ3d3cifQ%3D%3D&ccb=17-1&_nc_gid=NXq84vVKPOq1xADBe7xB8A&_nc_ss=7a389&_nc_zt=28&oh=00_Af04pKzf6mxLFCgAordXoRS5rtYqauppDxMQD1c_zVS3zg&oe=69DB0B34 | K72: shop.try-forge.com | L72: 768328883041750
A73: 945217994655029 | B73: The Everyday Man | C73: 46113 | D73: Image | E73: Bloated For No Reason? 🫃 | F73: Stomach hurting for no clear reason? Always tired? Nobody talks about this and it explains WAY more than people think. If you deal with stuff like 👇 Random stomach pain or bloating after eating 🤢 Feeling tired even when you sleep enough 😴 Brain fog, low focus, low patience 🧠 Cravings that feel out of control, especially sugar 🍩 Low energy, low drive, low motivation 😐 There's a chance it's not your diet, It's not stress. It could be parasites 😬🦠 You don't need to be dirty, travel the world, or drink bad water. Parasites can come from food, takeout, sushi, pets, vegetables... And they don't just mess with your stomach. They steal nutrients, drain your energy, mess with digestion, and keep your body stuck feeling weak and off. That's why some people eat clean, train, take supplements, and still feel horrible. Here's the part that clicked for me 👇 Parasites survive best when your body is undernourished. Low vitamins, low minerals, weak gut, low immune energy. So instead of just trying to "kill" them, you need to out-feed them 🥩🔥 That's why beef organs make sense. 🥩 Liver refills the vitamins parasites drain first. 🫀 Heart supports real cellular energy, not fake caffeine energy⚡ 🫘 Pancreas helps break down food properly so parasites have less to feed on. 🦴 Bone marrow supports gut repair and immune strength. 🥚 Testicles provide minerals men need for drive and resilience 💪 Once your body is properly fueled, it finally has the strength to push back. It's not magic, it's fixing something that's been quietly draining you. If your gut feels off and nothing makes sense anymore… This might be the missing piece 😮‍💨🔥 | G73: 97% feel a healtheir gut within 10 days ⚡ | H73: https://secure.try-forge.com/bridge-a1-simple | I73: Shop now | J73: https://scontent.fsgn5-3.fna.fbcdn.net/v/t39.35426-6/660540103_953979387332479_1662208938064218879_n.jpg?stp=dst-jpg_s600x600_tt6&_nc_cat=104&ccb=1-7&_nc_sid=c53f8f&_nc_ohc=SospvUc3E0sQ7kNvwGZsl7R&_nc_oc=AdpUwNbnNABScMxlR7hv73Z9WpeMO0KAy3xU18GHrTNo4u_c6DsS0eb2NteVlVHMKAQ&_nc_zt=14&_nc_ht=scontent.fsgn5-3.fna&_nc_gid=NXq84vVKPOq1xADBe7xB8A&_nc_ss=7a389&oh=00_Af135E8e946-cEa-Rfv6OOFgreHXrDfNz37uTPz9ZL3D_Q&oe=69DAF406 | K73: shop.try-forge.com | L73: 768328883041750
A74: 1237779891797805 | B74: The Everyday Man | C74: 46113 | D74: Image | E74: Bloated For No Reason? 🫃 | F74: Stomach hurting for no clear reason? Always tired? Nobody talks about this and it explains WAY more than people think. If you deal with stuff like 👇 Random stomach pain or bloating after eating 🤢 Feeling tired even when you sleep enough 😴 Brain fog, low focus, low patience 🧠 Cravings that feel out of control, especially sugar 🍩 Low energy, low drive, low motivation 😐 There's a chance it's not your diet, It's not stress. It could be parasites 😬🦠 You don't need to be dirty, travel the world, or drink bad water. Parasites can come from food, takeout, sushi, pets, vegetables... And they don't just mess with your stomach. They steal nutrients, drain your energy, mess with digestion, and keep your body stuck feeling weak and off. That's why some people eat clean, train, take supplements, and still feel horrible. Here's the part that clicked for me 👇 Parasites survive best when your body is undernourished. Low vitamins, low minerals, weak gut, low immune energy. So instead of just trying to "kill" them, you need to out-feed them 🥩🔥 That's why beef organs make sense. 🥩 Liver refills the vitamins parasites drain first. 🫀 Heart supports real cellular energy, not fake caffeine energy⚡ 🫘 Pancreas helps break down food properly so parasites have less to feed on. 🦴 Bone marrow supports gut repair and immune strength. 🥚 Testicles provide minerals men need for drive and resilience 💪 Once your body is properly fueled, it finally has the strength to push back. It's not magic, it's fixing something that's been quietly draining you. If your gut feels off and nothing makes sense anymore… This might be the missing piece 😮‍💨🔥 | G74: 97% feel a healtheir gut within 10 days ⚡ | H74: https://secure.try-forge.com/bridge-a1-simple | I74: Shop now | J74: https://scontent.fsgn5-10.fna.fbcdn.net/v/t39.35426-6/658086071_1609625860255676_3307824212352820185_n.jpg?stp=dst-jpg_s600x600_tt6&_nc_cat=101&ccb=1-7&_nc_sid=c53f8f&_nc_ohc=KANBBybiuH0Q7kNvwHwYi-X&_nc_oc=AdrFjaiECIThXU9A8-g_ovn5ZCxJBdiW_Ws73zcmrJmZ7t1MLfip9Igci2ZKIPTGXW4&_nc_zt=14&_nc_ht=scontent.fsgn5-10.fna&_nc_gid=NXq84vVKPOq1xADBe7xB8A&_nc_ss=7a389&oh=00_Af2kCRGJcNJ29CDAuI7qkbB1H5uVQt74E19Rg_59ZlKUBA&oe=69DAE05C | K74: shop.try-forge.com | L74: 768328883041750
A75: 2426681831102652 | B75: The Everyday Man | C75: 46113 | D75: Image | E75: Bloated For No Reason? 🫃 | F75: Stomach hurting for no clear reason? Always tired? Nobody talks about this and it explains WAY more than people think. If you deal with stuff like 👇 Random stomach pain or bloating after eating 🤢 Feeling tired even when you sleep enough 😴 Brain fog, low focus, low patience 🧠 Cravings that feel out of control, especially sugar 🍩 Low energy, low drive, low motivation 😐 There's a chance it's not your diet, It's not stress. It could be parasites 😬🦠 You don't need to be dirty, travel the world, or drink bad water. Parasites can come from food, takeout, sushi, pets, vegetables... And they don't just mess with your stomach. They steal nutrients, drain your energy, mess with digestion, and keep your body stuck feeling weak and off. That's why some people eat clean, train, take supplements, and still feel horrible. Here's the part that clicked for me 👇 Parasites survive best when your body is undernourished. Low vitamins, low minerals, weak gut, low immune energy. So instead of just trying to "kill" them, you need to out-feed them 🥩🔥 That's why beef organs make sense. 🥩 Liver refills the vitamins parasites drain first. 🫀 Heart supports real cellular energy, not fake caffeine energy⚡ 🫘 Pancreas helps break down food properly so parasites have less to feed on. 🦴 Bone marrow supports gut repair and immune strength. 🥚 Testicles provide minerals men need for drive and resilience 💪 Once your body is properly fueled, it finally has the strength to push back. It's not magic, it's fixing something that's been quietly draining you. If your gut feels off and nothing makes sense anymore… This might be the missing piece 😮‍💨🔥 | G75: 97% feel a healtheir gut within 10 days ⚡ | H75: https://secure.try-forge.com/bridge-a1-simple | I75: Shop now | J75: https://scontent.fsgn5-11.fna.fbcdn.net/v/t39.35426-6/659056156_1642203853494446_1810574266135678996_n.jpg?stp=dst-jpg_s600x600_tt6&_nc_cat=110&ccb=1-7&_nc_sid=c53f8f&_nc_ohc=q66y9WZMKk8Q7kNvwGfsh0U&_nc_oc=Adr1hYP5uaamPCFeewXSDifUYyOM16Pn5e6G4u2EA9dbk2g5fN2WfgfQrneDC73ZHOU&_nc_zt=14&_nc_ht=scontent.fsgn5-11.fna&_nc_gid=NXq84vVKPOq1xADBe7xB8A&_nc_ss=7a389&oh=00_Af3c4HTdQwBOTPucn3ZSHnigt5uO4M2UNb6KLLnQ_3cq1Q&oe=69DADFED | K75: shop.try-forge.com | L75: 768328883041750
A76: 4461157284135468 | B76: The Everyday Man | C76: 46113 | D76: Image | E76: Attractive Skin in 3 Weeks | F76: How can beef tallow rejuvenate and revitalize your skin, making you look years younger quickly? Because it contains 12 out of the 16 essential nutrients your skin needs. Vitamins, fatty acids, and so much more... ✔ Tightens wrinkles QUICKLY ✔ Hydrates and repairs the skin ✔ Clears up dark spots ✔ Reduces eye bags ✔ 100% natural Want to try it out? Click the link below to get your pure beef tallow balm now! 👇 | G76: Very Few Men Know This... | H76: https://shop.try-forge.com/listicle-eyebags | I76: Shop now | J76: https://scontent.fsgn5-3.fna.fbcdn.net/v/t39.35426-6/660557161_949267314257136_7736128482189432058_n.jpg?stp=dst-jpg_s600x600_tt6&_nc_cat=104&ccb=1-7&_nc_sid=c53f8f&_nc_ohc=n08dTT2qXI4Q7kNvwFDNOL5&_nc_oc=AdoNh6owvpbPKdGS-By-TKAXD0z_pG48oJXfQNajHjLmfUZQf4lRS0auSciiACEBTCA&_nc_zt=14&_nc_ht=scontent.fsgn5-3.fna&_nc_gid=NXq84vVKPOq1xADBe7xB8A&_nc_ss=7a389&oh=00_Af0lCkrqdSswkcHdKhl-RqqXU9dXUCM0qGKY71goN7LQ2A&oe=69DADD21 | K76: shop.try-forge.com | L76: 768328883041750
A77: 2115106209273944 | B77: The Everyday Man | C77: 46113 | D77: Image | E77: Bloated For No Reason? 🫃 | F77: Stomach hurting for no clear reason? Always tired? Nobody talks about this and it explains WAY more than people think. If you deal with stuff like 👇 Random stomach pain or bloating after eating 🤢 Feeling tired even when you sleep enough 😴 Brain fog, low focus, low patience 🧠 Cravings that feel out of control, especially sugar 🍩 Low energy, low drive, low motivation 😐 There's a chance it's not your diet, It's not stress. It could be parasites 😬🦠 You don't need to be dirty, travel the world, or drink bad water. Parasites can come from food, takeout, sushi, pets, vegetables... And they don't just mess with your stomach. They steal nutrients, drain your energy, mess with digestion, and keep your body stuck feeling weak and off. That's why some people eat clean, train, take supplements, and still feel horrible. Here's the part that clicked for me 👇 Parasites survive best when your body is undernourished. Low vitamins, low minerals, weak gut, low immune energy. So instead of just trying to "kill" them, you need to out-feed them 🥩🔥 That's why beef organs make sense. 🥩 Liver refills the vitamins parasites drain first. 🫀 Heart supports real cellular energy, not fake caffeine energy⚡ 🫘 Pancreas helps break down food properly so parasites have less to feed on. 🦴 Bone marrow supports gut repair and immune strength. 🥚 Testicles provide minerals men need for drive and resilience 💪 Once your body is properly fueled, it finally has the strength to push back. It's not magic, it's fixing something that's been quietly draining you. If your gut feels off and nothing makes sense anymore… This might be the missing piece 😮‍💨🔥 | G77: 97% feel a healtheir gut within 10 days ⚡ | H77: https://secure.try-forge.com/bridge-a1-simple | I77: Shop now | J77: https://scontent.fsgn5-10.fna.fbcdn.net/v/t39.35426-6/661247460_833733986413847_4707846676653534589_n.jpg?stp=dst-jpg_s600x600_tt6&_nc_cat=107&ccb=1-7&_nc_sid=c53f8f&_nc_ohc=asv1Kph5yUYQ7kNvwGPokDb&_nc_oc=Adom86ed9n7G4F2PSu6iJYy2PqrLVYkDagYUDZgusW0Am7bsJpU9QOMf-qEPQ8cgqaY&_nc_zt=14&_nc_ht=scontent.fsgn5-10.fna&_nc_gid=NXq84vVKPOq1xADBe7xB8A&_nc_ss=7a389&oh=00_Af2XvPYA_FJVwF6SbkVCmj13fYbMotiDuRlDgmvWH-_P3Q&oe=69DAEDFD | K77: shop.try-forge.com | L77: 768328883041750
A78: 1006292468728646 | B78: The Everyday Man | C78: 46108 | D78: Image | E78: My Morning Stiffness Hell | F78: I was diagnosed with rheumatoid arthritis back in 2003. Hard to believe that was over 20 years ago now. From the very beginning, it was rough. But the mornings... God, the mornings were the worst. I'd wake up and my entire body felt like concrete. My fingers wouldn't bend. My knees felt locked in place. It took me 45 minutes just to get out of bed some days. The doctors put me on Enbrel and Methotrexate. Strong medications that were supposed to help with the morning stiffness. And I stayed on them for years. But here's the truth nobody tells you... I was still waking up like the Tin Man every single morning. Locked up. Frozen. Dreading those first movements. My wife would have to help me open pill bottles because my hands were so stiff I couldn't grip anything properly. Five years in, I hit my breaking point. That's when I heard about something called beef organ nutrition. And not some trendy superfood powder from Instagram. I'm talking about the actual organ meats our ancestors ate daily — the nutrients that built strong joints and flexible bodies. So I gave it a shot with something called Forge Beef Organ Complex. And slowly, something incredible happened. Those brutal morning episodes? They started getting shorter. Week by week, I was waking up with less stiffness. Until one morning... I got out of bed and walked straight to the bathroom without shuffling like an old man. No 45-minute warm-up period. No wife helping me open bottles. Just normal movement. Like a human being should move. And I'll tell you this... I've never looked back. Now here's the part most people don't realize: Your joints need the same nutrients your ancestors got from eating organ meats. The synthetic glucosamine at the drugstore? Forget it. Your body barely recognizes it. That's why I only take Forge now. It's the only thing I've found that actually works. 🥩 Beef heart — packed with CoQ10 for cellular energy and circulation 🥩 Beef liver — nature's multivitamin with bioavailable nutrients 🥩 Beef bone marrow — 20X more collagen than bone broth 🥩 Beef pancreas — digestive enzymes for better nutrient absorption 🥩 Beef testicles — testosterone support for muscle strength and recovery No synthetic garbage. No lab-created compounds. Just the same organ nutrition that kept our ancestors moving pain-free their entire lives. It's been part of my daily routine for years now. Two capsules with breakfast. That's it. And honestly? After decades of dreading every morning... These little capsules gave me back my life. If you're still waking up stiff, still taking 30+ minutes to feel human again, still shuffling around like you're 90 years old... Don't wait as long as I did. This changed my mornings and it could change yours too. Click the link below to see if Forge is still in stock. | G78: Finally wakes up normal | H78: https://secure.try-forge.com/bridge-a1-simple | I78: Learn more | J78: https://scontent.fsgn5-3.fna.fbcdn.net/v/t39.35426-6/658697727_2159717251529497_7150415521931615289_n.jpg?stp=dst-jpg_s600x600_tt6&_nc_cat=104&ccb=1-7&_nc_sid=c53f8f&_nc_ohc=LQone3WWnH4Q7kNvwHSNzmN&_nc_oc=Adp7yIms18_DretMXswXoXH65NARmevD2REl6leaY0XO6Kjy_j_bynD9WpKjCvGV7AU&_nc_zt=14&_nc_ht=scontent.fsgn5-3.fna&_nc_gid=NXq84vVKPOq1xADBe7xB8A&_nc_ss=7a389&oh=00_Af1Klcc1AyxFlTqr3miJii2NAOlcMFV6BWdLAI9kNwIlmw&oe=69DAF84D | K78: shop.try-forge.com | L78: 768328883041750
A79: 1073480732508664 | B79: The Everyday Man | C79: 46113 | D79: Image | E79: Hair Loss Isn't Genetic For Most Men 🧬 | F79: Losing more hair every time you shower? 😬🔥 Before you blame genetics, read this. Most men assume hair loss is locked in their DNA. But new research shows that the majority of early hair thinning in men is driven by nutrient deficiencies, not genetics. Studies published in the Journal of Dermatological Science found that low levels of iron, zinc, biotin, B12, and vitamin A are directly linked to hair follicle shutdown. When these nutrients drop, your follicles literally starve and stop producing new hair 😤 And here is the part that makes it worse. The modern diet is completely stripped of these nutrients. Processed food, synthetic supplements your body barely absorbs, and low quality meat mean your hair follicles have been running on empty for years ⚠️ That is why beef organs work where other "hair supplements" fail 🥩💊 They deliver the exact bioavailable nutrients your follicles are starving for, in a form your body actually recognizes and uses. 🥩 Beef Liver for retinol vitamin A, B12, iron, and biotin that directly fuel hair follicle growth cycles 🫀️ Beef Heart for CoQ10 that improves blood circulation to your scalp and energizes follicle cells 💥 Beef Testicle for zinc, selenium, and peptides that support the hormonal balance behind healthy hair 🫘 Beef Pancreas for digestive enzymes that maximize absorption of every nutrient you take in 🦴 Bone Marrow for collagen, growth factors, and healthy fats that strengthen hair from the root When your follicles finally get what they need, the difference is real. 🔥 Less hair in the drain ⚡ Thicker strands that actually hold 💪 New growth in thinning areas 😌 Confidence when you look in the mirror 🧬 Your hair is responding to nutrition, not fighting genetics Your hair did not give up on you. Your diet gave up on your hair. Feed it right and watch what happens 🔥💪 | G79: Feed your follicles what they actually need 🥩 | H79: https://secure.try-forge.com/bridge-a1-simple | I79: Shop now | J79: https://scontent.fsgn5-8.fna.fbcdn.net/v/t39.35426-6/662498160_1823313431683839_1950314760495866572_n.jpg?stp=dst-jpg_s600x600_tt6&_nc_cat=109&ccb=1-7&_nc_sid=c53f8f&_nc_ohc=ooNbad1AsPMQ7kNvwFy8M1z&_nc_oc=AdpOKyuta0pDdO_-spKyjBVp4uho3XLeLzRm9c7sHV8LML9LuLlWA9Z-JD3fM-UcgVk&_nc_zt=14&_nc_ht=scontent.fsgn5-8.fna&_nc_gid=NXq84vVKPOq1xADBe7xB8A&_nc_ss=7a389&oh=00_Af0vjRnYPPWeUx6kwdHOZR2GX0QycJi4VEFWNg1bg1GiVQ&oe=69DAE8F3 | K79: shop.try-forge.com | L79: 768328883041750
A80: 1.2592591e+15 | B80: The Everyday Man | C80: 46113 | D80: Image | E80: Bloated For No Reason? 🫃 | F80: Stomach hurting for no clear reason? Always tired? Nobody talks about this and it explains WAY more than people think. If you deal with stuff like 👇 Random stomach pain or bloating after eating 🤢 Feeling tired even when you sleep enough 😴 Brain fog, low focus, low patience 🧠 Cravings that feel out of control, especially sugar 🍩 Low energy, low drive, low motivation 😐 There's a chance it's not your diet, It's not stress. It could be parasites 😬🦠 You don't need to be dirty, travel the world, or drink bad water. Parasites can come from food, takeout, sushi, pets, vegetables... And they don't just mess with your stomach. They steal nutrients, drain your energy, mess with digestion, and keep your body stuck feeling weak and off. That's why some people eat clean, train, take supplements, and still feel horrible. Here's the part that clicked for me 👇 Parasites survive best when your body is undernourished. Low vitamins, low minerals, weak gut, low immune energy. So instead of just trying to "kill" them, you need to out-feed them 🥩🔥 That's why beef organs make sense. 🥩 Liver refills the vitamins parasites drain first. 🫀 Heart supports real cellular energy, not fake caffeine energy⚡ 🫘 Pancreas helps break down food properly so parasites have less to feed on. 🦴 Bone marrow supports gut repair and immune strength. 🥚 Testicles provide minerals men need for drive and resilience 💪 Once your body is properly fueled, it finally has the strength to push back. It's not magic, it's fixing something that's been quietly draining you. If your gut feels off and nothing makes sense anymore… This might be the missing piece 😮‍💨🔥 | G80: 97% feel a healtheir gut within 10 days ⚡ | H80: https://secure.try-forge.com/bridge-a1-simple | I80: Shop now | J80: https://scontent.fsgn5-12.fna.fbcdn.net/v/t39.35426-6/657182787_2839856706356312_1958000204842437683_n.jpg?stp=dst-jpg_s600x600_tt6&_nc_cat=105&ccb=1-7&_nc_sid=c53f8f&_nc_ohc=i6E37qP5CRsQ7kNvwHlhqyg&_nc_oc=AdpLsVu9iD3r2JsAznPQk8H5oBpXX3WyHFwEyQn4mFtggRe74aie34UphngxGhoVFHA&_nc_zt=14&_nc_ht=scontent.fsgn5-12.fna&_nc_gid=NXq84vVKPOq1xADBe7xB8A&_nc_ss=7a389&oh=00_Af2SuTEtAy9voUGBrxYspqOC5gUT3RoHTxOABR_YGCK4Cg&oe=69DAF684 | K80: shop.try-forge.com | L80: 768328883041750
A81: 1531769355615559 | B81: The Everyday Man | C81: 46108 | D81: Image | E81: My Morning Stiffness Hell | F81: I was diagnosed with rheumatoid arthritis back in 2003. Hard to believe that was over 20 years ago now. From the very beginning, it was rough. But the mornings... God, the mornings were the worst. I'd wake up and my entire body felt like concrete. My fingers wouldn't bend. My knees felt locked in place. It took me 45 minutes just to get out of bed some days. The doctors put me on Enbrel and Methotrexate. Strong medications that were supposed to help with the morning stiffness. And I stayed on them for years. But here's the truth nobody tells you... I was still waking up like the Tin Man every single morning. Locked up. Frozen. Dreading those first movements. My wife would have to help me open pill bottles because my hands were so stiff I couldn't grip anything properly. Five years in, I hit my breaking point. That's when I heard about something called beef organ nutrition. And not some trendy superfood powder from Instagram. I'm talking about the actual organ meats our ancestors ate daily — the nutrients that built strong joints and flexible bodies. So I gave it a shot with something called Forge Beef Organ Complex. And slowly, something incredible happened. Those brutal morning episodes? They started getting shorter. Week by week, I was waking up with less stiffness. Until one morning... I got out of bed and walked straight to the bathroom without shuffling like an old man. No 45-minute warm-up period. No wife helping me open bottles. Just normal movement. Like a human being should move. And I'll tell you this... I've never looked back. Now here's the part most people don't realize: Your joints need the same nutrients your ancestors got from eating organ meats. The synthetic glucosamine at the drugstore? Forget it. Your body barely recognizes it. That's why I only take Forge now. It's the only thing I've found that actually works. 🥩 Beef heart — packed with CoQ10 for cellular energy and circulation 🥩 Beef liver — nature's multivitamin with bioavailable nutrients 🥩 Beef bone marrow — 20X more collagen than bone broth 🥩 Beef pancreas — digestive enzymes for better nutrient absorption 🥩 Beef testicles — testosterone support for muscle strength and recovery No synthetic garbage. No lab-created compounds. Just the same organ nutrition that kept our ancestors moving pain-free their entire lives. It's been part of my daily routine for years now. Two capsules with breakfast. That's it. And honestly? After decades of dreading every morning... These little capsules gave me back my life. If you're still waking up stiff, still taking 30+ minutes to feel human again, still shuffling around like you're 90 years old... Don't wait as long as I did. This changed my mornings and it could change yours too. Click the link below to see if Forge is still in stock. | G81: Finally wakes up normal | H81: https://secure.try-forge.com/bridge-a1-simple | I81: Learn more | J81: https://scontent.fsgn5-12.fna.fbcdn.net/v/t39.35426-6/657063484_934408876249373_7729155368270243478_n.jpg?stp=dst-jpg_s600x600_tt6&_nc_cat=105&ccb=1-7&_nc_sid=c53f8f&_nc_ohc=U-7TdR2ojv0Q7kNvwHVAI1E&_nc_oc=AdqNEi3ppUQS3Ud113pMnhEsF3bKGXLgAeyc0L-naFGzfjJcf69fbCGD7frSapQP9jI&_nc_zt=14&_nc_ht=scontent.fsgn5-12.fna&_nc_gid=NXq84vVKPOq1xADBe7xB8A&_nc_ss=7a389&oh=00_Af1Wihbd7h3hX36qkId3teSLfoBbgiwiabl_XVOrwDTLqw&oe=69DAD652 | K81: shop.try-forge.com | L81: 768328883041750
A82: 1890045068372329 | B82: The Everyday Man | C82: 46113 | D82: Image | E82: Hair Loss Isn't Genetic For Most Men 🧬 | F82: Losing more hair every time you shower? 😬🔥 Before you blame genetics, read this. Most men assume hair loss is locked in their DNA. But new research shows that the majority of early hair thinning in men is driven by nutrient deficiencies, not genetics. Studies published in the Journal of Dermatological Science found that low levels of iron, zinc, biotin, B12, and vitamin A are directly linked to hair follicle shutdown. When these nutrients drop, your follicles literally starve and stop producing new hair 😤 And here is the part that makes it worse. The modern diet is completely stripped of these nutrients. Processed food, synthetic supplements your body barely absorbs, and low quality meat mean your hair follicles have been running on empty for years ⚠️ That is why beef organs work where other "hair supplements" fail 🥩💊 They deliver the exact bioavailable nutrients your follicles are starving for, in a form your body actually recognizes and uses. 🥩 Beef Liver for retinol vitamin A, B12, iron, and biotin that directly fuel hair follicle growth cycles 🫀️ Beef Heart for CoQ10 that improves blood circulation to your scalp and energizes follicle cells 💥 Beef Testicle for zinc, selenium, and peptides that support the hormonal balance behind healthy hair 🫘 Beef Pancreas for digestive enzymes that maximize absorption of every nutrient you take in 🦴 Bone Marrow for collagen, growth factors, and healthy fats that strengthen hair from the root When your follicles finally get what they need, the difference is real. 🔥 Less hair in the drain ⚡ Thicker strands that actually hold 💪 New growth in thinning areas 😌 Confidence when you look in the mirror 🧬 Your hair is responding to nutrition, not fighting genetics Your hair did not give up on you. Your diet gave up on your hair. Feed it right and watch what happens 🔥💪 | G82: Feed your follicles what they actually need 🥩 | H82: https://secure.try-forge.com/bridge-a1-simple | I82: Shop now | J82: https://scontent.fsgn5-3.fna.fbcdn.net/v/t39.35426-6/659597574_1481613703414893_2310962285084286729_n.jpg?stp=dst-jpg_s600x600_tt6&_nc_cat=104&ccb=1-7&_nc_sid=c53f8f&_nc_ohc=x6XEN5dftLAQ7kNvwFtx3Hz&_nc_oc=AdqTJNHJyAyHKEb-c5_c8WqMweC-t5fT45qcSQbFf30pPmG21KI0ZMawY2-JuucfSbY&_nc_zt=14&_nc_ht=scontent.fsgn5-3.fna&_nc_gid=NXq84vVKPOq1xADBe7xB8A&_nc_ss=7a389&oh=00_Af3bYjr56kfvg9INjiCw3-gAh60P7scMEm-IEsu81P1TGA&oe=69DB08A9 | K82: shop.try-forge.com | L82: 768328883041750
A83: 1636508274261393 | B83: The Everyday Man | C83: 46113 | D83: Image | E83: Hair Loss Isn't Genetic For Most Men 🧬 | F83: Losing more hair every time you shower? 😬🔥 Before you blame genetics, read this. Most men assume hair loss is locked in their DNA. But new research shows that the majority of early hair thinning in men is driven by nutrient deficiencies, not genetics. Studies published in the Journal of Dermatological Science found that low levels of iron, zinc, biotin, B12, and vitamin A are directly linked to hair follicle shutdown. When these nutrients drop, your follicles literally starve and stop producing new hair 😤 And here is the part that makes it worse. The modern diet is completely stripped of these nutrients. Processed food, synthetic supplements your body barely absorbs, and low quality meat mean your hair follicles have been running on empty for years ⚠️ That is why beef organs work where other "hair supplements" fail 🥩💊 They deliver the exact bioavailable nutrients your follicles are starving for, in a form your body actually recognizes and uses. 🥩 Beef Liver for retinol vitamin A, B12, iron, and biotin that directly fuel hair follicle growth cycles 🫀️ Beef Heart for CoQ10 that improves blood circulation to your scalp and energizes follicle cells 💥 Beef Testicle for zinc, selenium, and peptides that support the hormonal balance behind healthy hair 🫘 Beef Pancreas for digestive enzymes that maximize absorption of every nutrient you take in 🦴 Bone Marrow for collagen, growth factors, and healthy fats that strengthen hair from the root When your follicles finally get what they need, the difference is real. 🔥 Less hair in the drain ⚡ Thicker strands that actually hold 💪 New growth in thinning areas 😌 Confidence when you look in the mirror 🧬 Your hair is responding to nutrition, not fighting genetics Your hair did not give up on you. Your diet gave up on your hair. Feed it right and watch what happens 🔥💪 | G83: Feed your follicles what they actually need 🥩 | H83: https://secure.try-forge.com/bridge-a1-simple | I83: Shop now | J83: https://scontent.fsgn5-10.fna.fbcdn.net/v/t39.35426-6/658878724_1380140657249660_7045419058120473029_n.jpg?stp=dst-jpg_s600x600_tt6&_nc_cat=107&ccb=1-7&_nc_sid=c53f8f&_nc_ohc=D-mkcPU0_F8Q7kNvwFY4BHW&_nc_oc=AdofRsNd4u6xhnDdj-hbdKo4NWvnRrbFVSPqDO5X0eNeWsSQRZszW_N30ZfkuhJLac4&_nc_zt=14&_nc_ht=scontent.fsgn5-10.fna&_nc_gid=NXq84vVKPOq1xADBe7xB8A&_nc_ss=7a389&oh=00_Af0OhR2DpWe5M2JZ_LeO44gx387how0GnJ7j6r7P85JgAg&oe=69DAF9DF | K83: shop.try-forge.com | L83: 768328883041750
A84: 1461208048654999 | B84: The Everyday Man | C84: 46113 | D84: Image | E84: Hair Loss Isn't Genetic For Most Men 🧬 | F84: Losing more hair every time you shower? 😬🔥 Before you blame genetics, read this. Most men assume hair loss is locked in their DNA. But new research shows that the majority of early hair thinning in men is driven by nutrient deficiencies, not genetics. Studies published in the Journal of Dermatological Science found that low levels of iron, zinc, biotin, B12, and vitamin A are directly linked to hair follicle shutdown. When these nutrients drop, your follicles literally starve and stop producing new hair 😤 And here is the part that makes it worse. The modern diet is completely stripped of these nutrients. Processed food, synthetic supplements your body barely absorbs, and low quality meat mean your hair follicles have been running on empty for years ⚠️ That is why beef organs work where other "hair supplements" fail 🥩💊 They deliver the exact bioavailable nutrients your follicles are starving for, in a form your body actually recognizes and uses. 🥩 Beef Liver for retinol vitamin A, B12, iron, and biotin that directly fuel hair follicle growth cycles 🫀️ Beef Heart for CoQ10 that improves blood circulation to your scalp and energizes follicle cells 💥 Beef Testicle for zinc, selenium, and peptides that support the hormonal balance behind healthy hair 🫘 Beef Pancreas for digestive enzymes that maximize absorption of every nutrient you take in 🦴 Bone Marrow for collagen, growth factors, and healthy fats that strengthen hair from the root When your follicles finally get what they need, the difference is real. 🔥 Less hair in the drain ⚡ Thicker strands that actually hold 💪 New growth in thinning areas 😌 Confidence when you look in the mirror 🧬 Your hair is responding to nutrition, not fighting genetics Your hair did not give up on you. Your diet gave up on your hair. Feed it right and watch what happens 🔥💪 | G84: Feed your follicles what they actually need 🥩 | H84: https://secure.try-forge.com/bridge-a1-simple | I84: Shop now | J84: https://scontent.fsgn5-5.fna.fbcdn.net/v/t39.35426-6/658223792_929488776667592_7164262250079978054_n.jpg?stp=dst-jpg_s600x600_tt6&_nc_cat=100&ccb=1-7&_nc_sid=c53f8f&_nc_ohc=lwk7nXgU7TUQ7kNvwHEi2wG&_nc_oc=AdocT6hsBI2kXYLTnZ701_lrs0UXzJFvzt4YWqLE9HBaW0Qmml1avKdDZ1lCL5BHerg&_nc_zt=14&_nc_ht=scontent.fsgn5-5.fna&_nc_gid=NXq84vVKPOq1xADBe7xB8A&_nc_ss=7a389&oh=00_Af17LHsikReAc9ovtK2_FMlH-4vbFK2r7l0E8SEsonJZ4A&oe=69DADC3E | K84: shop.try-forge.com | L84: 768328883041750
A85: 2.1090107e+15 | B85: The Everyday Man | C85: 46113 | D85: Image | E85: Hair Loss Isn't Genetic For Most Men 🧬 | F85: Losing more hair every time you shower? 😬🔥 Before you blame genetics, read this. Most men assume hair loss is locked in their DNA. But new research shows that the majority of early hair thinning in men is driven by nutrient deficiencies, not genetics. Studies published in the Journal of Dermatological Science found that low levels of iron, zinc, biotin, B12, and vitamin A are directly linked to hair follicle shutdown. When these nutrients drop, your follicles literally starve and stop producing new hair 😤 And here is the part that makes it worse. The modern diet is completely stripped of these nutrients. Processed food, synthetic supplements your body barely absorbs, and low quality meat mean your hair follicles have been running on empty for years ⚠️ That is why beef organs work where other "hair supplements" fail 🥩💊 They deliver the exact bioavailable nutrients your follicles are starving for, in a form your body actually recognizes and uses. 🥩 Beef Liver for retinol vitamin A, B12, iron, and biotin that directly fuel hair follicle growth cycles 🫀️ Beef Heart for CoQ10 that improves blood circulation to your scalp and energizes follicle cells 💥 Beef Testicle for zinc, selenium, and peptides that support the hormonal balance behind healthy hair 🫘 Beef Pancreas for digestive enzymes that maximize absorption of every nutrient you take in 🦴 Bone Marrow for collagen, growth factors, and healthy fats that strengthen hair from the root When your follicles finally get what they need, the difference is real. 🔥 Less hair in the drain ⚡ Thicker strands that actually hold 💪 New growth in thinning areas 😌 Confidence when you look in the mirror 🧬 Your hair is responding to nutrition, not fighting genetics Your hair did not give up on you. Your diet gave up on your hair. Feed it right and watch what happens 🔥💪 | G85: Feed your follicles what they actually need 🥩 | H85: https://secure.try-forge.com/bridge-a1-simple | I85: Shop now | J85: https://scontent.fsgn5-10.fna.fbcdn.net/v/t39.35426-6/659802355_2424044904745008_2023026585656356077_n.jpg?stp=dst-jpg_s600x600_tt6&_nc_cat=106&ccb=1-7&_nc_sid=c53f8f&_nc_ohc=Yj2RQVSSK78Q7kNvwGK7uqp&_nc_oc=AdqmVeuRnm-cTYTEfdZgGhwYkIKOoj_96_DGDOMjSenKK2xOLDXr_SU8OxOHTKS56EY&_nc_zt=14&_nc_ht=scontent.fsgn5-10.fna&_nc_gid=NXq84vVKPOq1xADBe7xB8A&_nc_ss=7a389&oh=00_Af15TS2i4nlszHyrf5hSI16ZOLwhfL8lzmnn6sSVbRcJkg&oe=69DB0975 | K85: shop.try-forge.com | L85: 768328883041750
A86: 1520475836159626 | B86: The Everyday Man | C86: 46108 | D86: Image | E86: Wife Had To Help | F86: I was diagnosed with rheumatoid arthritis back in 2003. Hard to believe that was over 20 years ago now. From the very beginning, it was rough. But the mornings... God, the mornings were the worst. I'd wake up and my entire body felt like concrete. My fingers wouldn't bend. My knees felt locked in place. It took me 45 minutes just to get out of bed some days. The doctors put me on Enbrel and Methotrexate. Strong medications that were supposed to help with the morning stiffness. And I stayed on them for years. But here's the truth nobody tells you... I was still waking up like the Tin Man every single morning. Locked up. Frozen. Dreading those first movements. My wife would have to help me open pill bottles because my hands were so stiff I couldn't grip anything properly. Five years in, I hit my breaking point. That's when I heard about something called beef organ nutrition. And not some trendy superfood powder from Instagram. I'm talking about the actual organ meats our ancestors ate daily — the nutrients that built strong joints and flexible bodies. So I gave it a shot with something called Forge Beef Organ Complex. And slowly, something incredible happened. Those brutal morning episodes? They started getting shorter. Week by week, I was waking up with less stiffness. Until one morning... I got out of bed and walked straight to the bathroom without shuffling like an old man. No 45-minute warm-up period. No wife helping me open bottles. Just normal movement. Like a human being should move. And I'll tell you this... I've never looked back. Now here's the part most people don't realize: Your joints need the same nutrients your ancestors got from eating organ meats. The synthetic glucosamine at the drugstore? Forget it. Your body barely recognizes it. That's why I only take Forge now. It's the only thing I've found that actually works. 🥩 Beef heart — packed with CoQ10 for cellular energy and circulation 🥩 Beef liver — nature's multivitamin with bioavailable nutrients 🥩 Beef bone marrow — 20X more collagen than bone broth 🥩 Beef pancreas — digestive enzymes for better nutrient absorption 🥩 Beef testicles — testosterone support for muscle strength and recovery No synthetic garbage. No lab-created compounds. Just the same organ nutrition that kept our ancestors moving pain-free their entire lives. It's been part of my daily routine for years now. Two capsules with breakfast. That's it. And honestly? After decades of dreading every morning... These little capsules gave me back my life. If you're still waking up stiff, still taking 30+ minutes to feel human again, still shuffling around like you're 90 years old... Don't wait as long as I did. This changed my mornings and it could change yours too. Click the link below to see if Forge is still in stock. | G86: Thousands feel the difference | H86: https://secure.try-forge.com/bridge-a1-simple | I86: Learn more | J86: https://scontent.fsgn5-11.fna.fbcdn.net/v/t39.35426-6/656378315_1232419428877153_2755353446569242293_n.jpg?stp=dst-jpg_s600x600_tt6&_nc_cat=111&ccb=1-7&_nc_sid=c53f8f&_nc_ohc=0gNq-CPLa-AQ7kNvwECPddl&_nc_oc=AdqB0Gx_5a-129V0_wiIoM45iDHIyFBhvCfUGhxPRAtWzlEvZ1WdXsS8OMt9NI8Gky8&_nc_zt=14&_nc_ht=scontent.fsgn5-11.fna&_nc_gid=hM6-4k5bVws8_HCiHdUQGA&_nc_ss=7a389&oh=00_Af0w0KlUirzaDph66LNkudEtpmxX2zXdvmQ0C39WiujyOw&oe=69DAFF48 | K86: shop.try-forge.com | L86: 768328883041750
A87: 810391341508856 | B87: The Everyday Man | C87: 46108 | D87: Image | E87: 45 Minutes Just Standing | F87: I was diagnosed with rheumatoid arthritis back in 2003. Hard to believe that was over 20 years ago now. From the very beginning, it was rough. But the mornings... God, the mornings were the worst. I'd wake up and my entire body felt like concrete. My fingers wouldn't bend. My knees felt locked in place. It took me 45 minutes just to get out of bed some days. The doctors put me on Enbrel and Methotrexate. Strong medications that were supposed to help with the morning stiffness. And I stayed on them for years. But here's the truth nobody tells you... I was still waking up like the Tin Man every single morning. Locked up. Frozen. Dreading those first movements. My wife would have to help me open pill bottles because my hands were so stiff I couldn't grip anything properly. Five years in, I hit my breaking point. That's when I heard about something called beef organ nutrition. And not some trendy superfood powder from Instagram. I'm talking about the actual organ meats our ancestors ate daily — the nutrients that built strong joints and flexible bodies. So I gave it a shot with something called Forge Beef Organ Complex. And slowly, something incredible happened. Those brutal morning episodes? They started getting shorter. Week by week, I was waking up with less stiffness. Until one morning... I got out of bed and walked straight to the bathroom without shuffling like an old man. No 45-minute warm-up period. No wife helping me open bottles. Just normal movement. Like a human being should move. And I'll tell you this... I've never looked back. Now here's the part most people don't realize: Your joints need the same nutrients your ancestors got from eating organ meats. The synthetic glucosamine at the drugstore? Forget it. Your body barely recognizes it. That's why I only take Forge now. It's the only thing I've found that actually works. 🥩 Beef heart — packed with CoQ10 for cellular energy and circulation 🥩 Beef liver — nature's multivitamin with bioavailable nutrients 🥩 Beef bone marrow — 20X more collagen than bone broth 🥩 Beef pancreas — digestive enzymes for better nutrient absorption 🥩 Beef testicles — testosterone support for muscle strength and recovery No synthetic garbage. No lab-created compounds. Just the same organ nutrition that kept our ancestors moving pain-free their entire lives. It's been part of my daily routine for years now. Two capsules with breakfast. That's it. And honestly? After decades of dreading every morning... These little capsules gave me back my life. If you're still waking up stiff, still taking 30+ minutes to feel human again, still shuffling around like you're 90 years old... Don't wait as long as I did. This changed my mornings and it could change yours too. Click the link below to see if Forge is still in stock. | G87: See the organ solution | H87: https://secure.try-forge.com/bridge-a1-simple | I87: Learn more | J87: https://scontent.fsgn5-5.fna.fbcdn.net/v/t39.35426-6/657788901_752052894510942_2263491665577121471_n.jpg?stp=dst-jpg_s600x600_tt6&_nc_cat=108&ccb=1-7&_nc_sid=c53f8f&_nc_ohc=Ih0YKPrCv5UQ7kNvwELQnrb&_nc_oc=Adqk4IGLoq4Kl12-MWmDtK7LOZL91oE8vYwNjev8EKgpkVR-dxFQWeAasMpieHOBaC0&_nc_zt=14&_nc_ht=scontent.fsgn5-5.fna&_nc_gid=hM6-4k5bVws8_HCiHdUQGA&_nc_ss=7a389&oh=00_Af3bMxxa_kP0ryVapLhEWPposH5_1EnOFQQ9itvPUq9Abg&oe=69DAED76 | K87: shop.try-forge.com | L87: 768328883041750
A88: 1310594614462425 | B88: Better Performance | C88: 46099 | D88: Image | E88: Why Cattle Ranchers Never Go Bald | F88: A Montana rancher just made every hair loss clinic in America look like idiots. He's never spent a dime on treatments. David Kern is 54 years old. He runs a 3,000-acre ranch outside Billings, Montana. Last year, his daughter posted a photo of him on Facebook. Within an hour, 47 people commented asking about his hair. Not because it looked good for his age. Because it looked better than most 30-year-olds. Thick. Full. Zero bald spots. Barely any gray. One comment stood out: "Bro, what clinic did you go to? I've spent $15K on treatments and I'm still thinning." David's response: "I've never been to a hair clinic in my life." The guy didn't believe him. Accused him of hair plugs. Propecia. Something. So David posted a throwback photo from when he was 38. Receding hairline. Thinning crown. Classic male pattern baldness starting to take over. Then a photo at 45. Even worse. Then one at 50. Thicker than at 38. Then the recent one at 54. Fullest it's been since his 20s. The comment section exploded. What Changed? David Started Processing His Own Beef. The Nutrient Deficiency That's Actually Causing Your Hair Loss Here's what David's dermatologist told him when he was 38 and starting to go bald: "It's genetic. DHT sensitivity. Nothing you can do except Propecia or accept it." That's what they tell everyone. And it's half true. Yes, DHT (a testosterone byproduct) miniaturizes hair follicles in genetically susceptible men. But here's what they don't tell you: Your follicles only become DHT-sensitive when they're starving for specific nutrients. Specifically: Retinol, Biotin, and Folate in their bioavailable forms. Not the synthetic versions in your overpriced hair vitamins. The real versions. Found almost exclusively in organ meat. When David started processing his own cattle at 42, he did what his grandfather did: He ate the organs. Liver twice a week. Heart on Sundays. Kidney in stew. Not for his hair. He didn't even make the connection. He did it because that's what ranchers do. You don't waste the animal. Six months later, his wife noticed his crown looked fuller. A year later, his hairline had stopped receding. By age 50, barbers were commenting on how thick his hair was. At 54? People half his age ask him for advice. Why Hair Clinics Don't Want You to Know This A university research team heard about David's case and got curious. They tested 63 ranchers across Montana and Wyoming, ages 45-60. Men who process their own beef. Who eat nose-to-tail. The results shocked them: Only 11% showed significant hair thinning or baldness. Compare that to the general population of men that age: 53% show moderate to severe hair loss. Same genetics. Same age range. Same DHT levels. Completely different outcomes. The researchers dug into their diets. Every single rancher with a full head of hair ate organ meat at least twice a week. The 11% who were thinning? They'd stopped eating organs years ago. Switched to muscle meat only because their wives thought liver was "gross." The pattern was undeniable. The Biological Truth About Hair Follicles (That Your Doctor Never Learned) Your hair follicles are some of the fastest-growing cells in your body. That means they're metabolically expensive. They need constant fuel. Specifically, they need: Preformed Vitamin A (Retinol) - Regulates sebum production and keeps follicles from becoming brittle and DHT-sensitive. Bioavailable B-Vitamins - Particularly B12 and Folate, which drive cellular division in the follicle bulb. Heme Iron - Oxygenates follicle cells. Without it, they literally suffocate and die. Copper and Zinc in proper ratio - Copper builds the keratin structure. Zinc regulates the hormonal signals that tell follicles to grow. You cannot get adequate amounts of these from a multivitamin. You can't get them from chicken and rice. You can't even get them from grass-fed steak. You get them from organ meat. One serving of beef liver contains: 16,000 IU of retinol (your hair follicles are screaming for this) 1,400% of your B12 requirement 12mg of heme iron in the most bioavailable form Perfectly balanced copper and zinc Your $60 "hair growth" supplement contains synthetic versions your body barely recognizes and mostly pisses out. Why the Hair Loss Industry Is Built on a Lie If men knew that eating liver twice a week could stop hair loss... You wouldn't need their $200/month finasteride prescriptions. You wouldn't need their $8,000 PRP treatments. You wouldn't need their $15,000 hair transplant surgeries. The hair loss industry makes $4.8 billion per year convincing you that only drugs and procedures can save your hair. They can't. Propecia blocks DHT, but it also blocks testosterone conversion. Your hair might thicken, but your dick stops working and your energy crashes. Minoxidil irritates your scalp into forcing blood flow. The moment you stop using it, everything you gained falls out. Hair transplants move hair from the back of your head to the front. But if you're still nutrient-deficient, the transplanted follicles weaken and thin out too. None of these address the root cause: Your follicles are starving. What Happens When You Finally Feed Your Follicles The research team had 18 men with moderate hair thinning add organ meat to their diets. Beef liver twice a week. Heart once a week. No Propecia. No minoxidil. No procedures. After 6 months: Hair density increased by an average of 23%. Shedding decreased by 41%. Sebum production normalized (less oily scalp, less dandruff). One participant went from a Norwood 3 (visible thinning) to a Norwood 1.5 (minimal recession). His dermatologist accused him of secretly using finasteride. He wasn't. He was just eating food. The same food humans thrived on for 200,000 years before Bosley and Rogaine rewrote the rules. The Evolutionary Truth About Male Hair Loss For 2 million years, men ate the entire animal. Hunters claimed the organs first. Muscle meat was secondary. The liver for vitality and hormone regulation. The heart for stamina and blood flow. The kidney for mineral balance and detoxification. And their hair stayed thick well into old age. There's a reason every indigenous culture that ate nose-to-tail had full heads of hair even in their 60s and 70s. It wasn't genetics. It was nutrition. Your body is designed to have a full head of hair. Hair loss isn't genetic destiny. It's a nutrient deficiency signal. Feed your follicles what they're starving for, and they'll do what they're designed to do: grow. The Modern Man's Problem (And How We Solved It) Here's the issue: You're not going to buy liver at the butcher every week. You're not going to cook it. You're not going to eat it. Even if you know it's the answer, you're not doing it. It's expensive. Hard to find. Tastes like death if you didn't grow up eating it. That's exactly why this exists. Introducing Forge Men's Beef Organ Complex Grass-fed beef organs from Argentina. Freeze-dried to preserve every nutrient. Liver for retinol and B-vitamins. Heart for heme iron and CoQ10. Kidney for bioavailable copper and selenium. Two capsules a day. No cooking. No taste. No excuses. Just the same nutrition that gives 54-year-old ranchers thicker hair than their 28-year-old sons. What Happens When Your Follicles Finally Get What They Need Within the first month: Shedding slows. You stop seeing clumps in the shower drain. Your scalp feels healthier. Less oily. Less inflamed. Within two months: Existing hair feels thicker, stronger. Easier to style. Vellus hairs (the tiny colorless ones) start darkening and thickening. Within three to six months: Hairline stabilizes. The recession stops. Crown fills in. The "bald spot" gets smaller. Barbers start commenting that your hair looks different. Within a year: You look like a younger version of yourself. Not because of drugs. Because you finally gave your body what it's been starving for. But You Need to Understand Something Critical Do NOT buy random organ supplements off Amazon. Most are garbage. Grain-fed beef from factory farms. High-heat processing that destroys heat-sensitive nutrients like retinol. Capsules cut with rice flour and minimal actual organ content. They write "grass-fed" on the label and hope you don't investigate. What Makes Forge Men Different 100% grass-fed, grass-finished beef from regenerative farms in Argentina. Freeze-dried at low temperatures to preserve every heat-sensitive nutrient. No fillers. No flow agents. No bullshit. Just pure, bioavailable organ nutrition. The same food that stopped David Kern's hair loss and reversed it. The same nutrition that kept 89% of those ranchers from going bald. Now in capsule form. Here's the Deal Forge Men is offering a 90-day guarantee. Take the Beef Organ Complex for three full months. If your hair doesn't feel thicker, if the shedding doesn't slow, if you don't see improvement... send it back for a full refund. But I need to warn you: Forge Men is a small operation. They source only from regenerative farms. They refuse to scale at the expense of quality. Their last restock sold out in 36 hours. If you click and they're out of stock, I'm sorry. It happens. If you see them in stock, don't wait. A 54-Year-Old Rancher Has More Hair Than You. Not because of genetics. Not because of Propecia or PRP or transplants. Because he eats organ meat. The food your doctor never mentioned. The food the hair loss industry prays you never discover. Now you can take back what's yours. ⬇️Click below and give your follicles the nutrition evolution designed them to have.⬇️ | G88: Your doctor knows organ meats are nature’s multivitamin. But they’ll never prescribe them.Heart. Liver. Testicles. Kidney. Bone Marrow. The same nutrients medical textbooks call “nutritional gold” — now in capsule form. | H88: https://secure.try-forge.com/bridge-a1-simple | I88: Learn more | J88: https://scontent.fsgn5-5.fna.fbcdn.net/v/t39.35426-6/654296439_3325891080951039_4812675163920356003_n.jpg?stp=dst-jpg_s600x600_tt6&_nc_cat=108&ccb=1-7&_nc_sid=c53f8f&_nc_ohc=EPr7QpLyVDIQ7kNvwF_nW2v&_nc_oc=Adr7Xl0uxinkLv5yvJ3szCqBcpukr6rBKV-e09omJSWNFOHC3-xfe8Z1KmKMg8Wd3ms&_nc_zt=14&_nc_ht=scontent.fsgn5-5.fna&_nc_gid=5suOildPrctzIWzjVlT1Eg&_nc_ss=7a389&oh=00_Af32QnbZWfwjihCxlJtMNlHa3ln14oN4GHOnlLT9RqMvMw&oe=69DADDD9 | K88: shop.try-forge.com | L88: 892916470563125
A89: 923107313654129 | B89: Better Performance | C89: 46099 | D89: Image | E89: Why Cattle Ranchers Never Go Bald | F89: A Montana rancher just made every hair loss clinic in America look like idiots. He's never spent a dime on treatments. David Kern is 54 years old. He runs a 3,000-acre ranch outside Billings, Montana. Last year, his daughter posted a photo of him on Facebook. Within an hour, 47 people commented asking about his hair. Not because it looked good for his age. Because it looked better than most 30-year-olds. Thick. Full. Zero bald spots. Barely any gray. One comment stood out: "Bro, what clinic did you go to? I've spent $15K on treatments and I'm still thinning." David's response: "I've never been to a hair clinic in my life." The guy didn't believe him. Accused him of hair plugs. Propecia. Something. So David posted a throwback photo from when he was 38. Receding hairline. Thinning crown. Classic male pattern baldness starting to take over. Then a photo at 45. Even worse. Then one at 50. Thicker than at 38. Then the recent one at 54. Fullest it's been since his 20s. The comment section exploded. What Changed? David Started Processing His Own Beef. The Nutrient Deficiency That's Actually Causing Your Hair Loss Here's what David's dermatologist told him when he was 38 and starting to go bald: "It's genetic. DHT sensitivity. Nothing you can do except Propecia or accept it." That's what they tell everyone. And it's half true. Yes, DHT (a testosterone byproduct) miniaturizes hair follicles in genetically susceptible men. But here's what they don't tell you: Your follicles only become DHT-sensitive when they're starving for specific nutrients. Specifically: Retinol, Biotin, and Folate in their bioavailable forms. Not the synthetic versions in your overpriced hair vitamins. The real versions. Found almost exclusively in organ meat. When David started processing his own cattle at 42, he did what his grandfather did: He ate the organs. Liver twice a week. Heart on Sundays. Kidney in stew. Not for his hair. He didn't even make the connection. He did it because that's what ranchers do. You don't waste the animal. Six months later, his wife noticed his crown looked fuller. A year later, his hairline had stopped receding. By age 50, barbers were commenting on how thick his hair was. At 54? People half his age ask him for advice. Why Hair Clinics Don't Want You to Know This A university research team heard about David's case and got curious. They tested 63 ranchers across Montana and Wyoming, ages 45-60. Men who process their own beef. Who eat nose-to-tail. The results shocked them: Only 11% showed significant hair thinning or baldness. Compare that to the general population of men that age: 53% show moderate to severe hair loss. Same genetics. Same age range. Same DHT levels. Completely different outcomes. The researchers dug into their diets. Every single rancher with a full head of hair ate organ meat at least twice a week. The 11% who were thinning? They'd stopped eating organs years ago. Switched to muscle meat only because their wives thought liver was "gross." The pattern was undeniable. The Biological Truth About Hair Follicles (That Your Doctor Never Learned) Your hair follicles are some of the fastest-growing cells in your body. That means they're metabolically expensive. They need constant fuel. Specifically, they need: Preformed Vitamin A (Retinol) - Regulates sebum production and keeps follicles from becoming brittle and DHT-sensitive. Bioavailable B-Vitamins - Particularly B12 and Folate, which drive cellular division in the follicle bulb. Heme Iron - Oxygenates follicle cells. Without it, they literally suffocate and die. Copper and Zinc in proper ratio - Copper builds the keratin structure. Zinc regulates the hormonal signals that tell follicles to grow. You cannot get adequate amounts of these from a multivitamin. You can't get them from chicken and rice. You can't even get them from grass-fed steak. You get them from organ meat. One serving of beef liver contains: 16,000 IU of retinol (your hair follicles are screaming for this) 1,400% of your B12 requirement 12mg of heme iron in the most bioavailable form Perfectly balanced copper and zinc Your $60 "hair growth" supplement contains synthetic versions your body barely recognizes and mostly pisses out. Why the Hair Loss Industry Is Built on a Lie If men knew that eating liver twice a week could stop hair loss... You wouldn't need their $200/month finasteride prescriptions. You wouldn't need their $8,000 PRP treatments. You wouldn't need their $15,000 hair transplant surgeries. The hair loss industry makes $4.8 billion per year convincing you that only drugs and procedures can save your hair. They can't. Propecia blocks DHT, but it also blocks testosterone conversion. Your hair might thicken, but your dick stops working and your energy crashes. Minoxidil irritates your scalp into forcing blood flow. The moment you stop using it, everything you gained falls out. Hair transplants move hair from the back of your head to the front. But if you're still nutrient-deficient, the transplanted follicles weaken and thin out too. None of these address the root cause: Your follicles are starving. What Happens When You Finally Feed Your Follicles The research team had 18 men with moderate hair thinning add organ meat to their diets. Beef liver twice a week. Heart once a week. No Propecia. No minoxidil. No procedures. After 6 months: Hair density increased by an average of 23%. Shedding decreased by 41%. Sebum production normalized (less oily scalp, less dandruff). One participant went from a Norwood 3 (visible thinning) to a Norwood 1.5 (minimal recession). His dermatologist accused him of secretly using finasteride. He wasn't. He was just eating food. The same food humans thrived on for 200,000 years before Bosley and Rogaine rewrote the rules. The Evolutionary Truth About Male Hair Loss For 2 million years, men ate the entire animal. Hunters claimed the organs first. Muscle meat was secondary. The liver for vitality and hormone regulation. The heart for stamina and blood flow. The kidney for mineral balance and detoxification. And their hair stayed thick well into old age. There's a reason every indigenous culture that ate nose-to-tail had full heads of hair even in their 60s and 70s. It wasn't genetics. It was nutrition. Your body is designed to have a full head of hair. Hair loss isn't genetic destiny. It's a nutrient deficiency signal. Feed your follicles what they're starving for, and they'll do what they're designed to do: grow. The Modern Man's Problem (And How We Solved It) Here's the issue: You're not going to buy liver at the butcher every week. You're not going to cook it. You're not going to eat it. Even if you know it's the answer, you're not doing it. It's expensive. Hard to find. Tastes like death if you didn't grow up eating it. That's exactly why this exists. Introducing Forge Men's Beef Organ Complex Grass-fed beef organs from Argentina. Freeze-dried to preserve every nutrient. Liver for retinol and B-vitamins. Heart for heme iron and CoQ10. Kidney for bioavailable copper and selenium. Two capsules a day. No cooking. No taste. No excuses. Just the same nutrition that gives 54-year-old ranchers thicker hair than their 28-year-old sons. What Happens When Your Follicles Finally Get What They Need Within the first month: Shedding slows. You stop seeing clumps in the shower drain. Your scalp feels healthier. Less oily. Less inflamed. Within two months: Existing hair feels thicker, stronger. Easier to style. Vellus hairs (the tiny colorless ones) start darkening and thickening. Within three to six months: Hairline stabilizes. The recession stops. Crown fills in. The "bald spot" gets smaller. Barbers start commenting that your hair looks different. Within a year: You look like a younger version of yourself. Not because of drugs. Because you finally gave your body what it's been starving for. But You Need to Understand Something Critical Do NOT buy random organ supplements off Amazon. Most are garbage. Grain-fed beef from factory farms. High-heat processing that destroys heat-sensitive nutrients like retinol. Capsules cut with rice flour and minimal actual organ content. They write "grass-fed" on the label and hope you don't investigate. What Makes Forge Men Different 100% grass-fed, grass-finished beef from regenerative farms in Argentina. Freeze-dried at low temperatures to preserve every heat-sensitive nutrient. No fillers. No flow agents. No bullshit. Just pure, bioavailable organ nutrition. The same food that stopped David Kern's hair loss and reversed it. The same nutrition that kept 89% of those ranchers from going bald. Now in capsule form. Here's the Deal Forge Men is offering a 90-day guarantee. Take the Beef Organ Complex for three full months. If your hair doesn't feel thicker, if the shedding doesn't slow, if you don't see improvement... send it back for a full refund. But I need to warn you: Forge Men is a small operation. They source only from regenerative farms. They refuse to scale at the expense of quality. Their last restock sold out in 36 hours. If you click and they're out of stock, I'm sorry. It happens. If you see them in stock, don't wait. A 54-Year-Old Rancher Has More Hair Than You. Not because of genetics. Not because of Propecia or PRP or transplants. Because he eats organ meat. The food your doctor never mentioned. The food the hair loss industry prays you never discover. Now you can take back what's yours. ⬇️Click below and give your follicles the nutrition evolution designed them to have.⬇️ | G89: Your doctor knows organ meats are nature’s multivitamin. But they’ll never prescribe them.Heart. Liver. Testicles. Kidney. Bone Marrow. The same nutrients medical textbooks call “nutritional gold” — now in capsule form. | H89: https://secure.try-forge.com/bridge-a1-simple | I89: Learn more | J89: https://scontent.fsgn5-10.fna.fbcdn.net/v/t39.35426-6/653709869_1443629240874823_2308788871468420547_n.jpg?stp=dst-jpg_s600x600_tt6&_nc_cat=107&ccb=1-7&_nc_sid=c53f8f&_nc_ohc=ADe3NeVrfLIQ7kNvwECNwGy&_nc_oc=Adoxb-Oauuc05kYer_uAxtn_KE0mdPF3qEwfJv44oG0IewJ2NMvej9XETBpaT8q2VxA&_nc_zt=14&_nc_ht=scontent.fsgn5-10.fna&_nc_gid=5suOildPrctzIWzjVlT1Eg&_nc_ss=7a389&oh=00_Af3ZKOeqjVr4gRXG-i7pwIGAAvgK29prSlkLV5v554HN1g&oe=69DAD734 | K89: shop.try-forge.com | L89: 892916470563125
